Workbook

Sheet Inputs
B2: Project Assumption | F2: Project Execution timeline | I2: Financial Assumptions
B3: Total number of pallet position | C3: # | D3: 8928 | F3: Start Date | G3: 45566 | I3: Company Name | J3: PPGPL | L3: Assumption List
B4: Project Life | D4: 15 | F4: # of months | G4: 14 | I4: Cost of Capital | J4: =J6*9.5%*(1-J5)+J7*20% -> 0.0710904 | L4: Sr. No. | M4: Parameters | N4: Value | O4: UOM | P4: Remarks
F5: End Date | G5: =EOMONTH(G3,G4-1) -> 45991 | I5: Tax Rate | J5: =22%*(1+4%)*(1+10%) -> 0.25168 | L5: A | M5: Project
B6: Charges to the customer | F6: End of Project | G6: =EOMONTH(G5,D4*12)+1 -> 51471 | I6: Debt | J6: 1 | L6: 1 | M6: Project life | N6: =D4 -> 15 | O6: years
B7: Security Deposit from consumer | C7: months | D7: 3 | I7: Equity | J7: =MAX(1-J6,0.0000000001%) -> 1e-12 | L7: 2 | M7: Number of pallet position | N7: =D3 -> 8928 | O7: # | P7: Based on current planning
B8: Storage Utilisation | C8: % | D8: ='Warehouse Inventory '!I18 -> 0.83990912 | L8: 3 | M8: Rent per pallet per day | N8: =D10 -> 67.827523 | O8: Rs./day/pallet | P8: In reference to Radiant and Kothur warehouse rentals
B9: Markup from market cost | D9: 0.15 | L9: 4 | M9: Term of rent agreement | N9: =D12 -> 7 | O9: years
B10: Rent per pallet per day | C10: Rs./pallet/day | D10: =D22*(1+D9) -> 67.827523 | L10: 5 | M10: Storage duration of each pallet | N10: =D8 -> 0.83990912 | O10: days | P10: Material will be outbound within this days
B11: Escalation | C11: every year | D11: 0.05 | L11: 6 | M11: Inventory Turnover | N11: =D13 -> 0 | O11: times
B12: Rent renewal/Term of agreement | C12: every ___ years | D12: 7 | L12: 7 | M12: Start of Project Execution | N12: =G3 -> 45566
L13: 8 | M13: End of Project Execution | N13: =G5 -> 45991
L14: 9 | M14: Land | P14: As per the land lease rental of HSTL <> PEPPL Gas yard and Kothur lease rental
L15: a | M15: Total land required | N15: ='Project Expenses'!F36 -> 248396 | O15: sq. ft. | P15: As per the diagram
B16: Returns | L16: b | M16: Land lease rental | N16: ='Project Expenses'!F37 -> 16 | O16: Rs./sq. ft./month
B17: IRR | C17: =IRR!C24 -> 0.13098165 | D17: % | L17: c | M17: Security deposit on land | N17: 3 | O17: months
B18: NPV | C18: =IRR!C25 -> 66.396621 | D18: crore | L18: d | M18: Term of land rental | N18: 7 | O18: years
B19: Payback period | C19: =IRR!C26 -> 5.1618635 | D19: years | L19: e | M19: Escalation
B20: ROCE-Post Tax | C20: =IRR!C28 -> 0.35581103 | D20: % | E20: =1/C20 -> 2.8104806 | M20: Yr 1 | N20: 0 | O20: %
M21: Yr 2 | N21: 0 | O21: %
B22: Warehousing cost | C22: =C10 -> Rs./pallet/day | D22: =F47 -> 58.980455 | M22: Yr 3 | N22: 0.05 | O22: %
M23: Yr 4 | N23: 0.05 | O23: %
M24: Yr 5 | N24: 0.05 | O24: %
B25: Warehouse | D25: Area (Sqft) | E25: Rate/Sqft | F25: Rent per month | G25: Storage Capacity (Pallets) | H25: Rate/Pallet | I25: Rate per pallet per day | M25: Yr 6 | N25: 0.05 | O25: %
B26: Kothur | D26: ='Kothur Reference'!C2 -> 261597.18 | E26: ='Kothur Reference'!C6 -> 23 | F26: ='Kothur Reference'!C7 -> 7099747.5 | G26: ='Kothur Reference'!C3 -> 9354.8387 | H26: =F26/G26 -> 758.93852 | I26: =H26/30 -> 25.297951 | M26: Yr 7 | N26: 0.05 | O26: %
B27: Radiant | D27: ='Radiant Reference'!C2 -> 71858 | E27: ='Radiant Reference'!C6 -> 22 | F27: ='Radiant Reference'!C7 -> 1865433.7 | G27: ='Radiant Reference'!C3 -> 2902.9032 | H27: =F27/G27 -> 642.60967 | I27: =H27/30 -> 21.420322 | L27: B | M27: Financial
B28: Weighted Average | D28: =SUM(D26:D27) -> 333455.18 | E28: =F28/D28 -> 26.885716 | F28: =SUM(F26:F27) -> 8965181.1 | G28: =SUM(G26:G27) -> 12257.742 | H28: =F28/G28 -> 731.38929 | I28: =H28/30 -> 24.379643 | L28: 1 | M28: Total project cost | N28: ='Project Cost Details'!G35/10^7 -> 54.166044 | O28: Rs. Crore
B29: Transportation Cost to be factored (factory to Kottur) | F29: ='Kothur Reference'!C42/12 -> 5162500 | H29: =F29/G26 -> 551.85345 | I29: =F29/G26/30 -> 18.395115 | L29: a | M29: Debt | N29: ='Project Cost Details'!G38/10^7 -> 54.166044 | O29: Rs. Crore
B30: Transportation Cost to be factored (factory to Radiant) | F30: ='Radiant Reference'!C42/12 -> 171100 | H30: =F30/G27 -> 58.940993 | I30: =F30/G27/30 -> 1.9646998 | L30: b | M30: Equity | N30: ='Project Cost Details'!G39/10^7 -> 5.4166044e-11 | O30: Rs. Crore
B31: Storages Charges cost per pallet | H31: =H28+H29+H30 -> 1342.1837 | I31: =I28+I29+I30 -> 44.739458 | L31: 2 | M31: WACC | N31: =J4 -> 0.0710904 | O31: %
B32: Operational Charges | L32: 3 | M32: Tax Rate | N32: =J5 -> 0.25168 | O32: %
B33: Manpower | D33: =D36 -> 333455.18 | E33: =F33/D33 -> 2.2101921 | F33: =(('Radiant Reference'!E19)+'Kothur Reference'!E19)/12 -> 737000 | G33: =G28 -> 12257.742 | H33: =F33/G33 -> 60.125266 | I33: =H33/30 -> 2.0041755 | L33: 4 | M33: Depreciation term | N33: ='Project Expenses'!C51 -> 7.5 | O33: years
B34: IT assets | D34: =D33 -> 333455.18 | E34: =F34/D34 -> 0.088967479 | F34: =('Radiant Reference'!E26+'Kothur Reference'!E26)/12 -> 29666.667 | G34: =G33 -> 12257.742 | H34: =F34/G34 -> 2.4202391 | I34: =H34/30 -> 0.080674638
B35: Machineries | D35: =D34 -> 333455.18 | E35: =F35/D35 -> 4.3433798 | F35: =('Radiant Reference'!E32+'Kothur Reference'!E32)/12 -> 1448322.5 | G35: =G34 -> 12257.742 | H35: =F35/G35 -> 118.15573 | I35: =H35/30 -> 3.9385245
B36: Total Operational charges per pallet | D36: =D28 -> 333455.18 | E36: =F36/D36 -> 6.6425394 | F36: =SUM(F33:F35) -> 2214989.2 | G36: =G28 -> 12257.742 | H36: =F36/G36 -> 180.70124 | I36: =H36/30 -> 6.0233747
B37: Markup @ 15% | F37: =D9 -> 0.15 | H37: =(H31+H36)*15% -> 228.43275 | I37: =(I31+I36)*F37 -> 7.6144248
B38: Gajwel charges per pallet per day | H38: =H31+H37+H36 -> 1751.3177 | I38: =I31+I37+I36 -> 58.377257
B39: No of pallets capacity | I39: =D3 -> 8928 | P39: =5000*7 -> 35000
B40: Occupancy | H40: ='Warehouse Inventory '!I18 -> 0.83990912 | I40: =I39*H40 -> 7498.7086
B41: Revenue to Gajwel per annum | D41: 6696*49.93*365 | H41: Rs in Crs | I41: =(I38*I40*365)/10^7 -> 15.978023
B44: Warehouse | C44: Average daily rental per pallet | D44: Total max pallet | E44: Total Cost | F44: Average cost per pallet per day
B45: Kothur | C45: ='Kothur Reference'!X63 -> 67.409817 | D45: ='Kothur Reference'!C3 -> 9354.8387 | E45: =C45*D45*365 -> 2.3017191e+08
B46: Radiant | C46: ='Radiant Reference'!Y62 -> 31.816157 | D46: ='Radiant Reference'!C3 -> 2902.9032 | E46: =C46*D46*365 -> 33711117
B47: Net | D47: =D45+D46 -> 12257.742 | E47: =SUM(E45:E46) -> 2.6388302e+08 | F47: =E47/D47/365 -> 58.980455
B64: Expense Parameter | C64: Radiant Warehouse (Rs. Cr.) | D64: Kothur Warehouse (Rs. Cr.)
B65: Lease cost
B66: Lease Rent | C66: ='Radiant Reference'!C46 -> 2.2385204 | D66: ='Kothur Reference'!C46 -> 8.519697
B67: Security Deposit | C67: ='Radiant Reference'!C8/10^7 -> 0.5596301 | D67: ='Kothur Reference'!C47 -> 2.1299242
B68: Total Lease Cost | C68: =C66+C67 -> 2.7981505 | D68: ='Kothur Reference'!C48 -> 10.649621
B69: Add: Operational cost
B70: Electricity | C70: ='Radiant Reference'!C49 -> 0.034392 | D70: ='Kothur Reference'!C49 -> 0.034392
B71: Manpower | C71: ='Radiant Reference'!C50 -> 0.2652 | D71: ='Kothur Reference'!C50 -> 0.6192
B72: IT Costs | C72: ='Radiant Reference'!C51 -> 0.0178 | D72: ='Kothur Reference'!C51 -> 0.0178
B73: Machinery & Equipment | C73: ='Radiant Reference'!C52 -> 0.54930238 | D73: ='Kothur Reference'!C52 -> 1.6225583
B74: Transport Cost | C74: ='Radiant Reference'!C53 -> 0.20532 | D74: ='Kothur Reference'!C53 -> 6.195
B75: Total Cost | C75: =SUM(C68:C74) -> 3.8701649 | D75: =SUM(D68:D74) -> 19.138572

Sheet IRR
B2: Type | C2: =IF(C4<=Inputs!$G$5,"Cons","Beyond Cons") -> Cons | D2: =IF(D4<=Inputs!$G$5,"Cons","Beyond Cons") -> Cons | E2: =IF(E4<=Inputs!$G$5,"Cons","Beyond Cons") -> Cons | F2: =IF(F4<=Inputs!$G$5,"Cons","Beyond Cons") -> Cons | G2: =IF(G4<=Inputs!$G$5,"Cons","Beyond Cons") -> Cons | H2: =IF(H4<=Inputs!$G$5,"Cons","Beyond Cons") -> Cons | I2: =IF(I4<=Inputs!$G$5,"Cons","Beyond Cons") -> Cons | J2: =IF(J4<=Inputs!$G$5,"Cons","Beyond Cons") -> Cons | ... BA2: =IF(BA4<=Inputs!$G$5,"Cons","Beyond Cons") -> Beyond Cons
B3: Start Month | C3: =Inputs!G3 -> 45566 | D3: =IFERROR(IF(C4+1<Inputs!$G$6,C4+1,"-"),"-") -> 45597 | E3: =IFERROR(IF(D4+1<Inputs!$G$6,D4+1,"-"),"-") -> 45627 | F3: =IFERROR(IF(E4+1<Inputs!$G$6,E4+1,"-"),"-") -> 45658 | G3: =IFERROR(IF(F4+1<Inputs!$G$6,F4+1,"-"),"-") -> 45689 | H3: =IFERROR(IF(G4+1<Inputs!$G$6,G4+1,"-"),"-") -> 45717 | I3: =IFERROR(IF(H4+1<Inputs!$G$6,H4+1,"-"),"-") -> 45748 | J3: =IFERROR(IF(I4+1<Inputs!$G$6,I4+1,"-"),"-") -> 45778 | K3: =IFERROR(IF(J4+1<Inputs!$G$6,J4+1,"-"),"-") -> 45809 | ... BA3: =IFERROR(IF(AZ4+1<Inputs!$G$6,AZ4+1,"-"),"-") -> -
B4: End Month | C4: =EOMONTH(C3,0.5) -> 45596 | D4: =IFERROR(IF(EOMONTH(D3,0.5)<=Inputs!$G$5,EOMONTH(D3,0.5),EOMONTH(D3,11)),"-") -> 45626 | E4: =IFERROR(IF(EOMONTH(E3,0.5)<=Inputs!$G$5,EOMONTH(E3,0.5),EOMONTH(E3,11)),"-") -> 45657 | F4: =IFERROR(IF(EOMONTH(F3,0.5)<=Inputs!$G$5,EOMONTH(F3,0.5),EOMONTH(F3,11)),"-") -> 45688 | G4: =IFERROR(IF(EOMONTH(G3,0.5)<=Inputs!$G$5,EOMONTH(G3,0.5),EOMONTH(G3,11)),"-") -> 45716 | H4: =IFERROR(IF(EOMONTH(H3,0.5)<=Inputs!$G$5,EOMONTH(H3,0.5),EOMONTH(H3,11)),"-") -> 45747 | I4: =IFERROR(IF(EOMONTH(I3,0.5)<=Inputs!$G$5,EOMONTH(I3,0.5),EOMONTH(I3,11)),"-") -> 45777 | J4: =IFERROR(IF(EOMONTH(J3,0.5)<=Inputs!$G$5,EOMONTH(J3,0.5),EOMONTH(J3,11)),"-") -> 45808 | K4: =IFERROR(IF(EOMONTH(K3,0.5)<=Inputs!$G$5,EOMONTH(K3,0.5),EOMONTH(K3,11)),"-") -> 45838 | ... BA4: =IFERROR(IF(EOMONTH(BA3,0.5)<=Inputs!$G$5,EOMONTH(BA3,0.5),EOMONTH(BA3,11)),"-") -> -
B5: Days | C5: =_xlfn.DAYS(C4,C3)+1 -> 31 | D5: =IFERROR(_xlfn.DAYS(D4,D3)+1,0) -> 30 | E5: =IFERROR(_xlfn.DAYS(E4,E3)+1,0) -> 31 | F5: =IFERROR(_xlfn.DAYS(F4,F3)+1,0) -> 31 | G5: =IFERROR(_xlfn.DAYS(G4,G3)+1,0) -> 28 | H5: =IFERROR(_xlfn.DAYS(H4,H3)+1,0) -> 31 | I5: =IFERROR(_xlfn.DAYS(I4,I3)+1,0) -> 30 | J5: =IFERROR(_xlfn.DAYS(J4,J3)+1,0) -> 31 | K5: =IFERROR(_xlfn.DAYS(K4,K3)+1,0) -> 30 | ... BA5: =IFERROR(_xlfn.DAYS(BA4,BA3)+1,0) -> 0
B6: Count | C6: =IF(C2="Cons",0,1) -> 0 | D6: =IF(D2="Cons",0,MAX(C6+1,Inputs!D4)) -> 0 | E6: =IF(E2="Cons",0,MAX(D6+1,Inputs!E7)) -> 0 | F6: =IF(F2="Cons",0,MAX(E6+1,Inputs!F7)) -> 0 | G6: =IF(G2="Cons",0,MAX(F6+1,Inputs!G7)) -> 0 | H6: =IF(H2="Cons",0,MAX(G6+1,Inputs!H7)) -> 0 | I6: =IF(I2="Cons",0,MAX(H6+1,Inputs!I7)) -> 0 | J6: =IF(J2="Cons",0,MAX(I6+1,Inputs!J7)) -> 0 | K6: =IF(K2="Cons",0,MAX(J6+1,Inputs!K7)) -> 0 | L6: =IF(L2="Cons",0,MAX(K6+1,Inputs!L7)) -> 0 | ... BA6: =IF(BA2="Cons",0,MAX(AZ6+1,Inputs!BA7)) -> 37
B8: CAPEX
B9: Outflows | C9: =IF(C2="Cons",_xlfn.XLOOKUP(C3,'Project Capex'!$E$2:$AG$2,'Project Capex'!$E$69:$AG$69),0) -> 15.600953 | D9: =IF(D2="Cons",_xlfn.XLOOKUP(D3,'Project Capex'!$E$2:$AG$2,'Project Capex'!$E$69:$AG$69),0) -> 0.30095298 | E9: =IF(E2="Cons",_xlfn.XLOOKUP(E3,'Project Capex'!$E$2:$AG$2,'Project Capex'!$E$69:$AG$69),0) -> 0.30095298 | F9: =IF(F2="Cons",_xlfn.XLOOKUP(F3,'Project Capex'!$E$2:$AG$2,'Project Capex'!$E$69:$AG$69),0) -> 0.30095298 | G9: =IF(G2="Cons",_xlfn.XLOOKUP(G3,'Project Capex'!$E$2:$AG$2,'Project Capex'!$E$69:$AG$69),0) -> 0.80403491 | H9: =IF(H2="Cons",_xlfn.XLOOKUP(H3,'Project Capex'!$E$2:$AG$2,'Project Capex'!$E$69:$AG$69),0) -> 1.657997 | I9: =IF(I2="Cons",_xlfn.XLOOKUP(I3,'Project Capex'!$E$2:$AG$2,'Project Capex'!$E$69:$AG$69),0) -> 2.9820605 | J9: =IF(J2="Cons",_xlfn.XLOOKUP(J3,'Project Capex'!$E$2:$AG$2,'Project Capex'!$E$69:$AG$69),0) -> 8.409215 | ... BA9: =IF(BA2="Cons",_xlfn.XLOOKUP(BA3,'Project Capex'!$E$2:$AG$2,'Project Capex'!$E$69:$AG$69),0) -> 0
B11: Inflows
A12: =AVERAGE(Q12:AE12) -> 13.38543 | B12: FCF | C12: =IF(C2="Cons",0,_xlfn.XLOOKUP(C3,Computations!$C$4:$AG$4,Computations!$C$67:$AG$67)) -> 0 | D12: =IF(D2="Cons",0,_xlfn.XLOOKUP(D3,Computations!$C$4:$AG$4,Computations!$C$67:$AG$67)) -> 0 | E12: =IF(E2="Cons",0,_xlfn.XLOOKUP(E3,Computations!$C$4:$AG$4,Computations!$C$67:$AG$67)) -> 0 | F12: =IF(F2="Cons",0,_xlfn.XLOOKUP(F3,Computations!$C$4:$AG$4,Computations!$C$67:$AG$67)) -> 0 | G12: =IF(G2="Cons",0,_xlfn.XLOOKUP(G3,Computations!$C$4:$AG$4,Computations!$C$67:$AG$67)) -> 0 | H12: =IF(H2="Cons",0,_xlfn.XLOOKUP(H3,Computations!$C$4:$AG$4,Computations!$C$67:$AG$67)) -> 0 | I12: =IF(I2="Cons",0,_xlfn.XLOOKUP(I3,Computations!$C$4:$AG$4,Computations!$C$67:$AG$67)) -> 0 | J12: =IF(J2="Cons",0,_xlfn.XLOOKUP(J3,Computations!$C$4:$AG$4,Computations!$C$67:$AG$67)) -> 0 | ... BA12: =IF(BA2="Cons",0,_xlfn.XLOOKUP(BA3,Computations!$C$4:$AG$4,Computations!$C$67:$AG$67)) -> 0
B14: Net Cashflow | C14: =IFERROR(C12-C9,0) -> -15.600953 | D14: =IFERROR(D12-D9,0) -> -0.30095298 | E14: =IFERROR(E12-E9,0) -> -0.30095298 | F14: =IFERROR(F12-F9,0) -> -0.30095298 | G14: =IFERROR(G12-G9,0) -> -0.80403491 | H14: =IFERROR(H12-H9,0) -> -1.657997 | I14: =IFERROR(I12-I9,0) -> -2.9820605 | J14: =IFERROR(J12-J9,0) -> -8.409215 | ... BA14: =IFERROR(BA12-BA9,0) -> 0
B15: Cummulative CF | C15: =C14 -> -15.600953 | D15: =D14+C15 -> -15.901906 | E15: =E14+D15 -> -16.202859 | F15: =F14+E15 -> -16.503812 | G15: =G14+F15 -> -17.307847 | H15: =H14+G15 -> -18.965844 | I15: =I14+H15 -> -21.947904 | J15: =J14+I15 -> -30.357119 | K15: =K14+J15 -> -35.354272 | ... AL15: =AL14+AK15 -> 146.61541
A16: =Inputs!J4 -> 0.0710904 | B16: Discount factor | C16: =1/(1+$A$16)^C6 -> 1 | D16: =1/(1+$A$16)^D6 -> 1 | E16: =1/(1+$A$16)^E6 -> 1 | F16: =1/(1+$A$16)^F6 -> 1 | G16: =1/(1+$A$16)^G6 -> 1 | H16: =1/(1+$A$16)^H6 -> 1 | I16: =1/(1+$A$16)^I6 -> 1 | J16: =1/(1+$A$16)^J6 -> 1 | ... BA16: =1/(1+$A$16)^BA6 -> 0.078783144
B17: Discounted Cash flow | C17: =C14*C16 -> -15.600953 | D17: =D14*D16 -> -0.30095298 | E17: =E14*E16 -> -0.30095298 | F17: =F14*F16 -> -0.30095298 | G17: =G14*G16 -> -0.80403491 | H17: =H14*H16 -> -1.657997 | I17: =I14*I16 -> -2.9820605 | J17: =J14*J16 -> -8.409215 | ... BA17: =BA14*BA16 -> 0
B18: Cummulative DCF | C18: =C17 -> -15.600953 | D18: =D17+C18 -> -15.901906 | E18: =E17+D18 -> -16.202859 | F18: =F17+E18 -> -16.503812 | G18: =G17+F18 -> -17.307847 | H18: =H17+G18 -> -18.965844 | I18: =I17+H18 -> -21.947904 | J18: =J17+I18 -> -30.357119 | K18: =K17+J18 -> -35.354272 | ... AN18: =AN17+AM18 -> 66.396621
B19: For payback Cummulative DCF | C19: =IFERROR(-_xlfn.XLOOKUP(C3,'Project Capex'!$E$2:$AG$2,'Project Capex'!$E$69:$AG$69)*C16,_xlfn.XLOOKUP(C3,'Project Capex'!$E$2:$AG$2,'Project Capex'!$E$69:$AG$69)*C16+C15) -> -15.600953 | D19: =IFERROR(-_xlfn.XLOOKUP(D3,'Project Capex'!$E$2:$AG$2,'Project Capex'!$E$69:$AG$69)*D16,D17)+C19 -> -15.901906 | E19: =IFERROR(-_xlfn.XLOOKUP(E3,'Project Capex'!$E$2:$AG$2,'Project Capex'!$E$69:$AG$69)*E16,E17)+D19 -> -16.202859 | F19: =IFERROR(-_xlfn.XLOOKUP(F3,'Project Capex'!$E$2:$AG$2,'Project Capex'!$E$69:$AG$69)*F16,F17)+E19 -> -16.503812 | G19: =IFERROR(-_xlfn.XLOOKUP(G3,'Project Capex'!$E$2:$AG$2,'Project Capex'!$E$69:$AG$69)*G16,G17)+F19 -> -17.307847 | H19: =IFERROR(-_xlfn.XLOOKUP(H3,'Project Capex'!$E$2:$AG$2,'Project Capex'!$E$69:$AG$69)*H16,H17)+G19 -> -18.965844 | I19: =IFERROR(-_xlfn.XLOOKUP(I3,'Project Capex'!$E$2:$AG$2,'Project Capex'!$E$69:$AG$69)*I16,I17)+H19 -> -21.947904 | J19: =IFERROR(-_xlfn.XLOOKUP(J3,'Project Capex'!$E$2:$AG$2,'Project Capex'!$E$69:$AG$69)*J16,J17)+I19 -> -30.357119 | K19: =IFERROR(-_xlfn.XLOOKUP(K3,'Project Capex'!$E$2:$AG$2,'Project Capex'!$E$69:$AG$69)*K16,K17)+J19 -> -35.354272 | ... AN19: =IFERROR(-_xlfn.XLOOKUP(AN3,'Project Capex'!$E$2:$AG$2,'Project Capex'!$E$69:$AG$69)*AN16,AN17)+AM19 -> 66.396621
B20: Payback | C20: 0 | D20: {=_xlfn.IFS(AND(D2="Beyond Cons",C2="Cons"),1,AND(D2="Cons",C2="Cons"),0,AND(D2="Beyond Cons",C2="Beyond Cons"),IF(AND(D18<0,D6>1),D6,IF(AND(C20<1,D6>0),0,-C18/D17)))} -> 0 | E20: {=_xlfn.IFS(AND(E2="Beyond Cons",D2="Cons"),1,AND(E2="Cons",D2="Cons"),0,AND(E2="Beyond Cons",D2="Beyond Cons"),IF(AND(E18<0,E6>1),E6,IF(AND(D20<1,E6>0),0,-D18/E17)))} -> 0 | F20: {=_xlfn.IFS(AND(F2="Beyond Cons",E2="Cons"),1,AND(F2="Cons",E2="Cons"),0,AND(F2="Beyond Cons",E2="Beyond Cons"),IF(AND(F18<0,F6>1),F6,IF(AND(E20<1,F6>0),0,-E18/F17)))} -> 0 | G20: {=_xlfn.IFS(AND(G2="Beyond Cons",F2="Cons"),1,AND(G2="Cons",F2="Cons"),0,AND(G2="Beyond Cons",F2="Beyond Cons"),IF(AND(G18<0,G6>1),G6,IF(AND(F20<1,G6>0),0,-F18/G17)))} -> 0 | H20: {=_xlfn.IFS(AND(H2="Beyond Cons",G2="Cons"),1,AND(H2="Cons",G2="Cons"),0,AND(H2="Beyond Cons",G2="Beyond Cons"),IF(AND(H18<0,H6>1),H6,IF(AND(G20<1,H6>0),0,-G18/H17)))} -> 0 | I20: {=_xlfn.IFS(AND(I2="Beyond Cons",H2="Cons"),1,AND(I2="Cons",H2="Cons"),0,AND(I2="Beyond Cons",H2="Beyond Cons"),IF(AND(I18<0,I6>1),I6,IF(AND(H20<1,I6>0),0,-H18/I17)))} -> 0 | J20: {=_xlfn.IFS(AND(J2="Beyond Cons",I2="Cons"),1,AND(J2="Cons",I2="Cons"),0,AND(J2="Beyond Cons",I2="Beyond Cons"),IF(AND(J18<0,J6>1),J6,IF(AND(I20<1,J6>0),0,-I18/J17)))} -> 0 | K20: {=_xlfn.IFS(AND(K2="Beyond Cons",J2="Cons"),1,AND(K2="Cons",J2="Cons"),0,AND(K2="Beyond Cons",J2="Beyond Cons"),IF(AND(K18<0,K6>1),K6,IF(AND(J20<1,K6>0),0,-J18/K17)))} -> 0 | ... P20: {=_xlfn.IFS(AND(P2="Beyond Cons",O2="Cons"),1,AND(P2="Cons",O2="Cons"),0,AND(P2="Beyond Cons",O2="Beyond Cons"),IF(AND(P18<0,P6>1),P6,IF(AND(O20<1,P6>0),0,-O18/P17)))} -> 0 | Q20: {=_xlfn.IFS(AND(Q2="Beyond Cons",P2="Cons"),1,AND(Q2="Cons",P2="Cons"),0,AND(Q2="Beyond Cons",P2="Beyond Cons"),IF(AND(Q19<0,Q6>1),Q6,IF(AND(P20<1,Q6>0),0,-P19/Q17)))} -> 1 | R20: {=_xlfn.IFS(AND(R2="Beyond Cons",Q2="Cons"),1,AND(R2="Cons",Q2="Cons"),0,AND(R2="Beyond Cons",Q2="Beyond Cons"),IF(AND(R19<0,R6>1),R6,IF(AND(Q20<1,R6>0),0,-Q19/R17)))} -> 2 | S20: {=_xlfn.IFS(AND(S2="Beyond Cons",R2="Cons"),1,AND(S2="Cons",R2="Cons"),0,AND(S2="Beyond Cons",R2="Beyond Cons"),IF(AND(S19<0,S6>1),S6,IF(AND(R20<1,S6>0),0,-R19/S17)))} -> 3 | T20: {=_xlfn.IFS(AND(T2="Beyond Cons",S2="Cons"),1,AND(T2="Cons",S2="Cons"),0,AND(T2="Beyond Cons",S2="Beyond Cons"),IF(AND(T19<0,T6>1),T6,IF(AND(S20<1,T6>0),0,-S19/T17)))} -> 4 | U20: {=_xlfn.IFS(AND(U2="Beyond Cons",T2="Cons"),1,AND(U2="Cons",T2="Cons"),0,AND(U2="Beyond Cons",T2="Beyond Cons"),IF(AND(U19<0,U6>1),U6,IF(AND(T20<1,U6>0),0,-T19/U17)))} -> 5 | V20: {=_xlfn.IFS(AND(V2="Beyond Cons",U2="Cons"),1,AND(V2="Cons",U2="Cons"),0,AND(V2="Beyond Cons",U2="Beyond Cons"),IF(AND(V19<0,V6>1),V6,IF(AND(U20<1,V6>0),0,-U19/V17)))} -> 0.16186346 | W20: {=_xlfn.IFS(AND(W2="Beyond Cons",V2="Cons"),1,AND(W2="Cons",V2="Cons"),0,AND(W2="Beyond Cons",V2="Beyond Cons"),IF(AND(W19<0,W6>1),W6,IF(AND(V20<1,W6>0),0,-V19/W17)))} -> 0 | X20: {=_xlfn.IFS(AND(X2="Beyond Cons",W2="Cons"),1,AND(X2="Cons",W2="Cons"),0,AND(X2="Beyond Cons",W2="Beyond Cons"),IF(AND(X19<0,X6>1),X6,IF(AND(W20<1,X6>0),0,-W19/X17)))} -> 0 | ... BA20: {=_xlfn.IFS(AND(BA2="Beyond Cons",AZ2="Cons"),1,AND(BA2="Cons",AZ2="Cons"),0,AND(BA2="Beyond Cons",AZ2="Beyond Cons"),IF(AND(BA19<0,BA6>1),BA6,IF(AND(AZ20<1,BA6>0),0,-AZ19/BA17)))} -> 0
B21: Cummulative Payback | C21: 0 | D21: =IF(AND(D20<1,D20>0),C20+D20,0) -> 0 | E21: =IF(AND(E20<1,E20>0),D20+E20,0) -> 0 | F21: =IF(AND(F20<1,F20>0),E20+F20,0) -> 0 | G21: =IF(AND(G20<1,G20>0),F20+G20,0) -> 0 | H21: =IF(AND(H20<1,H20>0),G20+H20,0) -> 0 | I21: =IF(AND(I20<1,I20>0),H20+I20,0) -> 0 | J21: =IF(AND(J20<1,J20>0),I20+J20,0) -> 0 | K21: =IF(AND(K20<1,K20>0),J20+K20,0) -> 0 | ... BA21: =IF(AND(BA20<1,BA20>0),AZ20+BA20,0) -> 0
A23: =Inputs!J7 -> 1e-12 | B23: Equity | P23: =-SUM('Project Capex'!E72:R72) -> -5.4166044e-11 | Q23: =Q17 -> 9.5427751 | R23: =R17 -> 10.150766 | S23: =S17 -> 10.799431 | T23: =T17 -> 10.749805 | U23: =U17 -> 11.08989 | V23: =V17 -> 11.326693 | W23: =W17 -> 12.287297 | X23: =X17 -> 3.0537843 | ... AE23: =AE17 -> 2.1207593
B24: IRR | C24: =XIRR($C$17:$AE$17,$C$4:$AE$4) -> 0.13098165 | D24: %
B25: NPV | C25: =SUM(C17:BA17) -> 66.396621 | D25: Crore
B26: Payback | C26: =MAX(C21:BA21) -> 5.1618635 | D26: years
B27: ROCE - Pre Tax | C27: =AVERAGE(Computations!C27:Q27) -> 0.43830164 | D27: % | E27: =1/C27 -> 2.2815338
B28: ROCE - Post- Tax | C28: =(Computations!C26-Computations!C35+Computations!C36)/'Project Capex'!D69 -> 0.35581103 | D28: % | E28: =1/C28 -> 2.8104806
A30: 4.19 | B30: 0.05 | C30: -18.090992 | D30: -0.03699171 | E30: -0.03699171 | F30: -0.03699171 | G30: -0.54007364 | H30: -3.8364474 | I30: -3.6477917 | J30: -3.7316387 | K30: -3.7316387 | L30: -0.03699171 | M30: -0.03699171 | N30: -0.03699171 | O30: -0.03699171 | P30: -3.6687535 | Q30: 7.5767024 | R30: 8.4689324 | S30: 9.0390328 | T30: 9.561214 | U30: 10.148648 | V30: 4.2877924 | W30: 8.5556555 | X30: 8.4600074 | Y30: 9.3947628 | Z30: 9.9738746 | AA30: 4.1296406 | AB30: 7.6498117 | AC30: 8.141676 | AD30: 9.3357844 | AE30: 6.4705089 | AF30: 0 | AG30: 0 | AH30: 0 | AI30: 0 | AJ30: 0 | AK30: 0 | AL30: 0 | AM30: 0 | AN30: 0 | AO30: 0 | AP30: 0 | AQ30: 0 | AR30: 0 | AS30: 0 | AT30: 0 | AU30: 0 | AV30: 0 | AW30: 0 | AX30: 0 | AY30: 0 | AZ30: 0 | BA30: 0
A31: 4.28 | B31: 0.1 | C31: -18.090992 | D31: -0.03699171 | E31: -0.03699171 | F31: -0.03699171 | G31: -0.54007364 | H31: -3.8364474 | I31: -3.6477917 | J31: -3.7316387 | K31: -3.7316387 | L31: -0.03699171 | M31: -0.03699171 | N31: -0.03699171 | O31: -0.03699171 | P31: -3.6687535 | Q31: 8.1628147 | R31: 9.0843503 | S31: 9.6869968 | T31: 10.239712 | U31: 10.861071 | V31: 4.7273766 | W31: 9.1727641 | X31: 9.1061962 | Y31: 10.073261 | Z31: 10.686298 | AA31: 4.5704325 | AB31: 8.2652296 | AC31: 8.7878648 | AD31: 10.014283 | AE31: 7.0062941 | AF31: 0 | AG31: 0 | AH31: 0 | AI31: 0 | AJ31: 0 | AK31: 0 | AL31: 0 | AM31: 0 | AN31: 0 | AO31: 0 | AP31: 0 | AQ31: 0 | AR31: 0 | AS31: 0 | AT31: 0 | AU31: 0 | AV31: 0 | AW31: 0 | AX31: 0 | AY31: 0 | AZ31: 0 | BA31: 0
A32: 3.06 | B32: 0.15 | C32: -18.090992 | D32: -0.03699171 | E32: -0.03699171 | F32: -0.03699171 | G32: -0.54007364 | H32: -3.8364474 | I32: -3.6477917 | J32: -3.7316387 | K32: -3.7316387 | L32: -0.03699171 | M32: -0.03699171 | N32: -0.03699171 | O32: -0.03699171 | P32: -3.6687535 | Q32: 8.748927 | R32: 9.6997682 | S32: 10.334961 | T32: 10.91821 | U32: 11.573495 | V32: 5.1669608 | W32: 9.7898728 | X32: 9.752385 | Y32: 10.751759 | Z32: 11.398721 | AA32: 5.0112244 | AB32: 8.8806475 | AC32: 9.4340536 | AD32: 10.692781 | AE32: 7.5420794 | AF32: 0 | AG32: 0 | AH32: 0 | AI32: 0 | AJ32: 0 | AK32: 0 | AL32: 0 | AM32: 0 | AN32: 0 | AO32: 0 | AP32: 0 | AQ32: 0 | AR32: 0 | AS32: 0 | AT32: 0 | AU32: 0 | AV32: 0 | AW32: 0 | AX32: 0 | AY32: 0 | AZ32: 0 | BA32: 0
A33: 3.13 | B33: 0.2 | C33: -18.090992 | D33: -0.03699171 | E33: -0.03699171 | F33: -0.03699171 | G33: -0.54007364 | H33: -3.8364474 | I33: -3.6477917 | J33: -3.7316387 | K33: -3.7316387 | L33: -0.03699171 | M33: -0.03699171 | N33: -0.03699171 | O33: -0.03699171 | P33: -3.6687535 | Q33: 9.3350393 | R33: 10.315186 | S33: 10.982925 | T33: 11.596709 | U33: 12.285918 | V33: 5.606545 | W33: 10.406981 | X33: 10.398574 | Y33: 11.430258 | Z33: 12.111144 | AA33: 5.4520162 | AB33: 9.4960655 | AC33: 10.080242 | AD33: 11.371279 | AE33: 8.0778647 | AF33: 0 | AG33: 0 | AH33: 0 | AI33: 0 | AJ33: 0 | AK33: 0 | AL33: 0 | AM33: 0 | AN33: 0 | AO33: 0 | AP33: 0 | AQ33: 0 | AR33: 0 | AS33: 0 | AT33: 0 | AU33: 0 | AV33: 0 | AW33: 0 | AX33: 0 | AY33: 0 | AZ33: 0 | BA33: 0
D39: =1.0859/15 -> 0.072393333 | H39: =0.71*12 -> 8.52

Sheet Sensitivities
B2: IRR | C2: =IRR!#REF! -> #REF!
B3: NPV | C3: =IRR!C25 -> 66.396621
B4: Payback period | C4: =IRR!C26 -> 5.1618635 | G4: =G5-C2 -> #REF! | H4: =C4-H5 -> 0.14620192
G5: 0.25375693 | H5: 5.0156615
B6: Sr. No. | C6: Parameters | D6: Base | E6: UOM | F6: Changes | G6: Change in IRR | H6: Change in payback
B7: 1 | C7: Change in D:E | D7: 0:1 | F7: 3:1 | G7: - 9.51% | H7: +4.17 years
B8: 2 | C8: Change in rental cost | D8: 0.6 | E8: Rs./Pallet/day | F8: +/- 0.10 | G8: +/- 6.30% | H8: -/+ 0.26 years
B9: 3 | C9: Change in storage duration | D9: 5 | E9: days | F9: + 1 day | G9: -0.0669 | H9: +2.12 years
B10: 4 | C10: Change in project execution timeline | D10: 14 | E10: months | F10: + 1 month | G10: - 0.37% | H10: 0.00 years
B11: 5 | C11: Change in project life | D11: 15 | E11: years | F11: -/+ 5 years | G11: -/+ 1.50% | H11: +/- 0.04 years
B12: 6 | C12: Change in markup | D12: 0.15 | E12: % | F12: +/- 1% | G12: -/+ 1.91% | H12: + 1.41 / - 0.99 years
C22: Expense Parameter | D22: Annual Cost (Rs. Cr.)
C23: Lease Rent | D23: 2.24
C24: Security Deposit | D24: 0.56
C25: Total Lease Cost | D25: 2.8
C26: Electricity | D26: 0.03
C27: Manpower | D27: 0.27
C28: IT Costs | D28: 0.02
C29: Machinery & Equipment | D29: 0.55
C30: Total Operational Cost | D30: 3.67

Sheet Computations
B2: Operational Years
B3: Year | C3: 1 | D3: =IFERROR(IF(C3+1<=Inputs!$D$4,C3+1,"-"),"-") -> 2 | E3: =IFERROR(IF(D3+1<=Inputs!$D$4,D3+1,"-"),"-") -> 3 | F3: =IFERROR(IF(E3+1<=Inputs!$D$4,E3+1,"-"),"-") -> 4 | G3: =IFERROR(IF(F3+1<=Inputs!$D$4,F3+1,"-"),"-") -> 5 | H3: =IFERROR(IF(G3+1<=Inputs!$D$4,G3+1,"-"),"-") -> 6 | I3: =IFERROR(IF(H3+1<=Inputs!$D$4,H3+1,"-"),"-") -> 7 | J3: =IFERROR(IF(I3+1<=Inputs!$D$4,I3+1,"-"),"-") -> 8 | K3: =IFERROR(IF(J3+1<=Inputs!$D$4,J3+1,"-"),"-") -> 9 | ... AG3: =IFERROR(IF(AF3+1<=Inputs!$D$4,AF3+1,"-"),"-") -> -
B4: Start month | C4: =Inputs!G5+1 -> 45992 | D4: =IFERROR(C5+1,"-") -> 46357 | E4: =IFERROR(D5+1,"-") -> 46722 | F4: =IFERROR(E5+1,"-") -> 47088 | G4: =IFERROR(F5+1,"-") -> 47453 | H4: =IFERROR(G5+1,"-") -> 47818 | I4: =IFERROR(H5+1,"-") -> 48183 | J4: =IFERROR(I5+1,"-") -> 48549 | K4: =IFERROR(J5+1,"-") -> 48914 | ... AG4: =IFERROR(AF5+1,"-") -> -
B5: End month | C5: =EOMONTH(C4,11) -> 46356 | D5: =IFERROR(IF(EOMONTH(D4,11)<=Inputs!$G$6,EOMONTH(D4,11),"-"),"-") -> 46721 | E5: =IFERROR(IF(EOMONTH(E4,11)<=Inputs!$G$6,EOMONTH(E4,11),"-"),"-") -> 47087 | F5: =IFERROR(IF(EOMONTH(F4,11)<=Inputs!$G$6,EOMONTH(F4,11),"-"),"-") -> 47452 | G5: =IFERROR(IF(EOMONTH(G4,11)<=Inputs!$G$6,EOMONTH(G4,11),"-"),"-") -> 47817 | H5: =IFERROR(IF(EOMONTH(H4,11)<=Inputs!$G$6,EOMONTH(H4,11),"-"),"-") -> 48182 | I5: =IFERROR(IF(EOMONTH(I4,11)<=Inputs!$G$6,EOMONTH(I4,11),"-"),"-") -> 48548 | J5: =IFERROR(IF(EOMONTH(J4,11)<=Inputs!$G$6,EOMONTH(J4,11),"-"),"-") -> 48913 | K5: =IFERROR(IF(EOMONTH(K4,11)<=Inputs!$G$6,EOMONTH(K4,11),"-"),"-") -> 49278 | ... AG5: =IFERROR(IF(EOMONTH(AG4,11)<=Inputs!$G$6,EOMONTH(AG4,11),"-"),"-") -> -
B6: Days | C6: =IFERROR(_xlfn.DAYS(C5,C4),0)+1 -> 365 | D6: =IFERROR(_xlfn.DAYS(D5,D4),0)+1 -> 365 | E6: =IFERROR(_xlfn.DAYS(E5,E4),0)+1 -> 366 | F6: =IFERROR(_xlfn.DAYS(F5,F4),0)+1 -> 365 | G6: =IFERROR(_xlfn.DAYS(G5,G4),0)+1 -> 365 | H6: =IFERROR(_xlfn.DAYS(H5,H4),0)+1 -> 365 | I6: =IFERROR(_xlfn.DAYS(I5,I4),0)+1 -> 366 | J6: =IFERROR(_xlfn.DAYS(J5,J4),0)+1 -> 365 | ... AG6: =IFERROR(_xlfn.DAYS(AG5,AG4),0)+1 -> 1
A7: =C6*C9 -> 3258720
A8: =A7*A11 -> 2.210309e+08 | B8: Revenue
B9: # of pallet positions | C9: ='Project Cost Details'!$C$4 -> 8928 | D9: ='Project Cost Details'!$C$4 -> 8928 | E9: ='Project Cost Details'!$C$4 -> 8928 | F9: ='Project Cost Details'!$C$4 -> 8928 | G9: ='Project Cost Details'!$C$4 -> 8928 | H9: ='Project Cost Details'!$C$4 -> 8928 | I9: ='Project Cost Details'!$C$4 -> 8928 | J9: ='Project Cost Details'!$C$4 -> 8928 | ... AG9: ='Project Cost Details'!$C$4 -> 8928
B10: Utilisation | C10: =Inputs!H40 -> 0.83990912 | D10: =C10 -> 0.83990912 | E10: =D10 -> 0.83990912 | F10: =E10 -> 0.83990912 | G10: =F10 -> 0.83990912 | H10: =G10 -> 0.83990912 | I10: =H10 -> 0.83990912 | J10: =I10 -> 0.83990912 | K10: =J10 -> 0.83990912 | ... AG10: =AF10 -> 0.83990912
A11: =Inputs!D10 -> 67.827523 | B11: cost per pallet (Rs./pallet/day) | C11: =A11 -> 67.827523 | D11: =IFERROR(IF(MOD(D3-1,Inputs!$D$12)=0,Inputs!$D$10,C11*(1+D12)),0) -> 71.218899 | E11: =IFERROR(IF(MOD(E3-1,Inputs!$D$12)=0,Inputs!$D$10,D11*(1+E12)),0) -> 74.779844 | F11: =IFERROR(IF(MOD(F3-1,Inputs!$D$12)=0,Inputs!$D$10,E11*(1+F12)),0) -> 78.518836 | G11: =IFERROR(IF(MOD(G3-1,Inputs!$D$12)=0,Inputs!$D$10,F11*(1+G12)),0) -> 82.444778 | H11: =IFERROR(IF(MOD(H3-1,Inputs!$D$12)=0,Inputs!$D$10,G11*(1+H12)),0) -> 86.567017 | I11: =IFERROR(IF(MOD(I3-1,Inputs!$D$12)=0,Inputs!$D$10,H11*(1+I12)),0) -> 90.895367 | J11: =IFERROR(IF(MOD(J3-1,Inputs!$D$12)=0,Inputs!$D$10,I11*(1+J12)),0) -> 67.827523 | K11: =IFERROR(IF(MOD(K3-1,Inputs!$D$12)=0,Inputs!$D$10,J11*(1+K12)),0) -> 71.218899 | ... AG11: =IFERROR(IF(MOD(AG3-1,Inputs!$D$12)=0,Inputs!$D$10,AF11*(1+AG12)),0) -> 0
B12: escalation | C12: 0 | D12: =Inputs!$D$11 -> 0.05 | E12: =D12 -> 0.05 | F12: =E12 -> 0.05 | G12: =F12 -> 0.05 | H12: =G12 -> 0.05 | I12: =H12 -> 0.05 | J12: =I12 -> 0.05 | K12: =J12 -> 0.05 | L12: =K12 -> 0.05 | ... AG12: =AF12 -> 0.05
B13: Opportunity Cost | C13: ='Opportunity Cost'!D52 -> 14.425467 | D13: ='Opportunity Cost'!E52 -> 13.165102 | E13: ='Opportunity Cost'!F52 -> 13.629605 | F13: ='Opportunity Cost'!G52 -> 13.281556 | G13: ='Opportunity Cost'!H52 -> 13.745013 | H13: ='Opportunity Cost'!I52 -> 14.228053 | I13: ='Opportunity Cost'!J52 -> 13.899155 | J13: ='Opportunity Cost'!K52 -> 14.382397 | ... AG13: ='Opportunity Cost'!AH52 -> 0
B14: Total (rs.Cr.) | C14: =C9*C6*C11/10^7*C10+C13 -> 32.990054 | D14: =D9*D6*D11/10^7*D10+D13 -> 32.657919 | E14: =E9*E6*E11/10^7*E10+E13 -> 34.153138 | F14: =F9*F6*F11/10^7*F10+F13 -> 34.772386 | G14: =G9*G6*G11/10^7*G10+G13 -> 36.310385 | H14: =H9*H6*H11/10^7*H10+H13 -> 37.921694 | I14: =I9*I6*I11/10^7*I10+I13 -> 38.845637 | J14: =J9*J6*J11/10^7*J10+J13 -> 32.946984 | ... AG14: =AG9*AG6*AG11/10^7*AG10+AG13 -> 0
B16: Expenses
B17: ='Project Expenses'!B5 -> Operational and maintenance | C17: ='Project Expenses'!F6 -> 1.8054 | D17: ='Project Expenses'!G6 -> 1.89567 | E17: ='Project Expenses'!H6 -> 1.9904535 | F17: ='Project Expenses'!I6 -> 2.0899762 | G17: ='Project Expenses'!J6 -> 2.194475 | H17: ='Project Expenses'!K6 -> 2.3041987 | I17: ='Project Expenses'!L6 -> 2.4194087 | J17: ='Project Expenses'!M6 -> 2.5403791 | ... Q17: ='Project Expenses'!T6 -> 3.5745685
B18: ='Project Expenses'!B9 -> Manpower | C18: ='Project Expenses'!F16 -> 0.5208 | D18: ='Project Expenses'!G16 -> 0.54684 | E18: ='Project Expenses'!H16 -> 0.574182 | F18: ='Project Expenses'!I16 -> 0.6028911 | G18: ='Project Expenses'!J16 -> 0.63303566 | H18: ='Project Expenses'!K16 -> 0.66468744 | I18: ='Project Expenses'!L16 -> 0.69792181 | J18: ='Project Expenses'!M16 -> 0.7328179 | ... Q18: ='Project Expenses'!T16 -> 1.0311484
B19: ='Project Expenses'!B19 -> Power | C19: ='Project Expenses'!F25 -> 2.502066 | D19: ='Project Expenses'!G25 -> 2.502066 | E19: ='Project Expenses'!H25 -> 2.502066 | F19: ='Project Expenses'!I25 -> 2.502066 | G19: ='Project Expenses'!J25 -> 2.502066 | H19: ='Project Expenses'!K25 -> 2.502066 | I19: ='Project Expenses'!L25 -> 2.502066 | J19: ='Project Expenses'!M25 -> 2.502066 | ... Q19: ='Project Expenses'!T25 -> 2.502066
B20: ='Project Expenses'!B27 -> Water | C20: ='Project Expenses'!F29 -> 0.0657 | D20: ='Project Expenses'!G29 -> 0.0657 | E20: ='Project Expenses'!H29 -> 0.0657 | F20: ='Project Expenses'!I29 -> 0.0657 | G20: ='Project Expenses'!J29 -> 0.0657 | H20: ='Project Expenses'!K29 -> 0.0657 | I20: ='Project Expenses'!L29 -> 0.0657 | J20: ='Project Expenses'!M29 -> 0.0657 | ... Q20: ='Project Expenses'!T29 -> 0.0657
B21: ='Project Expenses'!B31 -> Repayment of Security Deposit | C21: ='Project Expenses'!F33 -> 0 | D21: ='Project Expenses'!G33 -> 0 | E21: ='Project Expenses'!H33 -> 0 | F21: ='Project Expenses'!I33 -> 0 | G21: ='Project Expenses'!J33 -> 0 | H21: ='Project Expenses'!K33 -> 0 | I21: ='Project Expenses'!L33 -> 0 | J21: ='Project Expenses'!M33 -> 8.236746 | ... AG21: ='Project Expenses'!AJ33 -> 0
B22: Land lease rentals | C22: ='Project Expenses'!F40/10^7 -> 5.961504 | D22: ='Project Expenses'!G40/10^7 -> 4.7692032 | E22: ='Project Expenses'!H40/10^7 -> 5.0076633 | F22: ='Project Expenses'!I40/10^7 -> 5.2580465 | G22: ='Project Expenses'!J40/10^7 -> 5.5209488 | H22: ='Project Expenses'!K40/10^7 -> 5.7969963 | I22: ='Project Expenses'!L40/10^7 -> 3.5769024 | J22: ='Project Expenses'!M40/10^7 -> 5.961504 | ... AG22: ='Project Expenses'!AJ40/10^7 -> 0
B23: Transportation cost | C23: ='Project Expenses'!F44/10^7 -> 0 | D23: ='Project Expenses'!G44/10^7 -> 0 | E23: ='Project Expenses'!H44/10^7 -> 0 | F23: ='Project Expenses'!I44/10^7 -> 0 | G23: ='Project Expenses'!J44/10^7 -> 0 | H23: ='Project Expenses'!K44/10^7 -> 0 | I23: ='Project Expenses'!L44/10^7 -> 0 | J23: ='Project Expenses'!M44/10^7 -> 0 | ... AG23: ='Project Expenses'!AJ44/10^7 -> 0
B24: Total | C24: =SUM(C17:C23) -> 10.85547 | D24: =SUM(D17:D23) -> 9.7794792 | E24: =SUM(E17:E23) -> 10.140065 | F24: =SUM(F17:F23) -> 10.51868 | G24: =SUM(G17:G23) -> 10.916225 | H24: =SUM(H17:H23) -> 11.333648 | I24: =SUM(I17:I23) -> 9.2619989 | J24: =SUM(J17:J23) -> 20.039213 | ... AG24: =SUM(AG17:AG23) -> 0
B26: PBIDT | C26: =C14-C24 -> 22.134584 | D26: =D14-D24 -> 22.878439 | E26: =E14-E24 -> 24.013073 | F26: =F14-F24 -> 24.253707 | G26: =G14-G24 -> 25.394159 | H26: =H14-H24 -> 26.588045 | I26: =I14-I24 -> 29.583638 | J26: =J14-J24 -> 12.907771 | ... AG26: =AG14-AG24 -> 0
B27: ROCE | C27: =C26/'Project Capex'!$D$69 -> 0.40864317 | D27: =D26/'Project Capex'!$D$69 -> 0.42237604 | E27: =E26/'Project Capex'!$D$69 -> 0.44332336 | F27: =F26/'Project Capex'!$D$69 -> 0.44776588 | G27: =G26/'Project Capex'!$D$69 -> 0.46882064 | H27: =H26/'Project Capex'!$D$69 -> 0.49086186 | I27: =I26/'Project Capex'!$D$69 -> 0.54616575 | J27: =J26/'Project Capex'!$D$69 -> 0.23830005 | ... Q27: =Q26/'Project Capex'!$D$69 -> 0.2417359
B28: Interest | C28: ='Term Loan'!D62 -> 5.1314804 | D28: ='Term Loan'!E62 -> 4.7884288 | E28: ='Term Loan'!F62 -> 4.4453772 | F28: ='Term Loan'!G62 -> 4.1023255 | G28: ='Term Loan'!H62 -> 3.7592739 | H28: ='Term Loan'!I62 -> 3.4162223 | I28: ='Term Loan'!J62 -> 3.0731707 | J28: ='Term Loan'!K62 -> 2.7301191 | ... AG28: ='Term Loan'!AH62 -> 0
B30: PBDT | C30: =C26-C28 -> 17.003103 | D30: =D26-D28 -> 18.090011 | E30: =E26-E28 -> 19.567696 | F30: =F26-F28 -> 20.151381 | G30: =G26-G28 -> 21.634885 | H30: =H26-H28 -> 23.171823 | I30: =I26-I28 -> 26.510468 | J30: =J26-J28 -> 10.177652 | ... AG30: =AG26-AG28 -> 0
B32: Depreciation | C32: ='Project Expenses'!F113 -> 6.8610323 | D32: ='Project Expenses'!G113 -> 6.8610323 | E32: ='Project Expenses'!H113 -> 6.8610323 | F32: ='Project Expenses'!I113 -> 6.8610323 | G32: ='Project Expenses'!J113 -> 6.8610323 | H32: ='Project Expenses'!K113 -> 6.8610323 | I32: ='Project Expenses'!L113 -> 6.8610323 | J32: ='Project Expenses'!M113 -> 3.4305161 | ... AG32: ='Project Expenses'!AJ113 -> 0
A34: =AVERAGE(C34:Q34) -> 17.580431 | B34: PBT | C34: =C30-C32 -> 10.142071 | D34: =D30-D32 -> 11.228978 | E34: =E30-E32 -> 12.706663 | F34: =F30-F32 -> 13.290349 | G34: =G30-G32 -> 14.773853 | H34: =H30-H32 -> 16.310791 | I34: =I30-I32 -> 19.649435 | J34: =J30-J32 -> 6.7471358 | ... AG34: =AG30-AG32 -> 0
A35: =Inputs!J5 -> 0.25168 | B35: Tax | C35: =IF(C34<0,0,$A$35*C34) -> 2.5525565 | D35: =IF(D34<0,0,$A$35*D34) -> 2.8261093 | E35: =IF(E34<0,0,$A$35*E34) -> 3.198013 | F35: =IF(F34<0,0,$A$35*F34) -> 3.344915 | G35: =IF(G34<0,0,$A$35*G34) -> 3.7182834 | H35: =IF(H34<0,0,$A$35*H34) -> 4.1050998 | I35: =IF(I34<0,0,$A$35*I34) -> 4.9453699 | J35: =IF(J34<0,0,$A$35*J34) -> 1.6981191 | ... AG35: =IF(AG34<0,0,$A$35*AG34) -> 0
B36: Deferred Tax | C36: =C46 -> -0.30915131 | D36: =D46 -> -0.0037609264 | E36: =E46 -> 0.2558209 | F36: =F46 -> 0.47646546 | G36: =G46 -> 0.66401333 | H36: =H46 -> 0.82342902 | I36: =I46 -> 0.95893236 | J36: =J46 -> 0.21071789 | ... AG36: =AG46 -> 0
A37: =AVERAGE(C37:Q37) -> 13.360886 | B37: PAT | C37: =C34-C35+C36 -> 7.2803634 | D37: =D34-D35+D36 -> 8.3991081 | E37: =E34-E35+E36 -> 9.7644711 | F37: =F34-F35+F36 -> 10.421899 | G37: =G34-G35+G36 -> 11.719583 | H37: =H34-H35+H36 -> 13.02912 | I37: =I34-I35+I36 -> 15.662998 | J37: =J34-J35+J36 -> 5.2597345 | ... AG37: =AG34-AG35+AG36 -> 0
C38: =C37/C14 -> 0.22068359 | D38: =D37/D14 -> 0.25718443 | E38: =E37/E14 -> 0.28590261 | F38: =F37/F14 -> 0.29971769 | G38: =G37/G14 -> 0.32276119 | H38: =H37/H14 -> 0.34357959 | I38: =I37/I14 -> 0.40321125 | J38: =J37/J14 -> 0.15964237 | ... AG38: =AG37/AG14 -> #DIV/0!
B39: TAXable Income
B40: PBT | C40: =C34 -> 10.142071 | D40: =D34 -> 11.228978 | E40: =E34 -> 12.706663 | F40: =F34 -> 13.290349 | G40: =G34 -> 14.773853 | H40: =H34 -> 16.310791 | I40: =I34 -> 19.649435 | J40: =J34 -> 6.7471358 | ... AG40: =AG34 -> 0
B41: Add: depreciation | C41: =C32 -> 6.8610323 | D41: =D32 -> 6.8610323 | E41: =E32 -> 6.8610323 | F41: =F32 -> 6.8610323 | G41: =G32 -> 6.8610323 | H41: =H32 -> 6.8610323 | I41: =I32 -> 6.8610323 | J41: =J32 -> 3.4305161 | ... AG41: =AG32 -> 0
B42: Subtotal | C42: =C40+C41 -> 17.003103 | D42: =D40+D41 -> 18.090011 | E42: =E40+E41 -> 19.567696 | F42: =F40+F41 -> 20.151381 | G42: =G40+G41 -> 21.634885 | H42: =H40+H41 -> 23.171823 | I42: =I40+I41 -> 26.510468 | J42: =J40+J41 -> 10.177652 | ... AG42: =AG40+AG41 -> 0
B43: Less: IT Depreciation WDV | C43: ='Project Expenses'!F236 -> 8.089383 | D43: ='Project Expenses'!G236 -> 6.8759756 | E43: ='Project Expenses'!H236 -> 5.8445792 | F43: ='Project Expenses'!I236 -> 4.9678923 | G43: ='Project Expenses'!J236 -> 4.2227085 | H43: ='Project Expenses'!K236 -> 3.5893022 | I43: ='Project Expenses'!L236 -> 3.0509069 | J43: ='Project Expenses'!M236 -> 2.5932709 | ... AG43: ='Project Expenses'!AJ236 -> 0
B44: PBT - For Income Tax | C44: =C42-C43 -> 8.9137205 | D44: =D42-D43 -> 11.214035 | E44: =E42-E43 -> 13.723116 | F44: =F42-F43 -> 15.183489 | G44: =G42-G43 -> 17.412177 | H44: =H42-H43 -> 19.582521 | I44: =I42-I43 -> 23.459561 | J44: =J42-J43 -> 7.5843811 | ... AG44: =AG42-AG43 -> 0
A45: =A35 -> 0.25168 | B45: Provision of Tax | C45: =IF(C37<0,0,$A$45*C44) -> 2.2434052 | D45: =IF(D37<0,0,$A$45*D44) -> 2.8223483 | E45: =IF(E37<0,0,$A$45*E44) -> 3.4538339 | F45: =IF(F37<0,0,$A$45*F44) -> 3.8213804 | G45: =IF(G37<0,0,$A$45*G44) -> 4.3822967 | H45: =IF(H37<0,0,$A$45*H44) -> 4.9285288 | I45: =IF(I37<0,0,$A$45*I44) -> 5.9043022 | J45: =IF(J37<0,0,$A$45*J44) -> 1.908837 | ... AG45: =IF(AG37<0,0,$A$45*AG44) -> 0
B46: Deferred Tax | C46: =(C59+C55) -> -0.30915131 | D46: =(D59+D55) -> -0.0037609264 | E46: =(E59+E55) -> 0.2558209 | F46: =(F59+F55) -> 0.47646546 | G46: =(G59+G55) -> 0.66401333 | H46: =(H59+H55) -> 0.82342902 | I46: =(I59+I55) -> 0.95893236 | J46: =(J59+J55) -> 0.21071789 | ... AG46: =(AG59+AG55) -> 0
B48: Schedule of Unabsorbed Depreciation
B49: Opening Balance | C49: 0 | D49: =C52 -> 0 | E49: =D52 -> 0 | F49: =E52 -> 0 | G49: =F52 -> 0 | H49: =G52 -> 0 | I49: =H52 -> 0 | J49: =I52 -> 0 | K49: =J52 -> 0 | ... AG49: =AF52 -> 0
B50: Carry forward of Losses | C50: =IF(C44<0,-C44,0) -> 0 | D50: =IF(D44<0,-D44,0) -> 0 | E50: =IF(E44<0,-E44,0) -> 0 | F50: =IF(F44<0,-F44,0) -> 0 | G50: =IF(G44<0,-G44,0) -> 0 | H50: =IF(H44<0,-H44,0) -> 0 | I50: =IF(I44<0,-I44,0) -> 0 | J50: =IF(J44<0,-J44,0) -> 0 | ... AG50: =IF(AG44<0,-AG44,0) -> 0
B51: Usage of setting off tax of current year | C51: =IF(C44>0,MIN(C44,C49),0) -> 0 | D51: =IF(D44>0,MIN(D44,D49),0) -> 0 | E51: =IF(E44>0,MIN(E44,E49),0) -> 0 | F51: =IF(F44>0,MIN(F44,F49),0) -> 0 | G51: =IF(G44>0,MIN(G44,G49),0) -> 0 | H51: =IF(H44>0,MIN(H44,H49),0) -> 0 | I51: =IF(I44>0,MIN(I44,I49),0) -> 0 | J51: =IF(J44>0,MIN(J44,J49),0) -> 0 | ... AG51: =IF(AG44>0,MIN(AG44,AG49),0) -> 0
B52: Closing Balance | C52: =C49+C50-C51 -> 0 | D52: =D49+D50-D51 -> 0 | E52: =E49+E50-E51 -> 0 | F52: =F49+F50-F51 -> 0 | G52: =G49+G50-G51 -> 0 | H52: =H49+H50-H51 -> 0 | I52: =I49+I50-I51 -> 0 | J52: =J49+J50-J51 -> 0 | ... AG52: =AG49+AG50-AG51 -> 0
B53: Taxable Profit | C53: =MAX(0,(C44-C51)) -> 8.9137205 | D53: =MAX(0,(D44-D51)) -> 11.214035 | E53: =MAX(0,(E44-E51)) -> 13.723116 | F53: =MAX(0,(F44-F51)) -> 15.183489 | G53: =MAX(0,(G44-G51)) -> 17.412177 | H53: =MAX(0,(H44-H51)) -> 19.582521 | I53: =MAX(0,(I44-I51)) -> 23.459561 | J53: =MAX(0,(J44-J51)) -> 7.5843811 | ... AG53: =MAX(0,(AG44-AG51)) -> 0
B54: Deferred Tax Asset on Cash flow | C54: =C50*$A$45 -> 0 | D54: =D52*$A$45 -> 0 | E54: =E52*$A$45 -> 0 | F54: =F52*$A$45 -> 0 | G54: =G52*$A$45 -> 0 | H54: =H52*$A$45 -> 0 | I54: =I52*$A$45 -> 0 | J54: =J52*$A$45 -> 0 | K54: =K52*$A$45 -> 0 | ... AG54: =AG52*$A$45 -> 0
B55: Movement of Deferred Tax | C55: =C54-0 -> 0 | D55: =D54-C54 -> 0 | E55: =E54-D54 -> 0 | F55: =F54-E54 -> 0 | G55: =G54-F54 -> 0 | H55: =H54-G54 -> 0 | I55: =I54-H54 -> 0 | J55: =J54-I54 -> 0 | K55: =K54-J54 -> 0 | ... AG55: =AG54-AF54 -> 0
B57: Book Depreciation | C57: =C32 -> 6.8610323 | D57: =D32 -> 6.8610323 | E57: =E32 -> 6.8610323 | F57: =F32 -> 6.8610323 | G57: =G32 -> 6.8610323 | H57: =H32 -> 6.8610323 | I57: =I32 -> 6.8610323 | J57: =J32 -> 3.4305161 | ... AG57: =AG32 -> 0
B58: IT Depreciation | C58: =C43 -> 8.089383 | D58: =D43 -> 6.8759756 | E58: =E43 -> 5.8445792 | F58: =F43 -> 4.9678923 | G58: =G43 -> 4.2227085 | H58: =H43 -> 3.5893022 | I58: =I43 -> 3.0509069 | J58: =J43 -> 2.5932709 | ... AG58: =AG43 -> 0
B59: Deferred Tax Liability/Asset | C59: =(C57-C58)*$A$45 -> -0.30915131 | D59: =(D57-D58)*$A$45 -> -0.0037609264 | E59: =(E57-E58)*$A$45 -> 0.2558209 | F59: =(F57-F58)*$A$45 -> 0.47646546 | G59: =(G57-G58)*$A$45 -> 0.66401333 | H59: =(H57-H58)*$A$45 -> 0.82342902 | I59: =(I57-I58)*$A$45 -> 0.95893236 | J59: =(J57-J58)*$A$45 -> 0.21071789 | ... AG59: =(AG57-AG58)*$A$45 -> 0
B62: Free Cash flow to equity
B63: PAT + Deferred Tax | C63: =C37+C46 -> 6.9712121 | D63: =D37+D46 -> 8.3953472 | E63: =E37+E46 -> 10.020292 | F63: =F37+F46 -> 10.898365 | G63: =G37+G46 -> 12.383596 | H63: =H37+H46 -> 13.852549 | I63: =I37+I46 -> 16.62193 | J63: =J37+J46 -> 5.4704524 | ... AG63: =AG37+AG46 -> 0
B64: Depreciation | C64: =C41 -> 6.8610323 | D64: =D41 -> 6.8610323 | E64: =E41 -> 6.8610323 | F64: =F41 -> 6.8610323 | G64: =G41 -> 6.8610323 | H64: =H41 -> 6.8610323 | I64: =I41 -> 6.8610323 | J64: =J41 -> 3.4305161 | ... AG64: =AG41 -> 0
B65: Repayments | C65: =-'Term Loan'!D61 -> -3.6110696 | D65: =-'Term Loan'!E61 -> -3.6110696 | E65: =-'Term Loan'!F61 -> -3.6110696 | F65: =-'Term Loan'!G61 -> -3.6110696 | G65: =-'Term Loan'!H61 -> -3.6110696 | H65: =-'Term Loan'!I61 -> -3.6110696 | I65: =-'Term Loan'!J61 -> -3.6110696 | J65: =-'Term Loan'!K61 -> -3.6110696 | ... AG65: =-'Term Loan'!AH61 -> 0
B67: Free Cash flow | C67: =C66+C63+C64+C65 -> 10.221175 | D67: =D66+D63+D64+D65 -> 11.64531 | E67: =E66+E63+E64+E65 -> 13.270255 | F67: =F66+F63+F64+F65 -> 14.148327 | G67: =G66+G63+G64+G65 -> 15.633559 | H67: =H66+H63+H64+H65 -> 17.102512 | I67: =I66+I63+I64+I65 -> 19.871893 | J67: =J66+J63+J64+J65 -> 5.289899 | ... AG67: =AG66+AG63+AG64+AG65 -> 0
B69: Working Capital
A70: =Inputs!D7 -> 3 | B70: Less: Security Deposit from Consumer | C70: =IFERROR(IF(MOD((C3-1),Inputs!$D$12)=0,C14/12*$A$70,0),0) -> 8.2475135 | D70: =IFERROR(IF(MOD((D3-1),Inputs!$D$12)=0,D14/12*$A$70,0),0) -> 0 | E70: =IFERROR(IF(MOD((E3-1),Inputs!$D$12)=0,E14/12*$A$70,0),0) -> 0 | F70: =IFERROR(IF(MOD((F3-1),Inputs!$D$12)=0,F14/12*$A$70,0),0) -> 0 | G70: =IFERROR(IF(MOD((G3-1),Inputs!$D$12)=0,G14/12*$A$70,0),0) -> 0 | H70: =IFERROR(IF(MOD((H3-1),Inputs!$D$12)=0,H14/12*$A$70,0),0) -> 0 | I70: =IFERROR(IF(MOD((I3-1),Inputs!$D$12)=0,I14/12*$A$70,0),0) -> 0 | J70: =IFERROR(IF(MOD((J3-1),Inputs!$D$12)=0,J14/12*$A$70,0),0) -> 8.236746 | ... AG70: =IFERROR(IF(MOD((AG3-1),Inputs!$D$12)=0,AG14/12*$A$70,0),0) -> 0
A71: 30 | B71: Add: Operational WC | C71: =C24/365*$A$71 -> 0.89223041 | D71: =D24/365*$A$71 -> 0.80379281 | E71: =E24/365*$A$71 -> 0.83342999 | F71: =F24/365*$A$71 -> 0.86454902 | G71: =G24/365*$A$71 -> 0.89722401 | H71: =H24/365*$A$71 -> 0.93153275 | I71: =I24/365*$A$71 -> 0.76126018 | J71: =J24/365*$A$71 -> 1.6470586 | ... AG71: =AG24/365*$A$71 -> 0
B72: Add: SD for land lease | C72: =IF('Project Expenses'!F39<0,0,'Project Expenses'!F39/10^7) -> 1.1923008 | D72: =IF('Project Expenses'!G39<0,0,'Project Expenses'!G39/10^7) -> 0 | E72: =IF('Project Expenses'!H39<0,0,'Project Expenses'!H39/10^7) -> 0 | F72: =IF('Project Expenses'!I39<0,0,'Project Expenses'!I39/10^7) -> 0 | G72: =IF('Project Expenses'!J39<0,0,'Project Expenses'!J39/10^7) -> 0 | H72: =IF('Project Expenses'!K39<0,0,'Project Expenses'!K39/10^7) -> 0 | I72: =IF('Project Expenses'!L39<0,0,'Project Expenses'!L39/10^7) -> 0 | J72: =IF('Project Expenses'!M39<0,0,'Project Expenses'!M39/10^7) -> 1.1923008 | ... AG72: =IF('Project Expenses'!AJ39<0,0,'Project Expenses'!AJ39/10^7) -> 0
B73: Working Capital | C73: =-C70+C71+C72 -> -6.1629823 | D73: =-D70+D71+D72 -> 0.80379281 | E73: =-E70+E71+E72 -> 0.83342999 | F73: =-F70+F71+F72 -> 0.86454902 | G73: =-G70+G71+G72 -> 0.89722401 | H73: =-H70+H71+H72 -> 0.93153275 | I73: =-I70+I71+I72 -> 0.76126018 | J73: =-J70+J71+J72 -> -5.3973866 | ... AG73: =-AG70+AG71+AG72 -> 0
A74: 0 | B74: Working Capital Loan | C74: =C73*$A$74 -> 0 | D74: =D73*$A$74 -> 0 | E74: =E73*$A$74 -> 0 | F74: =F73*$A$74 -> 0 | G74: =G73*$A$74 -> 0 | H74: =H73*$A$74 -> 0 | I74: =I73*$A$74 -> 0 | J74: =J73*$A$74 -> 0 | ... AG74: =AG73*$A$74 -> 0
B77: Cash Balance
B78: Add: Operational Cash Flows
B79: Cash from Operations | C79: =C80+C81-(C82+C83) -> 14.141396 | D79: =D80+D81-(D82+D83) -> 15.26014 | E79: =E80+E81-(E82+E83) -> 16.625503 | F79: =F80+F81-(F82+F83) -> 17.282932 | G79: =G80+G81-(G82+G83) -> 18.580615 | H79: =H80+H81-(H82+H83) -> 19.890152 | I79: =I80+I81-(I82+I83) -> 22.52403 | J79: =J80+J81-(J82+J83) -> 8.6902507 | ... AG79: =AG80+AG81-(AG82+AG83) -> 0
B80: PAT | C80: =C63 -> 6.9712121 | D80: =D63 -> 8.3953472 | E80: =E63 -> 10.020292 | F80: =F63 -> 10.898365 | G80: =G63 -> 12.383596 | H80: =H63 -> 13.852549 | I80: =I63 -> 16.62193 | J80: =J63 -> 5.4704524 | ... AG80: =AG63 -> 0
B81: Depreciation | C81: =C64 -> 6.8610323 | D81: =D64 -> 6.8610323 | E81: =E64 -> 6.8610323 | F81: =F64 -> 6.8610323 | G81: =G64 -> 6.8610323 | H81: =H64 -> 6.8610323 | I81: =I64 -> 6.8610323 | J81: =J64 -> 3.4305161 | ... AG81: =AG64 -> 0
B82: Movement of Deferred Tax | C82: =C55 -> 0 | D82: =D55 -> 0 | E82: =E55 -> 0 | F82: =F55 -> 0 | G82: =G55 -> 0 | H82: =H55 -> 0 | I82: =I55 -> 0 | J82: =J55 -> 0 | ... AG82: =AG55 -> 0
B83: Deferred Tax Liability/Asset | C83: =C59 -> -0.30915131 | D83: =D59 -> -0.0037609264 | E83: =E59 -> 0.2558209 | F83: =F59 -> 0.47646546 | G83: =G59 -> 0.66401333 | H83: =H59 -> 0.82342902 | I83: =I59 -> 0.95893236 | J83: =J59 -> 0.21071789 | ... AG83: =AG59 -> 0
B84: Change in working capital | C84: =0-C73 -> 6.1629823 | D84: =D73-C73 -> 6.9667751 | E84: =E73-D73 -> 0.029637177 | F84: =F73-E73 -> 0.031119036 | G84: =G73-F73 -> 0.032674988 | H84: =H73-G73 -> 0.034308738 | I84: =I73-H73 -> -0.17027257 | J84: =J73-I73 -> -6.1586468 | K84: =K73-J73 -> 6.2829065 | ... Q84: =Q73-P73 -> -7.5969183 | R84: 0 | S84: =S73-R73 -> 0 | T84: =T73-S73 -> 0 | U84: =U73-T73 -> 0 | V84: =V73-U73 -> 0 | W84: =W73-V73 -> 0 | X84: =X73-W73 -> 0 | Y84: =Y73-X73 -> 0 | Z84: =Z73-Y73 -> 0 | ... AG84: =AG73-AF73 -> 0
B85: Add: Financial Cash Flows
B86: Repayment of Loans | C86: =-'Term Loan'!D61 -> -3.6110696 | D86: =-'Term Loan'!E61 -> -3.6110696 | E86: =-'Term Loan'!F61 -> -3.6110696 | F86: =-'Term Loan'!G61 -> -3.6110696 | G86: =-'Term Loan'!H61 -> -3.6110696 | H86: =-'Term Loan'!I61 -> -3.6110696 | I86: =-'Term Loan'!J61 -> -3.6110696 | J86: =-'Term Loan'!K61 -> -3.6110696 | ... AG86: =-'Term Loan'!AH61 -> 0
B87: Increase in Working Capital | C87: =C73 -> -6.1629823 | D87: =C73-D73 -> -6.9667751 | E87: =D73-E73 -> -0.029637177 | F87: =E73-F73 -> -0.031119036 | G87: =F73-G73 -> -0.032674988 | H87: =G73-H73 -> -0.034308738 | I87: =H73-I73 -> 0.17027257 | J87: =I73-J73 -> 6.1586468 | K87: =J73-K73 -> -6.2829065 | ... Q87: =P73-Q73 -> 7.5969183 | R87: 0 | S87: =R73-S73 -> 0 | T87: =S73-T73 -> 0 | U87: =T73-U73 -> 0 | V87: =U73-V73 -> 0 | W87: =V73-W73 -> 0 | X87: =W73-X73 -> 0 | Y87: =X73-Y73 -> 0 | Z87: =Y73-Z73 -> 0 | ... AG87: =AF73-AG73 -> 0
B88: Debt Infusion (if any)
B89: Total Addition | C89: =C79+C84+C86+C87+C88 -> 10.530326 | D89: =D79+D84+D86+D87+D88 -> 11.649071 | E89: =E79+E84+E86+E87+E88 -> 13.014434 | F89: =F79+F84+F86+F87+F88 -> 13.671862 | G89: =G79+G84+G86+G87+G88 -> 14.969546 | H89: =H79+H84+H86+H87+H88 -> 16.279083 | I89: =I79+I84+I86+I87+I88 -> 18.91296 | J89: =J79+J84+J86+J87+J88 -> 5.0791811 | ... AG89: =AG79+AG84+AG86+AG87+AG88 -> 0
B90: Closing Cash Balance | C90: =IF(C3="-",0,C89) -> 10.530326 | D90: =IF(D3="-",0,D89+C90) -> 22.179397 | E90: =IF(E3="-",0,E89+D90) -> 35.193831 | F90: =IF(F3="-",0,F89+E90) -> 48.865693 | G90: =IF(G3="-",0,G89+F90) -> 63.835238 | H90: =IF(H3="-",0,H89+G90) -> 80.114321 | I90: =IF(I3="-",0,I89+H90) -> 99.027281 | J90: =IF(J3="-",0,J89+I90) -> 104.10646 | K90: =IF(K3="-",0,K89+J90) -> 116.3731 | ... AG90: =IF(AG3="-",0,AG89+AF90) -> 0
B93: Balance Sheet
B94: Fixed Assets
B95: Gross Fixed Assets | C95: ='Project Expenses'!F80 -> 54.166044 | D95: ='Project Expenses'!G80 -> 54.166044 | E95: ='Project Expenses'!H80 -> 54.166044 | F95: ='Project Expenses'!I80 -> 54.166044 | G95: ='Project Expenses'!J80 -> 54.166044 | H95: ='Project Expenses'!K80 -> 54.166044 | I95: ='Project Expenses'!L80 -> 54.166044 | J95: ='Project Expenses'!M80 -> 54.166044 | ... AG95: ='Project Expenses'!AJ80 -> 0
B96: Less: Acc. Depreciation | C96: =C64 -> 6.8610323 | D96: =C96+D64 -> 13.722065 | E96: =D96+E64 -> 20.583097 | F96: =E96+F64 -> 27.444129 | G96: =F96+G64 -> 34.305161 | H96: =G96+H64 -> 41.166194 | I96: =H96+I64 -> 48.027226 | J96: =I96+J64 -> 51.457742 | K96: =J96+K64 -> 51.457742 | ... Q96: =P96+Q64 -> 51.457742
B97: Closing Balance | C97: =MAX(C95-C96,0) -> 47.305012 | D97: =MAX(D95-D96,0) -> 40.44398 | E97: =MAX(E95-E96,0) -> 33.582947 | F97: =MAX(F95-F96,0) -> 26.721915 | G97: =MAX(G95-G96,0) -> 19.860883 | H97: =MAX(H95-H96,0) -> 12.999851 | I97: =MAX(I95-I96,0) -> 6.1388183 | J97: =MAX(J95-J96,0) -> 2.7083022 | ... Q97: =MAX(Q95-Q96,0) -> 2.7083022
B98: Working Capital (other than cash balance) | C98: =C73 -> -6.1629823 | D98: =D73 -> 0.80379281 | E98: =E73 -> 0.83342999 | F98: =F73 -> 0.86454902 | G98: =G73 -> 0.89722401 | H98: =H73 -> 0.93153275 | I98: =I73 -> 0.76126018 | J98: =J73 -> -5.3973866 | ... AG98: =AG73 -> 0
B99: Cash Balance | C99: =C90 -> 10.530326 | D99: =D90 -> 22.179397 | E99: =E90 -> 35.193831 | F99: =F90 -> 48.865693 | G99: =G90 -> 63.835238 | H99: =H90 -> 80.114321 | I99: =I90 -> 99.027281 | J99: =J90 -> 104.10646 | ... AG99: =AG90 -> 0
B100: Total Usage of Funds | C100: =C97+C98+C99 -> 51.672356 | D100: =D97+D98+D99 -> 63.427169 | E100: =E97+E98+E99 -> 69.610208 | F100: =F97+F98+F99 -> 76.452157 | G100: =G97+G98+G99 -> 84.593345 | H100: =H97+H98+H99 -> 94.045704 | I100: =I97+I98+I99 -> 105.92736 | J100: =J97+J98+J99 -> 101.41738 | ... AG100: =AG97+AG98+AG99 -> 0
B102: Equity | C102: ='Project Cost Details'!G39/10^7 -> 5.4166044e-11 | D102: =IF(D3="-",0,C102) -> 5.4166044e-11 | E102: =IF(E3="-",0,D102) -> 5.4166044e-11 | F102: =IF(F3="-",0,E102) -> 5.4166044e-11 | G102: =IF(G3="-",0,F102) -> 5.4166044e-11 | H102: =IF(H3="-",0,G102) -> 5.4166044e-11 | I102: =IF(I3="-",0,H102) -> 5.4166044e-11 | J102: =IF(J3="-",0,I102) -> 5.4166044e-11 | K102: =IF(K3="-",0,J102) -> 5.4166044e-11 | ... AG102: =IF(AG3="-",0,AF102) -> 0
B103: Reserves / PAT | C103: =C63 -> 6.9712121 | D103: =IF(D3="-",0,D63+C103) -> 15.366559 | E103: =IF(E3="-",0,E63+D103) -> 25.386851 | F103: =IF(F3="-",0,F63+E103) -> 36.285216 | G103: =IF(G3="-",0,G63+F103) -> 48.668813 | H103: =IF(H3="-",0,H63+G103) -> 62.521361 | I103: =IF(I3="-",0,I63+H103) -> 79.143292 | J103: =IF(J3="-",0,J63+I103) -> 84.613744 | K103: =IF(K3="-",0,K63+J103) -> 100.49145 | ... AG103: =IF(AG3="-",0,AG63+AF103) -> 0
B104: Working Capital Loan | C104: =C73 -> -6.1629823 | D104: =D73 -> 0.80379281 | E104: =E73 -> 0.83342999 | F104: =F73 -> 0.86454902 | G104: =G73 -> 0.89722401 | H104: =H73 -> 0.93153275 | I104: =I73 -> 0.76126018 | J104: =J73 -> -5.3973866 | ... AG104: =AG73 -> 0
B105: Deffered Tax Liabilities | C105: =IF(C3="-",0,0-C46) -> 0.30915131 | D105: =IF(D3="-",0,C105-D46) -> 0.31291224 | E105: =IF(E3="-",0,D105-E46) -> 0.057091337 | F105: =IF(F3="-",0,E105-F46) -> -0.41937412 | G105: =IF(G3="-",0,F105-G46) -> -1.0833874 | H105: =IF(H3="-",0,G105-H46) -> -1.9068165 | I105: =IF(I3="-",0,H105-I46) -> -2.8657488 | J105: =IF(J3="-",0,I105-J46) -> -3.0764667 | K105: =IF(K3="-",0,J105-K46) -> -3.0764667 | ... AG105: =IF(AG3="-",0,AF105-AG46) -> 0
B106: Loans | C106: =C109 -> 50.554975 | D106: =D109 -> 46.943905 | E106: =E109 -> 43.332835 | F106: =F109 -> 39.721766 | G106: =G109 -> 36.110696 | H106: =H109 -> 32.499627 | I106: =I109 -> 28.888557 | J106: =J109 -> 25.277487 | ... AG106: =AG109 -> 1.8163249e-13
B107: Opening Balance | C107: ='Term Loan'!C5 -> 54.166044 | D107: =C109 -> 50.554975 | E107: =D109 -> 46.943905 | F107: =E109 -> 43.332835 | G107: =F109 -> 39.721766 | H107: =G109 -> 36.110696 | I107: =H109 -> 32.499627 | J107: =I109 -> 28.888557 | K107: =J109 -> 25.277487 | ... AG107: =AF109 -> 1.851852e-13
B108: Less: Repayment | C108: ='Term Loan'!D61 -> 3.6110696 | D108: ='Term Loan'!E61 -> 3.6110696 | E108: ='Term Loan'!F61 -> 3.6110696 | F108: ='Term Loan'!G61 -> 3.6110696 | G108: ='Term Loan'!H61 -> 3.6110696 | H108: ='Term Loan'!I61 -> 3.6110696 | I108: ='Term Loan'!J61 -> 3.6110696 | J108: ='Term Loan'!K61 -> 3.6110696 | ... AG108: ='Term Loan'!AH61 -> 0
B109: Closing Balance | C109: =C107-C108 -> 50.554975 | D109: =D107-D108 -> 46.943905 | E109: =E107-E108 -> 43.332835 | F109: =F107-F108 -> 39.721766 | G109: =G107-G108 -> 36.110696 | H109: =H107-H108 -> 32.499627 | I109: =I107-I108 -> 28.888557 | J109: =J107-J108 -> 25.277487 | ... AG109: =AG107-AG108 -> 1.851852e-13
B110: Total Source of Funds | C110: =C102+C103+C105+C106+C104 -> 51.672356 | D110: =D102+D103+D105+D106+D104 -> 63.427169 | E110: =E102+E103+E105+E106+E104 -> 69.610208 | F110: =F102+F103+F105+F106+F104 -> 76.452157 | G110: =G102+G103+G105+G106+G104 -> 84.593345 | H110: =H102+H103+H105+H106+H104 -> 94.045704 | I110: =I102+I103+I105+I106+I104 -> 105.92736 | J110: =J102+J103+J105+J106+J104 -> 101.41738 | ... AG110: =AG102+AG103+AG105+AG106+AG104 -> 1.8163249e-13
B112: Check | C112: =C100-C110 -> -5.3738347e-11 | D112: =D100-D110 -> -5.4207305e-11 | E112: =E100-E110 -> -5.3816507e-11 | F112: =F100-F110 -> -5.3432814e-11 | G112: =G100-G110 -> -5.3461235e-11 | H112: =H100-H110 -> -5.4328098e-11 | I112: =I100-I110 -> -5.3915983e-11 | J112: =J100-J110 -> -5.353229e-11 | ... AG112: =AG100-AG110 -> -1.8163249e-13

Sheet Opportunity Cost
B2: Year | C2: UOM | D2: 1 | E2: =IFERROR(IF(D2<Inputs!$D$4,MIN(D2+1,Inputs!$D$4),"-"),"-") -> 2 | F2: =IFERROR(IF(E2<Inputs!$D$4,MIN(E2+1,Inputs!$D$4),"-"),"-") -> 3 | G2: =IFERROR(IF(F2<Inputs!$D$4,MIN(F2+1,Inputs!$D$4),"-"),"-") -> 4 | H2: =IFERROR(IF(G2<Inputs!$D$4,MIN(G2+1,Inputs!$D$4),"-"),"-") -> 5 | I2: =IFERROR(IF(H2<Inputs!$D$4,MIN(H2+1,Inputs!$D$4),"-"),"-") -> 6 | J2: =IFERROR(IF(I2<Inputs!$D$4,MIN(I2+1,Inputs!$D$4),"-"),"-") -> 7 | K2: =IFERROR(IF(J2<Inputs!$D$4,MIN(J2+1,Inputs!$D$4),"-"),"-") -> 8 | L2: =IFERROR(IF(K2<Inputs!$D$4,MIN(K2+1,Inputs!$D$4),"-"),"-") -> 9 | ... Y2: =IFERROR(IF(X2<Inputs!$D$4,MIN(X2+1,Inputs!$D$4),"-"),"-") -> -
A3: 1 | B3: Rental Cost
B4: Total space required to store 8928 pallets | C4: Sq. ft | D4: =8928*(36)/2/Computations!$C$10 -> 191334.99 | E4: =D4 -> 191334.99 | F4: =E4 -> 191334.99 | G4: =F4 -> 191334.99 | H4: =G4 -> 191334.99 | I4: =H4 -> 191334.99 | J4: =I4 -> 191334.99 | K4: =J4 -> 191334.99 | L4: =K4 -> 191334.99 | ... Y4: =X4 -> 191334.99
B5: Lease rental of the land | C5: Rs./sq.ft. | D5: 23 | E5: =D5*(1+E6) -> 24.15 | F5: =E5*(1+F6) -> 25.3575 | G5: =D5 -> 23 | H5: =G5*(1+H6) -> 24.15 | I5: =H5*(1+I6) -> 25.3575 | J5: =G5 -> 23 | K5: =J5*(1+K6) -> 24.15 | L5: =K5*(1+L6) -> 25.3575 | M5: =G5 -> 23 | N5: =M5*(1+N6) -> 24.15 | O5: =N5*(1+O6) -> 25.3575 | P5: =M5 -> 23 | Q5: =P5*(1+Q6) -> 24.15 | R5: =Q5*(1+R6) -> 25.3575
B6: Escalation | C6: % | D6: 0 | E6: 0.05 | F6: 0.05 | G6: 0 | H6: 0.05 | I6: 0.05 | J6: 0 | K6: 0.05 | L6: 0.05 | M6: 0 | N6: 0.05 | O6: 0.05 | P6: 0 | Q6: 0.05 | R6: 0.05
B7: Security Deposit | C7: Rs. Cr. | D7: =D4*D5*3/10^7 -> 1.3202114 | R7: =-D7 -> -1.3202114
B8: Total cost per year | C8: Rs. Cr. | D8: =D4*D5*12/10^7+D7 -> 6.601057 | E8: =E4*E5*12/10^7+E7 -> 5.5448879 | F8: =F4*F5*12/10^7+F7 -> 5.8221323 | G8: =G4*G5*12/10^7+G7 -> 5.2808456 | H8: =H4*H5*12/10^7+H7 -> 5.5448879 | I8: =I4*I5*12/10^7+I7 -> 5.8221323 | J8: =J4*J5*12/10^7+J7 -> 5.2808456 | K8: =K4*K5*12/10^7+K7 -> 5.5448879 | ... R8: =R4*R5*12/10^7+R7 -> 4.5019209
A10: 2 | B10: Operational cost
A11: a. | B11: Manpower
B12: Total number of employees | D12: Monthly salary | E12: Total annual cost
B13: Security | C13: 6 | D13: 12000 | E13: =D13*C13*12 -> 864000
B14: Site incharge | C14: 1 | D14: 50000 | E14: =D14*C14*12 -> 600000
B15: Managers | C15: 3 | D15: 15000 | E15: =D15*C15*12 -> 540000
B16: Operators | C16: 12 | D16: 10000 | E16: =D16*C16*12 -> 1440000
B17: Total | E17: =SUM(E13:E16) -> 3444000
B19: Escalation | D19: 0 | E19: 0.05 | F19: 0.05 | G19: 0.05 | H19: 0.05 | I19: 0.05 | J19: 0.05 | K19: 0.05 | L19: 0.05 | M19: 0.05 | N19: 0.05 | O19: 0.05 | P19: 0.05 | Q19: 0.05 | R19: 0.05
B20: Per year cost | C20: Rs. Cr. | D20: =E17/10^7 -> 0.3444 | E20: =D20*(1+E19) -> 0.36162 | F20: =E20*(1+F19) -> 0.379701 | G20: =F20*(1+G19) -> 0.39868605 | H20: =G20*(1+H19) -> 0.41862035 | I20: =H20*(1+I19) -> 0.43955137 | J20: =I20*(1+J19) -> 0.46152894 | K20: =J20*(1+K19) -> 0.48460539 | L20: =K20*(1+L19) -> 0.50883565 | ... R20: =Q20*(1+R19) -> 0.68188844
A22: b | B22: IT infrastructure
B23: IT assets | D23: Cost per month | E23: Total annual cost
B24: Printer | C24: 1 | D24: 5000 | E24: =D24*C24*12 -> 60000
B25: Laptops | C25: 4 | D25: =100000/12 -> 8333.3333 | E25: =D25*12*C25 -> 400000
B26: Wifi | C26: 1 | D26: 1500 | E26: =D26*C26*12 -> 18000
B27: Total | E27: =SUM(E24:E26) -> 478000
B29: Escalation | D29: 0 | E29: 0 | F29: 0 | G29: 0 | H29: 0 | I29: 0 | J29: 0 | K29: 0 | L29: 0 | M29: 0 | N29: 0 | O29: 0 | P29: 0 | Q29: 0 | R29: 0
B30: Per year cost | C30: Rs. Cr. | D30: =E27/10^7 -> 0.0478 | E30: =D30*(1+E29) -> 0.0478 | F30: =E30*(1+F29) -> 0.0478 | G30: =F30*(1+G29) -> 0.0478 | H30: =G30*(1+H29) -> 0.0478 | I30: =H30*(1+I29) -> 0.0478 | J30: =I30*(1+J29) -> 0.0478 | K30: =J30*(1+K29) -> 0.0478 | L30: =K30*(1+L29) -> 0.0478 | ... R30: =Q30*(1+R29) -> 0.0478
A32: c. | B32: Machineries
B33: Rentals
B34: Rental Electrical Forklifts charges | C34: 8 | D34: 138702.5 | E34: =C34*D34*12 -> 13315440
B35: BOPT | C35: 4 | D35: 50000 | E35: =C35*D35*12 -> 2400000
B36: Total | E36: =SUM(E34:E35) -> 15715440
B37: One time payment
B38: Dock Levellers | C38: 8 | D38: =392044*1.18 -> 462611.92 | E38: =C38*D38 -> 3700895.4
B39: Installation | C39: 8 | D39: =16500*1.18 -> 19470 | E39: =C39*D39 -> 155760
B40: Total | E40: =E38+E39 -> 3856655.4
B42: Per year cost | C42: Rs. Cr. | D42: =E36/10^7+E40/10^7 -> 1.9572095 | E42: =$E$36/10^7 -> 1.571544 | F42: =$E$36/10^7 -> 1.571544 | G42: =$E$36/10^7 -> 1.571544 | H42: =$E$36/10^7 -> 1.571544 | I42: =$E$36/10^7 -> 1.571544 | J42: =$E$36/10^7 -> 1.571544 | K42: =$E$36/10^7 -> 1.571544 | L42: =$E$36/10^7 -> 1.571544 | ... R42: =$E$36/10^7 -> 1.571544
A44: d. | B44: Transporatation cost
B45: Assumption
B46: Distance from plant | C46: 20 kms
B47: Per trip cost | C47: 10000
B48: Total trips per day | C48: 15
D49: 0 | E49: 0.03 | F49: 0.03 | G49: 0.03 | H49: 0.03 | I49: 0.03 | J49: 0.03 | K49: 0.03 | L49: 0.03 | M49: 0.03 | N49: 0.03 | O49: 0.03 | P49: 0.03 | Q49: 0.03 | R49: 0.03 | S49: 0.03
B50: Total cost | D50: =C47*C48*365/10^7 -> 5.475 | E50: =D50*(1+E49) -> 5.63925 | F50: =E50*(1+F49) -> 5.8084275 | G50: =F50*(1+G49) -> 5.9826803 | H50: =G50*(1+H49) -> 6.1621607 | I50: =H50*(1+I49) -> 6.3470256 | J50: =I50*(1+J49) -> 6.5374363 | K50: =J50*(1+K49) -> 6.7335594 | L50: =K50*(1+L49) -> 6.9355662 | ... S50: =R50*(1+S49) -> 8.5298716
A52: 3 | B52: Total savings in cost | D52: =D50+D42+D30+D20+D8 -> 14.425467 | E52: =E50+E42+E30+E20+E8 -> 13.165102 | F52: =F50+F42+F30+F20+F8 -> 13.629605 | G52: =G50+G42+G30+G20+G8 -> 13.281556 | H52: =H50+H42+H30+H20+H8 -> 13.745013 | I52: =I50+I42+I30+I20+I8 -> 14.228053 | J52: =J50+J42+J30+J20+J8 -> 13.899155 | K52: =K50+K42+K30+K20+K8 -> 14.382397 | ... R52: =R50+R42+R30+R20+R8 -> 15.084582

Sheet Project Capex
B2: Month | E2: =Inputs!G3 -> 45566 | F2: =IFERROR(IF(EOMONTH(E2,0.5)+1<=Inputs!$G$5,EOMONTH(E2,0.5)+1,"-"),"-") -> 45597 | G2: =IFERROR(IF(EOMONTH(F2,0.5)+1<=Inputs!$G$5,EOMONTH(F2,0.5)+1,"-"),"-") -> 45627 | H2: =IFERROR(IF(EOMONTH(G2,0.5)+1<=Inputs!$G$5,EOMONTH(G2,0.5)+1,"-"),"-") -> 45658 | I2: =IFERROR(IF(EOMONTH(H2,0.5)+1<=Inputs!$G$5,EOMONTH(H2,0.5)+1,"-"),"-") -> 45689 | J2: =IFERROR(IF(EOMONTH(I2,0.5)+1<=Inputs!$G$5,EOMONTH(I2,0.5)+1,"-"),"-") -> 45717 | K2: =IFERROR(IF(EOMONTH(J2,0.5)+1<=Inputs!$G$5,EOMONTH(J2,0.5)+1,"-"),"-") -> 45748 | L2: =IFERROR(IF(EOMONTH(K2,0.5)+1<=Inputs!$G$5,EOMONTH(K2,0.5)+1,"-"),"-") -> 45778 | M2: =IFERROR(IF(EOMONTH(L2,0.5)+1<=Inputs!$G$5,EOMONTH(L2,0.5)+1,"-"),"-") -> 45809 | ... AG2: =IFERROR(IF(EOMONTH(AF2,0.5)+1<=Inputs!$G$5,EOMONTH(AF2,0.5)+1,"-"),"-") -> - | BB2: 1 | BC2: Jan | BD2: Q4
B3: Quarter | E3: =IFERROR((VLOOKUP(MONTH(E2),$BB$2:$BD$13,3,FALSE) & " " & IF(OR(MONTH(E2)=1,MONTH(E2)=2,MONTH(E2)=3),YEAR(E2),YEAR(E2)+1)),"-") -> Q3 2025 | F3: =IFERROR((VLOOKUP(MONTH(F2),$BB$2:$BD$13,3,FALSE) & " " & IF(OR(MONTH(F2)=1,MONTH(F2)=2,MONTH(F2)=3),YEAR(F2),YEAR(F2)+1)),"-") -> Q3 2025 | G3: =IFERROR((VLOOKUP(MONTH(G2),$BB$2:$BD$13,3,FALSE) & " " & IF(OR(MONTH(G2)=1,MONTH(G2)=2,MONTH(G2)=3),YEAR(G2),YEAR(G2)+1)),"-") -> Q3 2025 | H3: =IFERROR((VLOOKUP(MONTH(H2),$BB$2:$BD$13,3,FALSE) & " " & IF(OR(MONTH(H2)=1,MONTH(H2)=2,MONTH(H2)=3),YEAR(H2),YEAR(H2)+1)),"-") -> Q4 2025 | I3: =IFERROR((VLOOKUP(MONTH(I2),$BB$2:$BD$13,3,FALSE) & " " & IF(OR(MONTH(I2)=1,MONTH(I2)=2,MONTH(I2)=3),YEAR(I2),YEAR(I2)+1)),"-") -> Q4 2025 | J3: =IFERROR((VLOOKUP(MONTH(J2),$BB$2:$BD$13,3,FALSE) & " " & IF(OR(MONTH(J2)=1,MONTH(J2)=2,MONTH(J2)=3),YEAR(J2),YEAR(J2)+1)),"-") -> Q4 2025 | K3: =IFERROR((VLOOKUP(MONTH(K2),$BB$2:$BD$13,3,FALSE) & " " & IF(OR(MONTH(K2)=1,MONTH(K2)=2,MONTH(K2)=3),YEAR(K2),YEAR(K2)+1)),"-") -> Q1 2026 | L3: =IFERROR((VLOOKUP(MONTH(L2),$BB$2:$BD$13,3,FALSE) & " " & IF(OR(MONTH(L2)=1,MONTH(L2)=2,MONTH(L2)=3),YEAR(L2),YEAR(L2)+1)),"-") -> Q1 2026 | ... AG3: =IFERROR((VLOOKUP(MONTH(AG2),$BB$2:$BD$13,3,FALSE) & " " & IF(OR(MONTH(AG2)=1,MONTH(AG2)=2,MONTH(AG2)=3),YEAR(AG2),YEAR(AG2)+1)),"-") -> - | BB3: =BB2+1 -> 2 | BC3: Feb | BD3: Q4
B4: Year | E4: =IFERROR(("FY " & YEAR(E2)+1),"-") -> FY 2025 | F4: =IFERROR(("FY " & YEAR(F2)+1),"-") -> FY 2025 | G4: =IFERROR(("FY " & YEAR(G2)+1),"-") -> FY 2025 | H4: =IFERROR(("FY " & YEAR(H2)+1),"-") -> FY 2026 | I4: =IFERROR(("FY " & YEAR(I2)+1),"-") -> FY 2026 | J4: =IFERROR(("FY " & YEAR(J2)+1),"-") -> FY 2026 | K4: =IFERROR(("FY " & YEAR(K2)+1),"-") -> FY 2026 | L4: =IFERROR(("FY " & YEAR(L2)+1),"-") -> FY 2026 | ... AG4: =IFERROR(("FY " & YEAR(AG2)+1),"-") -> - | BB4: =BB3+1 -> 3 | BC4: Mar | BD4: Q4
BB5: =BB4+1 -> 4 | BC5: Apr | BD5: Q1
B6: CAPEX | C6: 0.038135593 | BB6: =BB5+1 -> 5 | BC6: May | BD6: Q1
B7: ='Project Cost Details'!B3 -> ASRS | C7: =(1-E8-50%)/2 -> 0.038135593 | BB7: =BB6+1 -> 6 | BC7: Jun | BD7: Q1
B8: ='Project Cost Details'!B4 -> Racking system | C8: =1-E8-L8-M8 -> 0.40423729 | D8: =SUM(E8:AG8) -> 1 | E8: 0.42372881 | J8: 0 | K8: 0 | L8: 0.073728814 | M8: 0.098305085 | N8: 0.14745763 | O8: 0.12288136 | P8: 0.049152542 | Q8: =5%/1.18 -> 0.042372881 | R8: =5%/1.18 -> 0.042372881 | AP8: =AQ8/$AQ$38 -> 0.42372881 | AQ8: 153000000 | AR8: Received | BB8: =BB7+1 -> 7 | BC8: Jul | BD8: Q2
B9: ='Project Cost Details'!B5 -> Cladding for high bay | D9: =SUM(E9:AG9) -> 1 | E9: 0.42372881 | J9: 0 | K9: 0 | L9: 0.073728814 | M9: 0.098305085 | N9: 0.14745763 | O9: 0.12288136 | P9: 0.049152542 | Q9: =5%/1.18 -> 0.042372881 | R9: =5%/1.18 -> 0.042372881 | AP9: =AQ9/$AQ$38 -> 0.073728814 | AQ9: 26622000 | AR9: 45778 | BB9: =BB8+1 -> 8 | BC9: Aug | BD9: Q2
B10: ='Project Cost Details'!B6 -> Double deep Stacker crane | D10: =SUM(E10:AG10) -> 1 | E10: 0.42372881 | J10: 0 | K10: 0 | L10: 0.073728814 | M10: 0.098305085 | N10: 0.14745763 | O10: 0.12288136 | P10: 0.049152542 | Q10: =5%/1.18 -> 0.042372881 | R10: =5%/1.18 -> 0.042372881 | AP10: =AQ10/$AQ$38 -> 0.098305085 | AQ10: 35496000 | AR10: 45809 | BB10: =BB9+1 -> 9 | BC10: Sep | BD10: Q2
B11: ='Project Cost Details'!B7 -> Bottom Rail with aisle accessories | D11: =SUM(E11:AG11) -> 1 | E11: 0.42372881 | J11: 0 | K11: 0 | L11: 0.073728814 | M11: 0.098305085 | N11: 0.14745763 | O11: 0.12288136 | P11: 0.049152542 | Q11: =5%/1.18 -> 0.042372881 | R11: =5%/1.18 -> 0.042372881 | AP11: =AQ11/$AQ$38 -> 0 | BB11: =BB10+1 -> 10 | BC11: Oct | BD11: Q3
B12: ='Project Cost Details'!B8 -> Conveyor system | D12: =SUM(E12:AG12) -> 1 | E12: 0.42372881 | J12: 0 | K12: 0 | L12: 0.073728814 | M12: 0.098305085 | N12: 0.14745763 | O12: 0.12288136 | P12: 0.049152542 | Q12: =5%/1.18 -> 0.042372881 | R12: =5%/1.18 -> 0.042372881 | AP12: =AQ12/$AQ$38 -> 0.14745763 | AQ12: 53244000 | AR12: 45839 | BB12: =BB11+1 -> 11 | BC12: Nov | BD12: Q3
B13: ='Project Cost Details'!B9 -> Critical spares | D13: =SUM(E13:AG13) -> 1 | E13: 0.42372881 | J13: 0 | K13: 0 | L13: 0.073728814 | M13: 0.098305085 | N13: 0.14745763 | O13: 0.12288136 | P13: 0.049152542 | Q13: =5%/1.18 -> 0.042372881 | R13: =5%/1.18 -> 0.042372881 | AP13: =AQ13/$AQ$38 -> 0 | BB13: =BB12+1 -> 12 | BC13: Dec | BD13: Q3
B14: ='Project Cost Details'!B10 -> Metal pallets | D14: =SUM(E14:AG14) -> 1 | E14: 0.42372881 | J14: 0 | K14: 0 | L14: 0.073728814 | M14: 0.098305085 | N14: 0.14745763 | O14: 0.12288136 | P14: 0.049152542 | Q14: =5%/1.18 -> 0.042372881 | R14: =5%/1.18 -> 0.042372881 | AP14: =AQ14/$AQ$38 -> 0
B15: ='Project Cost Details'!B11 -> Discount | D15: =SUM(E15:AG15) -> 1 | E15: 0.42372881 | J15: 0 | K15: 0 | L15: 0.073728814 | M15: 0.098305085 | N15: 0.14745763 | O15: 0.12288136 | P15: 0.049152542 | Q15: =1-SUM(E15:P15) -> 0.084745763 | AP15: =AQ15/$AQ$38 -> 0.12288136 | AQ15: 44370000 | AR15: 45870
B16: ='Project Cost Details'!B12 -> Civil Cost
B17: ='Project Cost Details'!B13 -> Earthworks and soiling | D17: =SUM(E17:AG17) -> 1 | K17: =30% -> 0.3 | L17: 0.6 | M17: 0.1
B18: ='Project Cost Details'!B14 -> PCC works | D18: =SUM(E18:AG18) -> 1 | K18: =30% -> 0.3 | L18: 0.6 | M18: 0.1
B19: ='Project Cost Details'!B15 -> RCC works | D19: =SUM(E19:AG19) -> 1 | K19: =30% -> 0.3 | L19: 0.6 | M19: 0.1
B20: ='Project Cost Details'!B16 -> Shuttering | D20: =SUM(E20:AG20) -> 1 | K20: =30% -> 0.3 | L20: 0.6 | M20: 0.1
B21: ='Project Cost Details'!B17 -> TMT bards Fe 500 | D21: =SUM(E21:AG21) -> 1 | K21: =30% -> 0.3 | L21: 0.6 | M21: 0.1
B22: ='Project Cost Details'!B18 -> Masonary works | D22: =SUM(E22:AG22) -> 1 | K22: =30% -> 0.3 | L22: 0.6 | M22: 0.1
B23: ='Project Cost Details'!B19 -> Plastering | D23: =SUM(E23:AG23) -> 1 | K23: =30% -> 0.3 | L23: 0.6 | M23: 0.1
B24: ='Project Cost Details'!B20 -> VDF Flooring | D24: =SUM(E24:AG24) -> 1 | K24: =30% -> 0.3 | L24: 0.6 | M24: 0.1
B25: ='Project Cost Details'!B21 -> J BOLTS installation | D25: =SUM(E25:AG25) -> 1 | K25: =30% -> 0.3 | L25: 0.6 | M25: 0.1
B26: ='Project Cost Details'!B22 -> Baseplate Grouting | D26: =SUM(E26:AG26) -> 1 | K26: =30% -> 0.3 | L26: 0.6 | M26: 0.1
B27: ='Project Cost Details'!B23 -> Miscellenous | D27: =SUM(E27:AG27) -> 1 | K27: =30% -> 0.3 | L27: 0.6 | M27: 0.1
B28: ='Project Cost Details'!B24 -> Road | D28: =SUM(E28:AG28) -> 1 | M28: 0.1 | N28: 0.2 | O28: 0.2 | P28: 0.2 | Q28: 0.2 | R28: 0.1
B29: ='Project Cost Details'!B25 -> Electrical | D29: =SUM(E29:AG29) -> 0
B30: ='Project Cost Details'!B26 -> CDA | D30: =SUM(E30:AG30) -> 0
B31: ='Project Cost Details'!B27 -> FHS and FAS for the ASRS | D31: =SUM(E31:AG31) -> 0
B32: ='Project Cost Details'!B28 -> Dock levellers | D32: =SUM(E32:AG32) -> 1 | I32: 0.6 | J32: 0.2 | L32: 0.1 | M32: 0.1 | Q32: 0 | R32: 0 | AP32: =AQ32/$AQ$38 -> 0
B33: ='Project Cost Details'!B29 -> Contingency | D33: =SUM(E33:AG33) -> 1 | J33: 0.5 | R33: 0.5 | AP33: =AQ33/$AQ$38 -> 0
B34: ='Project Cost Details'!B30 -> Pre - operating expenses | D34: =SUM(E34:AG34) -> 1 | E34: =1/Inputs!$G$4 -> 0.071428571 | F34: =1/Inputs!$G$4 -> 0.071428571 | G34: =1/Inputs!$G$4 -> 0.071428571 | H34: =1/Inputs!$G$4 -> 0.071428571 | I34: =1/Inputs!$G$4 -> 0.071428571 | J34: =1/Inputs!$G$4 -> 0.071428571 | K34: =1/Inputs!$G$4 -> 0.071428571 | L34: =1/Inputs!$G$4 -> 0.071428571 | ... R34: =1/Inputs!$G$4 -> 0.071428571 | AP34: =AQ34/$AQ$38 -> 0.049152542 | AQ34: 17748000 | AR34: 45901
B35: ='Project Cost Details'!B31 -> IDC | D35: =SUM(E35:AG35) -> 1 | E35: =1/Inputs!$G$4 -> 0.071428571 | F35: =1/Inputs!$G$4 -> 0.071428571 | G35: =1/Inputs!$G$4 -> 0.071428571 | H35: =1/Inputs!$G$4 -> 0.071428571 | I35: =1/Inputs!$G$4 -> 0.071428571 | J35: =1/Inputs!$G$4 -> 0.071428571 | K35: =1/Inputs!$G$4 -> 0.071428571 | L35: =1/Inputs!$G$4 -> 0.071428571 | ... R35: =1/Inputs!$G$4 -> 0.071428571 | AP35: =AQ35/$AQ$38 -> 0
B36: ='Project Cost Details'!B32 -> Finance cost | D36: =SUM(E36:AG36) -> 1 | E36: =1/Inputs!$G$4 -> 0.071428571 | F36: =1/Inputs!$G$4 -> 0.071428571 | G36: =1/Inputs!$G$4 -> 0.071428571 | H36: =1/Inputs!$G$4 -> 0.071428571 | I36: =1/Inputs!$G$4 -> 0.071428571 | J36: =1/Inputs!$G$4 -> 0.071428571 | K36: =1/Inputs!$G$4 -> 0.071428571 | L36: =1/Inputs!$G$4 -> 0.071428571 | ... R36: =1/Inputs!$G$4 -> 0.071428571 | AP36: =AQ36/$AQ$38 -> 0.042372881 | AQ36: 15300000 | AR36: 45931
B37: Total | AP37: =AQ37/$AQ$38 -> 0.042372881 | AQ37: 15300000 | AR37: 45962
AP38: =SUM(AP8:AP37) -> 1 | AQ38: =SUM(AQ8:AQ37) -> 361080000
B39: =B7 -> ASRS | E39: =SUM(E40:E47) -> 15.3 | F39: =SUM(F40:F47) -> 0 | G39: =SUM(G40:G47) -> 0 | H39: =SUM(H40:H47) -> 0 | I39: =SUM(I40:I47) -> 0 | J39: =SUM(J40:J47) -> 0 | K39: =SUM(K40:K47) -> 0 | L39: =SUM(L40:L47) -> 2.6622 | ... R39: =SUM(R40:R47) -> 1.5313838
B40: =B8 -> Racking system | C40: ='Project Cost Details'!G4/10^7 -> 15.04193 | D40: =SUM(E40:AG40) -> 15.04193 | E40: =$C40*E8 -> 6.3736992 | F40: =$C40*F8 -> 0 | G40: =$C40*G8 -> 0 | H40: =$C40*H8 -> 0 | I40: =$C40*I8 -> 0 | J40: =$C40*J8 -> 0 | K40: =$C40*K8 -> 0 | L40: =$C40*L8 -> 1.1090237 | ... AG40: =$C40*AG8 -> 0
B41: =B9 -> Cladding for high bay | C41: ='Project Cost Details'!G5/10^7 -> 1.416 | D41: =SUM(E41:AG41) -> 1.416 | E41: =$C41*E9 -> 0.6 | F41: =$C41*F9 -> 0 | G41: =$C41*G9 -> 0 | H41: =$C41*H9 -> 0 | I41: =$C41*I9 -> 0 | J41: =$C41*J9 -> 0 | K41: =$C41*K9 -> 0 | L41: =$C41*L9 -> 0.1044 | ... AG41: =$C41*AG9 -> 0
B42: =B10 -> Double deep Stacker crane | C42: ='Project Cost Details'!G6/10^7 -> 6.5254 | D42: =SUM(E42:AG42) -> 6.5254 | E42: =$C42*E10 -> 2.765 | F42: =$C42*F10 -> 0 | G42: =$C42*G10 -> 0 | H42: =$C42*H10 -> 0 | I42: =$C42*I10 -> 0 | J42: =$C42*J10 -> 0 | K42: =$C42*K10 -> 0 | L42: =$C42*L10 -> 0.48111 | ... AG42: =$C42*AG10 -> 0
B43: =B11 -> Bottom Rail with aisle accessories | C43: ='Project Cost Details'!G7/10^7 -> 1.5871925 | D43: =SUM(E43:AG43) -> 1.5871925 | E43: =$C43*E11 -> 0.6725392 | F43: =$C43*F11 -> 0 | G43: =$C43*G11 -> 0 | H43: =$C43*H11 -> 0 | I43: =$C43*I11 -> 0 | J43: =$C43*J11 -> 0 | K43: =$C43*K11 -> 0 | L43: =$C43*L11 -> 0.11702182 | ... AG43: =$C43*AG11 -> 0
B44: =B12 -> Conveyor system | C44: ='Project Cost Details'!G8/10^7 -> 1.7582 | D44: =SUM(E44:AG44) -> 1.7582 | E44: =$C44*E12 -> 0.745 | F44: =$C44*F12 -> 0 | G44: =$C44*G12 -> 0 | H44: =$C44*H12 -> 0 | I44: =$C44*I12 -> 0 | J44: =$C44*J12 -> 0 | K44: =$C44*K12 -> 0 | L44: =$C44*L12 -> 0.12963 | ... AG44: =$C44*AG12 -> 0
B45: =B13 -> Critical spares | C45: ='Project Cost Details'!G9/10^7 -> 0.3304 | D45: =SUM(E45:AG45) -> 0.3304 | E45: =$C45*E13 -> 0.14 | F45: =$C45*F13 -> 0 | G45: =$C45*G13 -> 0 | H45: =$C45*H13 -> 0 | I45: =$C45*I13 -> 0 | J45: =$C45*J13 -> 0 | K45: =$C45*K13 -> 0 | L45: =$C45*L13 -> 0.02436 | ... AG45: =$C45*AG13 -> 0
B46: =B14 -> Metal pallets | C46: ='Project Cost Details'!G10/10^7 -> 9.481536 | D46: =SUM(E46:AG46) -> 9.481536 | E46: =$C46*E14 -> 4.0176 | F46: =$C46*F14 -> 0 | G46: =$C46*G14 -> 0 | H46: =$C46*H14 -> 0 | I46: =$C46*I14 -> 0 | J46: =$C46*J14 -> 0 | K46: =$C46*K14 -> 0 | L46: =$C46*L14 -> 0.6990624 | ... AG46: =$C46*AG14 -> 0
B47: =B15 -> Discount | C47: ='Project Cost Details'!G11/10^7 -> -0.032658624 | D47: =SUM(E47:AG47) -> -0.032658624 | E47: =$C47*E15 -> -0.0138384 | F47: =$C47*F15 -> 0 | G47: =$C47*G15 -> 0 | H47: =$C47*H15 -> 0 | I47: =$C47*I15 -> 0 | J47: =$C47*J15 -> 0 | K47: =$C47*K15 -> 0 | L47: =$C47*L15 -> -0.0024078816 | ... AG47: =$C47*AG15 -> 0
B48: =B16 -> Civil Cost
B49: =B17 -> Earthworks and soiling | C49: ='Project Cost Details'!G13/10^7 -> 1.593 | D49: =SUM(E49:AG49) -> 1.593 | E49: =$C49*E17 -> 0 | F49: =$C49*F17 -> 0 | G49: =$C49*G17 -> 0 | H49: =$C49*H17 -> 0 | I49: =$C49*I17 -> 0 | J49: =$C49*J17 -> 0 | K49: =$C49*K17 -> 0.4779 | L49: =$C49*L17 -> 0.9558 | ... AG49: =$C49*AG17 -> 0
B50: =B18 -> PCC works | C50: ='Project Cost Details'!G14/10^7 -> 0.531 | D50: =SUM(E50:AG50) -> 0.531 | E50: =$C50*E18 -> 0 | F50: =$C50*F18 -> 0 | G50: =$C50*G18 -> 0 | H50: =$C50*H18 -> 0 | I50: =$C50*I18 -> 0 | J50: =$C50*J18 -> 0 | K50: =$C50*K18 -> 0.1593 | L50: =$C50*L18 -> 0.3186 | ... AG50: =$C50*AG18 -> 0
B51: =B19 -> RCC works | C51: ='Project Cost Details'!G15/10^7 -> 3.54 | D51: =SUM(E51:AG51) -> 3.54 | E51: =$C51*E19 -> 0 | F51: =$C51*F19 -> 0 | G51: =$C51*G19 -> 0 | H51: =$C51*H19 -> 0 | I51: =$C51*I19 -> 0 | J51: =$C51*J19 -> 0 | K51: =$C51*K19 -> 1.062 | L51: =$C51*L19 -> 2.124 | ... AG51: =$C51*AG19 -> 0
B52: =B20 -> Shuttering | C52: ='Project Cost Details'!G16/10^7 -> 0.1475 | D52: =SUM(E52:AG52) -> 0.1475 | E52: =$C52*E20 -> 0 | F52: =$C52*F20 -> 0 | G52: =$C52*G20 -> 0 | H52: =$C52*H20 -> 0 | I52: =$C52*I20 -> 0 | J52: =$C52*J20 -> 0 | K52: =$C52*K20 -> 0.04425 | L52: =$C52*L20 -> 0.0885 | ... AG52: =$C52*AG20 -> 0
B53: =B21 -> TMT bards Fe 500 | C53: ='Project Cost Details'!G17/10^7 -> 2.478 | D53: =SUM(E53:AG53) -> 2.478 | E53: =$C53*E21 -> 0 | F53: =$C53*F21 -> 0 | G53: =$C53*G21 -> 0 | H53: =$C53*H21 -> 0 | I53: =$C53*I21 -> 0 | J53: =$C53*J21 -> 0 | K53: =$C53*K21 -> 0.7434 | L53: =$C53*L21 -> 1.4868 | ... AG53: =$C53*AG21 -> 0
B54: =B22 -> Masonary works | C54: ='Project Cost Details'!G18/10^7 -> 0.0708 | D54: =SUM(E54:AG54) -> 0.0708 | E54: =$C54*E22 -> 0 | F54: =$C54*F22 -> 0 | G54: =$C54*G22 -> 0 | H54: =$C54*H22 -> 0 | I54: =$C54*I22 -> 0 | J54: =$C54*J22 -> 0 | K54: =$C54*K22 -> 0.02124 | L54: =$C54*L22 -> 0.04248 | ... AG54: =$C54*AG22 -> 0
B55: =B23 -> Plastering | C55: ='Project Cost Details'!G19/10^7 -> 0.057525 | D55: =SUM(E55:AG55) -> 0.057525 | E55: =$C55*E23 -> 0 | F55: =$C55*F23 -> 0 | G55: =$C55*G23 -> 0 | H55: =$C55*H23 -> 0 | I55: =$C55*I23 -> 0 | J55: =$C55*J23 -> 0 | K55: =$C55*K23 -> 0.0172575 | L55: =$C55*L23 -> 0.034515 | ... AG55: =$C55*AG23 -> 0
B56: =B24 -> VDF Flooring | C56: ='Project Cost Details'!G20/10^7 -> 0.08496 | D56: =SUM(E56:AG56) -> 0.08496 | E56: =$C56*E24 -> 0 | F56: =$C56*F24 -> 0 | G56: =$C56*G24 -> 0 | H56: =$C56*H24 -> 0 | I56: =$C56*I24 -> 0 | J56: =$C56*J24 -> 0 | K56: =$C56*K24 -> 0.025488 | L56: =$C56*L24 -> 0.050976 | ... AG56: =$C56*AG24 -> 0
B57: =B25 -> J BOLTS installation | C57: ='Project Cost Details'!G21/10^7 -> 0.1888 | D57: =SUM(E57:AG57) -> 0.1888 | E57: =$C57*E25 -> 0 | F57: =$C57*F25 -> 0 | G57: =$C57*G25 -> 0 | H57: =$C57*H25 -> 0 | I57: =$C57*I25 -> 0 | J57: =$C57*J25 -> 0 | K57: =$C57*K25 -> 0.05664 | L57: =$C57*L25 -> 0.11328 | ... AG57: =$C57*AG25 -> 0
B58: =B26 -> Baseplate Grouting | C58: ='Project Cost Details'!G22/10^7 -> 0.10384 | D58: =SUM(E58:AG58) -> 0.10384 | E58: =$C58*E26 -> 0 | F58: =$C58*F26 -> 0 | G58: =$C58*G26 -> 0 | H58: =$C58*H26 -> 0 | I58: =$C58*I26 -> 0 | J58: =$C58*J26 -> 0 | K58: =$C58*K26 -> 0.031152 | L58: =$C58*L26 -> 0.062304 | ... AG58: =$C58*AG26 -> 0
B59: =B27 -> Miscellenous | C59: ='Project Cost Details'!G23/10^7 -> 0.1416 | D59: =SUM(E59:AG59) -> 0.1416 | E59: =$C59*E27 -> 0 | F59: =$C59*F27 -> 0 | G59: =$C59*G27 -> 0 | H59: =$C59*H27 -> 0 | I59: =$C59*I27 -> 0 | J59: =$C59*J27 -> 0 | K59: =$C59*K27 -> 0.04248 | L59: =$C59*L27 -> 0.08496 | ... AG59: =$C59*AG27 -> 0
B60: =B28 -> Road | C60: ='Project Cost Details'!G24/10^7 -> 1.6905075 | D60: =SUM(E60:AG60) -> 1.6905075 | E60: =$C60*E28 -> 0 | F60: =$C60*F28 -> 0 | G60: =$C60*G28 -> 0 | H60: =$C60*H28 -> 0 | I60: =$C60*I28 -> 0 | J60: =$C60*J28 -> 0 | K60: =$C60*K28 -> 0 | L60: =$C60*L28 -> 0 | ... AG60: =$C60*AG28 -> 0
... B68: =B36 -> Finance cost | C68: ='Project Cost Details'!G32/10^7 -> 0.26948281 | D68: =SUM(E68:AG68) -> 0.26948281 | E68: =$C68*E36 -> 0.019248772 | F68: =$C68*F36 -> 0.019248772 | G68: =$C68*G36 -> 0.019248772 | H68: =$C68*H36 -> 0.019248772 | I68: =$C68*I36 -> 0.019248772 | J68: =$C68*J36 -> 0.019248772 | K68: =$C68*K36 -> 0.019248772 | L68: =$C68*L36 -> 0.019248772 | ... AG68: =$C68*AG36 -> 0
B69: Total | C69: =SUM(C40:C68) -> 54.166044 | D69: =SUM(D40:D68) -> 54.166044 | E69: =SUM(E40:E68) -> 15.600953 | F69: =SUM(F40:F68) -> 0.30095298 | G69: =SUM(G40:G68) -> 0.30095298 | H69: =SUM(H40:H68) -> 0.30095298 | I69: =SUM(I40:I68) -> 0.80403491 | J69: =SUM(J40:J68) -> 1.657997 | ... AG69: =SUM(AG40:AG68) -> 0
B71: Debt | E71: ='Term Loan'!C40 -> 15.600953 | F71: ='Term Loan'!D40 -> 0.30095298 | G71: ='Term Loan'!E40 -> 0.30095298 | H71: ='Term Loan'!F40 -> 0.30095298 | I71: ='Term Loan'!G40 -> 0.80403491 | J71: ='Term Loan'!H40 -> 1.657997 | K71: ='Term Loan'!I40 -> 2.9820605 | L71: ='Term Loan'!J40 -> 8.409215 | ... AG71: ='Term Loan'!AE40 -> 0
B72: Equity | E72: ='Term Loan'!C35 -> 5.4166044e-11 | F72: ='Term Loan'!D35 -> 0 | G72: ='Term Loan'!E35 -> 0 | H72: ='Term Loan'!F35 -> 0 | I72: ='Term Loan'!G35 -> 0 | J72: ='Term Loan'!H35 -> 0 | K72: ='Term Loan'!I35 -> 0 | L72: ='Term Loan'!J35 -> 0 | ... AG72: ='Term Loan'!AE35 -> 0

Sheet Term Loan
B2: Project Details | F2: Month | G2: Qtr | I2: Year | J2: 0 | K2: 1 | L2: 2 | M2: =L2+1 -> 3 | N2: =M2+1 -> 4 | O2: =N2+1 -> 5 | P2: =O2+1 -> 6 | Q2: =P2+1 -> 7 | R2: =Q2+1 -> 8 | S2: =R2+1 -> 9 | T2: =S2+1 -> 10 | ... AF2: =AE2+1 -> 22
B3: Total project cost | C3: ='Project Capex'!D69 -> 54.166044 | D3: Crore | F3: 1 | G3: Q4 | I3: Interest Rate | J3: 0.095 | K3: 0.095 | L3: 0.095 | M3: 0.095 | N3: 0.095 | O3: 0.095 | P3: 0.095 | Q3: 0.095 | R3: 0.095 | S3: 0.095 | T3: 0.095 | U3: 0.095 | V3: 0.095 | W3: 0.095 | X3: 0.095 | Y3: 0.095 | Z3: 0.095 | AA3: 0.095 | AB3: 0.095 | AC3: 0.095 | AD3: 0.095 | AE3: 0.095 | AF3: 0.095
B4: Equity | C4: ='Project Cost Details'!G39/10^7 -> 5.4166044e-11 | D4: Crore | F4: 2 | G4: Q4
B5: Debt | C5: ='Project Cost Details'!G38/10^7 -> 54.166044 | D5: Crore | F5: 3 | G5: Q4
B6: Total period of loan | C6: =Inputs!D4 -> 15 | D6: years | F6: =F5+1 -> 4 | G6: Q1
B7: Total months | C7: =C6*12 -> 180 | D7: month | F7: =F6+1 -> 5 | G7: Q1
B8: Total quarter | C8: =C6*4 -> 60 | D8: quarter | F8: =F7+1 -> 6 | G8: Q1
F9: =F8+1 -> 7 | G9: Q2
B10: Loan | F10: =F9+1 -> 8 | G10: Q2
B11: Total loan repayment months | C11: =C6*12-C15 -> 174 | D11: months | F11: =F10+1 -> 9 | G11: Q2
B12: Total quarter | C12: =C6*4-ROUNDDOWN(C15/3,0) -> 58 | D12: quarter | F12: =F11+1 -> 10 | G12: Q3
B13: Interest | C13: 0 | D13: Crore | F13: =F12+1 -> 11 | G13: Q3
B14: IDC | C14: =A31 -> 3.4026072 | D14: Crore | F14: =F13+1 -> 12 | G14: Q3
B15: Moratorium period | C15: 6 | D15: months
B16: Type of payment | C16: Annually
B19: Type | C19: =IF(C20<=Inputs!$G$5,"Cons","Beyond Cons") -> Cons | D19: =IF(D20<=Inputs!$G$5,"Cons","Beyond Cons") -> Cons | E19: =IF(E20<=Inputs!$G$5,"Cons","Beyond Cons") -> Cons | F19: =IF(F20<=Inputs!$G$5,"Cons","Beyond Cons") -> Cons | G19: =IF(G20<=Inputs!$G$5,"Cons","Beyond Cons") -> Cons | H19: =IF(H20<=Inputs!$G$5,"Cons","Beyond Cons") -> Cons | I19: =IF(I20<=Inputs!$G$5,"Cons","Beyond Cons") -> Cons | J19: =IF(J20<=Inputs!$G$5,"Cons","Beyond Cons") -> Cons | ... IC19: =IF(IC20<=Inputs!$G$5,"Cons","Beyond Cons") -> Beyond Cons
B20: Month | C20: =Inputs!G3 -> 45566 | D20: =IFERROR(IF(EOMONTH(C20,0.5)+1<=EOMONTH(Inputs!$G$5,$C$7),EOMONTH(C20,0.5)+1,"-"),"-") -> 45597 | E20: =IFERROR(IF(EOMONTH(D20,0.5)+1<=EOMONTH(Inputs!$G$5,$C$7),EOMONTH(D20,0.5)+1,"-"),"-") -> 45627 | F20: =IFERROR(IF(EOMONTH(E20,0.5)+1<=EOMONTH(Inputs!$G$5,$C$7),EOMONTH(E20,0.5)+1,"-"),"-") -> 45658 | G20: =IFERROR(IF(EOMONTH(F20,0.5)+1<=EOMONTH(Inputs!$G$5,$C$7),EOMONTH(F20,0.5)+1,"-"),"-") -> 45689 | H20: =IFERROR(IF(EOMONTH(G20,0.5)+1<=EOMONTH(Inputs!$G$5,$C$7),EOMONTH(G20,0.5)+1,"-"),"-") -> 45717 | I20: =IFERROR(IF(EOMONTH(H20,0.5)+1<=EOMONTH(Inputs!$G$5,$C$7),EOMONTH(H20,0.5)+1,"-"),"-") -> 45748 | J20: =IFERROR(IF(EOMONTH(I20,0.5)+1<=EOMONTH(Inputs!$G$5,$C$7),EOMONTH(I20,0.5)+1,"-"),"-") -> 45778 | K20: =IFERROR(IF(EOMONTH(J20,0.5)+1<=EOMONTH(Inputs!$G$5,$C$7),EOMONTH(J20,0.5)+1,"-"),"-") -> 45809 | ... IC20: =IFERROR(IF(EOMONTH(IB20,0.5)+1<=EOMONTH(Inputs!$G$5,$C$7),EOMONTH(IB20,0.5)+1,"-"),"-") -> -
B21: Quarter | C21: =IFERROR((VLOOKUP(MONTH(C20),$F$3:$G$14,2,FALSE) & " " & IF(OR(MONTH(C20)=1,MONTH(C20)=2,MONTH(C20)=3),YEAR(C20),YEAR(C20)+1)),"-") -> Q3 2025 | D21: =IFERROR((VLOOKUP(MONTH(D20),$F$3:$G$14,2,FALSE) & " " & IF(OR(MONTH(D20)=1,MONTH(D20)=2,MONTH(D20)=3),YEAR(D20),YEAR(D20)+1)),"-") -> Q3 2025 | E21: =IFERROR((VLOOKUP(MONTH(E20),$F$3:$G$14,2,FALSE) & " " & IF(OR(MONTH(E20)=1,MONTH(E20)=2,MONTH(E20)=3),YEAR(E20),YEAR(E20)+1)),"-") -> Q3 2025 | F21: =IFERROR((VLOOKUP(MONTH(F20),$F$3:$G$14,2,FALSE) & " " & IF(OR(MONTH(F20)=1,MONTH(F20)=2,MONTH(F20)=3),YEAR(F20),YEAR(F20)+1)),"-") -> Q4 2025 | G21: =IFERROR((VLOOKUP(MONTH(G20),$F$3:$G$14,2,FALSE) & " " & IF(OR(MONTH(G20)=1,MONTH(G20)=2,MONTH(G20)=3),YEAR(G20),YEAR(G20)+1)),"-") -> Q4 2025 | H21: =IFERROR((VLOOKUP(MONTH(H20),$F$3:$G$14,2,FALSE) & " " & IF(OR(MONTH(H20)=1,MONTH(H20)=2,MONTH(H20)=3),YEAR(H20),YEAR(H20)+1)),"-") -> Q4 2025 | I21: =IFERROR((VLOOKUP(MONTH(I20),$F$3:$G$14,2,FALSE) & " " & IF(OR(MONTH(I20)=1,MONTH(I20)=2,MONTH(I20)=3),YEAR(I20),YEAR(I20)+1)),"-") -> Q1 2026 | J21: =IFERROR((VLOOKUP(MONTH(J20),$F$3:$G$14,2,FALSE) & " " & IF(OR(MONTH(J20)=1,MONTH(J20)=2,MONTH(J20)=3),YEAR(J20),YEAR(J20)+1)),"-") -> Q1 2026 | ... IC21: =IFERROR((VLOOKUP(MONTH(IC20),$F$3:$G$14,2,FALSE) & " " & IF(OR(MONTH(IC20)=1,MONTH(IC20)=2,MONTH(IC20)=3),YEAR(IC20),YEAR(IC20)+1)),"-") -> -
B22: Year | C22: =IFERROR(("FY " & IF(OR(MONTH(C20)=1,MONTH(C20)=2,MONTH(C20)=3),YEAR(C20),YEAR(C20)+1)),"-") -> FY 2025 | D22: =IFERROR(("FY " & IF(OR(MONTH(D20)=1,MONTH(D20)=2,MONTH(D20)=3),YEAR(D20),YEAR(D20)+1)),"-") -> FY 2025 | E22: =IFERROR(("FY " & IF(OR(MONTH(E20)=1,MONTH(E20)=2,MONTH(E20)=3),YEAR(E20),YEAR(E20)+1)),"-") -> FY 2025 | F22: =IFERROR(("FY " & IF(OR(MONTH(F20)=1,MONTH(F20)=2,MONTH(F20)=3),YEAR(F20),YEAR(F20)+1)),"-") -> FY 2025 | G22: =IFERROR(("FY " & IF(OR(MONTH(G20)=1,MONTH(G20)=2,MONTH(G20)=3),YEAR(G20),YEAR(G20)+1)),"-") -> FY 2025 | H22: =IFERROR(("FY " & IF(OR(MONTH(H20)=1,MONTH(H20)=2,MONTH(H20)=3),YEAR(H20),YEAR(H20)+1)),"-") -> FY 2025 | I22: =IFERROR(("FY " & IF(OR(MONTH(I20)=1,MONTH(I20)=2,MONTH(I20)=3),YEAR(I20),YEAR(I20)+1)),"-") -> FY 2026 | J22: =IFERROR(("FY " & IF(OR(MONTH(J20)=1,MONTH(J20)=2,MONTH(J20)=3),YEAR(J20),YEAR(J20)+1)),"-") -> FY 2026 | ... IC22: =IFERROR(("FY " & IF(OR(MONTH(IC20)=1,MONTH(IC20)=2,MONTH(IC20)=3),YEAR(IC20),YEAR(IC20)+1)),"-") -> -
B23: Count | C23: =IF(C19="Cons",0,1) -> 0 | D23: =IF(D19="Cons",0,IF(D20="-",0,C23+1)) -> 0 | E23: =IF(E19="Cons",0,IF(E20="-",0,D23+1)) -> 0 | F23: =IF(F19="Cons",0,IF(F20="-",0,E23+1)) -> 0 | G23: =IF(G19="Cons",0,IF(G20="-",0,F23+1)) -> 0 | H23: =IF(H19="Cons",0,IF(H20="-",0,G23+1)) -> 0 | I23: =IF(I19="Cons",0,IF(I20="-",0,H23+1)) -> 0 | J23: =IF(J19="Cons",0,IF(J20="-",0,I23+1)) -> 0 | K23: =IF(K19="Cons",0,IF(K20="-",0,J23+1)) -> 0 | ... IC23: =IF(IC19="Cons",0,IF(IC20="-",0,IB23+1)) -> 0
B24: Qtr | C24: =IF(C23=0,0,MOD(C23,3)) -> 0 | D24: =IF(D23=0,0,ROUNDUP(D23/3,0)) -> 0 | E24: =IF(E23=0,0,ROUNDUP(E23/3,0)) -> 0 | F24: =IF(F23=0,0,ROUNDUP(F23/3,0)) -> 0 | G24: =IF(G23=0,0,ROUNDUP(G23/3,0)) -> 0 | H24: =IF(H23=0,0,ROUNDUP(H23/3,0)) -> 0 | I24: =IF(I23=0,0,ROUNDUP(I23/3,0)) -> 0 | J24: =IF(J23=0,0,ROUNDUP(J23/3,0)) -> 0 | K24: =IF(K23=0,0,ROUNDUP(K23/3,0)) -> 0 | ... IC24: =IF(IC23=0,0,ROUNDUP(IC23/3,0)) -> 0
B25: Year | C25: =IF(C23=0,0,MOD(C23,12)) -> 0 | D25: =IF(D23=0,0,ROUNDUP(D23/12,0)) -> 0 | E25: =IF(E23=0,0,ROUNDUP(E23/12,0)) -> 0 | F25: =IF(F23=0,0,ROUNDUP(F23/12,0)) -> 0 | G25: =IF(G23=0,0,ROUNDUP(G23/12,0)) -> 0 | H25: =IF(H23=0,0,ROUNDUP(H23/12,0)) -> 0 | I25: =IF(I23=0,0,ROUNDUP(I23/12,0)) -> 0 | J25: =IF(J23=0,0,ROUNDUP(J23/12,0)) -> 0 | K25: =IF(K23=0,0,ROUNDUP(K23/12,0)) -> 0 | ... IC25: =IF(IC23=0,0,ROUNDUP(IC23/12,0)) -> 0
B27: Interest Rate | C27: =HLOOKUP(C25,$J$2:$AF$3,2,FALSE)/12 -> 0.0079166667 | D27: =HLOOKUP(D25,$J$2:$AF$3,2,FALSE)/12 -> 0.0079166667 | E27: =HLOOKUP(E25,$J$2:$AF$3,2,FALSE)/12 -> 0.0079166667 | F27: =HLOOKUP(F25,$J$2:$AF$3,2,FALSE)/12 -> 0.0079166667 | G27: =HLOOKUP(G25,$J$2:$AF$3,2,FALSE)/12 -> 0.0079166667 | H27: =HLOOKUP(H25,$J$2:$AF$3,2,FALSE)/12 -> 0.0079166667 | I27: =HLOOKUP(I25,$J$2:$AF$3,2,FALSE)/12 -> 0.0079166667 | J27: =HLOOKUP(J25,$J$2:$AF$3,2,FALSE)/12 -> 0.0079166667 | ... IC27: =HLOOKUP(IC25,$J$2:$AF$3,2,FALSE)/12 -> 0.0079166667
B29: CAPEX requirement | C29: =IFERROR(_xlfn.XLOOKUP(C20,'Project Capex'!$E$2:$X$2,'Project Capex'!$E$69:$X$69),0) -> 15.600953 | D29: =IFERROR(_xlfn.XLOOKUP(D20,'Project Capex'!$E$2:$X$2,'Project Capex'!$E$69:$X$69),0) -> 0.30095298 | E29: =IFERROR(_xlfn.XLOOKUP(E20,'Project Capex'!$E$2:$X$2,'Project Capex'!$E$69:$X$69),0) -> 0.30095298 | F29: =IFERROR(_xlfn.XLOOKUP(F20,'Project Capex'!$E$2:$X$2,'Project Capex'!$E$69:$X$69),0) -> 0.30095298 | G29: =IFERROR(_xlfn.XLOOKUP(G20,'Project Capex'!$E$2:$X$2,'Project Capex'!$E$69:$X$69),0) -> 0.80403491 | H29: =IFERROR(_xlfn.XLOOKUP(H20,'Project Capex'!$E$2:$X$2,'Project Capex'!$E$69:$X$69),0) -> 1.657997 | I29: =IFERROR(_xlfn.XLOOKUP(I20,'Project Capex'!$E$2:$X$2,'Project Capex'!$E$69:$X$69),0) -> 2.9820605 | J29: =IFERROR(_xlfn.XLOOKUP(J20,'Project Capex'!$E$2:$X$2,'Project Capex'!$E$69:$X$69),0) -> 8.409215 | ... W29: =IFERROR(_xlfn.XLOOKUP(W20,'Project Capex'!$E$2:$X$2,'Project Capex'!$E$69:$X$69),0) -> 0
B30: IDC | C30: =IF(C29>$C$4,C29-C4,0) -> 15.600953 | D30: =IF(SUM($C$29:D29)<=$C$4,0,D29) -> 0.30095298 | E30: =IF(SUM($C$29:E29)<=$C$4,0,E29) -> 0.30095298 | F30: =IF(SUM($C$29:F29)<=$C$4,0,F29) -> 0.30095298 | G30: =IF(SUM($C$29:G29)<=$C$4,0,G29) -> 0.80403491 | H30: =IF(SUM($C$29:H29)<=$C$4,0,H29) -> 1.657997 | I30: =IF(SUM($C$29:I29)<=$C$4,0,I29) -> 2.9820605 | J30: =IF(SUM($C$29:J29)<=$C$4,0,J29) -> 8.409215 | K30: =IF(SUM($C$29:K29)<=$C$4,0,K29) -> 4.9971532 | ... W30: =IF(SUM($C$29:W29)<=$C$4,0,W29) -> 0
A31: =SUM(C31:P31) -> 3.4026072 | B31: IDC | C31: =C30*C27 -> 0.12350754 | D31: =SUM($C$30:D30)*D27 -> 0.12589009 | E31: =SUM($C$30:E30)*E27 -> 0.12827263 | F31: =SUM($C$30:F30)*F27 -> 0.13065518 | G31: =SUM($C$30:G30)*G27 -> 0.13702045 | H31: =SUM($C$30:H30)*H27 -> 0.15014626 | I31: =SUM($C$30:I30)*I27 -> 0.17375424 | J31: =SUM($C$30:J30)*J27 -> 0.24032719 | K31: =SUM($C$30:K30)*K27 -> 0.27988799 | ... P31: =SUM($C$30:P30)*P27 -> 0.42881452
B32: Fundings
B33: Equity funding
B34: Opening Balance | C34: 0 | D34: =IF(D19="Cons",C36,0) -> 5.4166044e-11 | E34: =IF(E19="Cons",D36,0) -> 5.4166044e-11 | F34: =IF(F19="Cons",E36,0) -> 5.4166044e-11 | G34: =IF(G19="Cons",F36,0) -> 1.0833209e-10 | H34: =IF(H19="Cons",G36,0) -> 1.0833209e-10 | I34: =IF(I19="Cons",H36,0) -> 1.0833209e-10 | J34: =IF(J19="Cons",I36,0) -> 5.4166044e-11 | K34: =IF(K19="Cons",J36,0) -> 1.0833209e-10 | ... IC34: =IF(IC19="Cons",IB36,0) -> 0
B35: Disbursement | C35: =IF(C19="Cons",MIN(C29,C4),0) -> 5.4166044e-11 | D35: =IF(D19="Cons",IF(D34>=$C$4,0,MIN(D29,$C$4)),0) -> 5.4166044e-11 | E35: =IF(E19="Cons",IF(E34>=$C$4,0,MIN(E29,$C$4)),0) -> 5.4166044e-11 | F35: =IF(F19="Cons",IF(F34>=$C$4,0,MIN(F29,$C$4)),0) -> 5.4166044e-11 | G35: =IF(G19="Cons",IF(G34>=$C$4,0,MIN(G29,$C$4)),0) -> 0 | H35: =IF(H19="Cons",IF(H34>=$C$4,0,MIN(H29,$C$4)),0) -> 0 | I35: =IF(I19="Cons",IF(I34>=$C$4,0,MIN(I29,$C$4)),0) -> 0 | J35: =IF(J19="Cons",IF(J34>=$C$4,0,MIN(J29,$C$4)),0) -> 5.4166044e-11 | K35: =IF(K19="Cons",IF(K34>=$C$4,0,MIN(K29,$C$4)),0) -> 0 | ... IC35: =IF(IC19="Cons",IF(IC34>=$C$4,0,MIN(IC29,$C$4)),0) -> 0
B36: Closing Balance | C36: =C35+C34 -> 5.4166044e-11 | D36: =D35+D34 -> 1.0833209e-10 | E36: =E35+E34 -> 1.0833209e-10 | F36: =F35+F34 -> 1.0833209e-10 | G36: =G35+G34 -> 1.0833209e-10 | H36: =H35+H34 -> 1.0833209e-10 | I36: =I35+I34 -> 1.0833209e-10 | J36: =J35+J34 -> 1.0833209e-10 | ... IC36: =IC35+IC34 -> 0
B38: Debt funding
B39: Opening Balance | C39: 0 | D39: =IF(D19="Cons",C41,0) -> 15.600953 | E39: =IF(E19="Cons",D41,0) -> 15.901906 | F39: =IF(F19="Cons",E41,0) -> 16.202859 | G39: =IF(G19="Cons",F41,0) -> 16.503812 | H39: =IF(H19="Cons",G41,0) -> 17.307847 | I39: =IF(I19="Cons",H41,0) -> 18.965844 | J39: =IF(J19="Cons",I41,0) -> 21.947904 | K39: =IF(K19="Cons",J41,0) -> 30.357119 | ... IC39: =IF(IC19="Cons",IB41,0) -> 0
B40: Disbursement | C40: =IF(C19="Cons",IF(ROUND(C36,2)=ROUND($C$4,2),C29-C35),0) -> 15.600953 | D40: =IF(D19="Cons",IF(ROUND(D36,2)=ROUND($C$4,2),D29-D35),0) -> 0.30095298 | E40: =IF(E19="Cons",IF(ROUND(E36,2)=ROUND($C$4,2),E29-E35),0) -> 0.30095298 | F40: =IF(F19="Cons",IF(ROUND(F36,2)=ROUND($C$4,2),F29-F35),0) -> 0.30095298 | G40: =IF(G19="Cons",IF(ROUND(G36,2)=ROUND($C$4,2),G29-G35),0) -> 0.80403491 | H40: =IF(H19="Cons",IF(ROUND(H36,2)=ROUND($C$4,2),H29-H35),0) -> 1.657997 | I40: =IF(I19="Cons",IF(ROUND(I36,2)=ROUND($C$4,2),I29-I35),0) -> 2.9820605 | J40: =IF(J19="Cons",IF(ROUND(J36,2)=ROUND($C$4,2),J29-J35),0) -> 8.409215 | ... IC40: =IF(IC19="Cons",IF(ROUND(IC36,2)=ROUND($C$4,2),IC29-IC35),0) -> 0
B41: Closing Balance | C41: =C39+C40 -> 15.600953 | D41: =D39+D40 -> 15.901906 | E41: =E39+E40 -> 16.202859 | F41: =F39+F40 -> 16.503812 | G41: =G39+G40 -> 17.307847 | H41: =H39+H40 -> 18.965844 | I41: =I39+I40 -> 21.947904 | J41: =J39+J40 -> 30.357119 | ... IC41: =IC39+IC40 -> 0
B43: Repayments
A44: =SUM(C44:IC44) -> 3.4026072 | B44: IDC | C44: =C41*C27 -> 0.12350754 | D44: =D41*D27 -> 0.12589009 | E44: =E41*E27 -> 0.12827263 | F44: =F41*F27 -> 0.13065518 | G44: =G41*G27 -> 0.13702045 | H44: =H41*H27 -> 0.15014626 | I44: =I41*I27 -> 0.17375424 | J44: =J41*J27 -> 0.24032719 | ... IC44: =IC41*IC27 -> 0
B46: Interest
B47: Opening Balance | C47: =IF(C19="Cons",0,$C$5) -> 0 | D47: =IF(D19="Cons",0,IF(D19<>C19,$C$5,C49)) -> 0 | E47: =IF(E19="Cons",0,IF(E19<>D19,$C$5,D49)) -> 0 | F47: =IF(F19="Cons",0,IF(F19<>E19,$C$5,E49)) -> 0 | G47: =IF(G19="Cons",0,IF(G19<>F19,$C$5,F49)) -> 0 | H47: =IF(H19="Cons",0,IF(H19<>G19,$C$5,G49)) -> 0 | I47: =IF(I19="Cons",0,IF(I19<>H19,$C$5,H49)) -> 0 | J47: =IF(J19="Cons",0,IF(J19<>I19,$C$5,I49)) -> 0 | K47: =IF(K19="Cons",0,IF(K19<>J19,$C$5,J49)) -> 0 | ... P47: =IF(P19="Cons",0,IF(P19<>O19,$C$5,O49)) -> 0 | Q47: =IF(Q19="Cons",0,IF(Q19<>P19,$C$5+$C$13,P49)) -> 54.166044 | R47: =IF(R19="Cons",0,IF(R19<>Q19,$C$5,Q49)) -> 54.166044 | S47: =IF(S19="Cons",0,IF(S19<>R19,$C$5,R49)) -> 54.166044 | T47: =IF(T19="Cons",0,IF(T19<>S19,$C$5,S49)) -> 54.166044 | U47: =IF(U19="Cons",0,IF(U19<>T19,$C$5,T49)) -> 54.166044 | V47: =IF(V19="Cons",0,IF(V19<>U19,$C$5,U49)) -> 54.166044 | W47: =IF(W19="Cons",0,IF(W19<>V19,$C$5,V49)) -> 54.166044 | X47: =IF(X19="Cons",0,IF(X19<>W19,$C$5,W49)) -> 54.166044 | Y47: =IF(Y19="Cons",0,IF(Y19<>X19,$C$5,X49)) -> 54.166044 | ... IC47: =IF(IC19="Cons",0,IF(IC19<>IB19,$C$5,IB49)) -> -3.3217873e-13
A48: =COUNTIFS(C48:IC48,">0") -> 15 | B48: Repayment | C48: {=IF(C47=0,0,IF(C23<=$C$15,0,_xlfn.IFS($C$16="Monthly",IF(C23=D23,0,($C$5+$C$13)/$C$11),$C$16="Quarterly",IF(C24=D24,0,($C$5+$C$13)/$C$12),$C$16="Annually",IF(C25=D25,0,($C$5+$C$13)/($C$6)*(IF(ROUNDDOWN($C$6,0)<C25,(ROUNDDOWN(C25,0)-$C$6),1))))))} -> 0 | D48: {=IF(D47=0,0,IF(D23<=$C$15,0,_xlfn.IFS($C$16="Monthly",IF(D23=E23,0,($C$5+$C$13)/$C$11),$C$16="Quarterly",IF(D24=E24,0,($C$5+$C$13)/$C$12),$C$16="Annually",IF(D25=E25,0,($C$5+$C$13)/($C$6)*(IF(ROUNDDOWN($C$6,0)<D25,(ROUNDDOWN(D25,0)-$C$6),1))))))} -> 0 | E48: {=IF(E47=0,0,IF(E23<=$C$15,0,_xlfn.IFS($C$16="Monthly",IF(E23=F23,0,($C$5+$C$13)/$C$11),$C$16="Quarterly",IF(E24=F24,0,($C$5+$C$13)/$C$12),$C$16="Annually",IF(E25=F25,0,($C$5+$C$13)/($C$6)*(IF(ROUNDDOWN($C$6,0)<E25,(ROUNDDOWN(E25,0)-$C$6),1))))))} -> 0 | F48: {=IF(F47=0,0,IF(F23<=$C$15,0,_xlfn.IFS($C$16="Monthly",IF(F23=G23,0,($C$5+$C$13)/$C$11),$C$16="Quarterly",IF(F24=G24,0,($C$5+$C$13)/$C$12),$C$16="Annually",IF(F25=G25,0,($C$5+$C$13)/($C$6)*(IF(ROUNDDOWN($C$6,0)<F25,(ROUNDDOWN(F25,0)-$C$6),1))))))} -> 0 | G48: {=IF(G47=0,0,IF(G23<=$C$15,0,_xlfn.IFS($C$16="Monthly",IF(G23=H23,0,($C$5+$C$13)/$C$11),$C$16="Quarterly",IF(G24=H24,0,($C$5+$C$13)/$C$12),$C$16="Annually",IF(G25=H25,0,($C$5+$C$13)/($C$6)*(IF(ROUNDDOWN($C$6,0)<G25,(ROUNDDOWN(G25,0)-$C$6),1))))))} -> 0 | H48: {=IF(H47=0,0,IF(H23<=$C$15,0,_xlfn.IFS($C$16="Monthly",IF(H23=I23,0,($C$5+$C$13)/$C$11),$C$16="Quarterly",IF(H24=I24,0,($C$5+$C$13)/$C$12),$C$16="Annually",IF(H25=I25,0,($C$5+$C$13)/($C$6)*(IF(ROUNDDOWN($C$6,0)<H25,(ROUNDDOWN(H25,0)-$C$6),1))))))} -> 0 | I48: {=IF(I47=0,0,IF(I23<=$C$15,0,_xlfn.IFS($C$16="Monthly",IF(I23=J23,0,($C$5+$C$13)/$C$11),$C$16="Quarterly",IF(I24=J24,0,($C$5+$C$13)/$C$12),$C$16="Annually",IF(I25=J25,0,($C$5+$C$13)/($C$6)*(IF(ROUNDDOWN($C$6,0)<I25,(ROUNDDOWN(I25,0)-$C$6),1))))))} -> 0 | J48: {=IF(J47=0,0,IF(J23<=$C$15,0,_xlfn.IFS($C$16="Monthly",IF(J23=K23,0,($C$5+$C$13)/$C$11),$C$16="Quarterly",IF(J24=K24,0,($C$5+$C$13)/$C$12),$C$16="Annually",IF(J25=K25,0,($C$5+$C$13)/($C$6)*(IF(ROUNDDOWN($C$6,0)<J25,(ROUNDDOWN(J25,0)-$C$6),1))))))} -> 0 | ... IC48: {=IF(IC47=0,0,IF(IC23<=$C$15,0,_xlfn.IFS($C$16="Monthly",IF(IC23=ID23,0,($C$5+$C$13)/$C$11),$C$16="Quarterly",IF(IC24=ID24,0,($C$5+$C$13)/$C$12),$C$16="Annually",IF(IC25=ID25,0,($C$5+$C$13)/($C$6)*(IF(ROUNDDOWN($C$6,0)<IC25,(ROUNDDOWN(IC25,0)-$C$6),1))))))} -> 0
B49: Closing Balance | C49: =C47-C48 -> 0 | D49: =D47-D48 -> 0 | E49: =E47-E48 -> 0 | F49: =F47-F48 -> 0 | G49: =G47-G48 -> 0 | H49: =H47-H48 -> 0 | I49: =I47-I48 -> 0 | J49: =J47-J48 -> 0 | ... IC49: =IC47-IC48 -> -3.3217873e-13
B50: Interest | C50: =(C47+C49)/2*C27 -> 0 | D50: =(D47+D49)/2*D27 -> 0 | E50: =(E47+E49)/2*E27 -> 0 | F50: =(F47+F49)/2*F27 -> 0 | G50: =(G47+G49)/2*G27 -> 0 | H50: =(H47+H49)/2*H27 -> 0 | I50: =(I47+I49)/2*I27 -> 0 | J50: =(J47+J49)/2*J27 -> 0 | ... IC50: =(IC47+IC49)/2*IC27 -> -2.6297483e-15
B53: Annual
B54: FY | C54: =C22 -> FY 2025 | D54: FY 2026 | E54: FY 2027 | F54: FY 2028 | G54: FY 2029 | H54: FY 2030 | I54: FY 2031 | J54: FY 2032 | K54: FY 2033 | L54: FY 2034 | M54: FY 2035 | N54: FY 2036 | O54: FY 2037 | P54: FY 2038 | Q54: FY 2039 | R54: FY 2040 | S54: FY 2041 | T54: FY 2042 | U54: FY 2043 | V54: FY 2044 | W54: FY 2045 | X54: FY 2046 | Y54: FY 2047
B55: IDC | C55: =SUMIFS($C$44:$IC$44,$C$22:$IC$22,C54) -> 0.79549216 | D55: =SUMIFS($C$44:$IC$44,$C$22:$IC$22,D54) -> 2.607115 | E55: =SUMIFS($C$44:$IC$44,$C$22:$IC$22,E54) -> 0 | F55: =SUMIFS($C$44:$IC$44,$C$22:$IC$22,F54) -> 0 | G55: =SUMIFS($C$44:$IC$44,$C$22:$IC$22,G54) -> 0 | H55: =SUMIFS($C$44:$IC$44,$C$22:$IC$22,H54) -> 0 | I55: =SUMIFS($C$44:$IC$44,$C$22:$IC$22,I54) -> 0 | J55: =SUMIFS($C$44:$IC$44,$C$22:$IC$22,J54) -> 0 | ... Y55: =SUMIFS($C$44:$IC$44,$C$22:$IC$22,Y54) -> 0
B56: Repayments | C56: =+SUMIFS($C$48:$IC$48,$C$22:$IC$22,C54) -> 0 | D56: =+SUMIFS($C$48:$IC$48,$C$22:$IC$22,D54) -> 0 | E56: =+SUMIFS($C$48:$IC$48,$C$22:$IC$22,E54) -> 3.6110696 | F56: =+SUMIFS($C$48:$IC$48,$C$22:$IC$22,F54) -> 3.6110696 | G56: =+SUMIFS($C$48:$IC$48,$C$22:$IC$22,G54) -> 3.6110696 | H56: =+SUMIFS($C$48:$IC$48,$C$22:$IC$22,H54) -> 3.6110696 | I56: =+SUMIFS($C$48:$IC$48,$C$22:$IC$22,I54) -> 3.6110696 | J56: =+SUMIFS($C$48:$IC$48,$C$22:$IC$22,J54) -> 3.6110696 | ... Y56: =+SUMIFS($C$48:$IC$48,$C$22:$IC$22,Y54) -> 0
B57: Interest | C57: =+SUMIFS($C$50:$IC$50,$C$22:$IC$22,C54) -> 0 | D57: =+SUMIFS($C$50:$IC$50,$C$22:$IC$22,D54) -> 1.7152581 | E57: =+SUMIFS($C$50:$IC$50,$C$22:$IC$22,E54) -> 5.0171298 | F57: =+SUMIFS($C$50:$IC$50,$C$22:$IC$22,F54) -> 4.6740782 | G57: =+SUMIFS($C$50:$IC$50,$C$22:$IC$22,G54) -> 4.3310266 | H57: =+SUMIFS($C$50:$IC$50,$C$22:$IC$22,H54) -> 3.987975 | I57: =+SUMIFS($C$50:$IC$50,$C$22:$IC$22,I54) -> 3.6449234 | J57: =+SUMIFS($C$50:$IC$50,$C$22:$IC$22,J54) -> 3.3018718 | ... Y57: =+SUMIFS($C$50:$IC$50,$C$22:$IC$22,Y54) -> 0
B59: Operational year | C59: 0 | D59: 1 | E59: =D59+1 -> 2 | F59: =E59+1 -> 3 | G59: =F59+1 -> 4 | H59: =G59+1 -> 5 | I59: =H59+1 -> 6 | J59: =I59+1 -> 7 | K59: =J59+1 -> 8 | L59: =K59+1 -> 9 | ... Y59: =X59+1 -> 22
B60: IDC | C60: =SUMIFS($C$44:$IC$44,$C$25:$IC$25,C59) -> 3.4026072 | D60: =SUMIFS($C$44:$IC$44,$C$25:$IC$25,D59) -> 0 | E60: =SUMIFS($C$44:$IC$44,$C$25:$IC$25,E59) -> 0 | F60: =SUMIFS($C$44:$IC$44,$C$25:$IC$25,F59) -> 0 | G60: =SUMIFS($C$44:$IC$44,$C$25:$IC$25,G59) -> 0 | H60: =SUMIFS($C$44:$IC$44,$C$25:$IC$25,H59) -> 0 | I60: =SUMIFS($C$44:$IC$44,$C$25:$IC$25,I59) -> 0 | J60: =SUMIFS($C$44:$IC$44,$C$25:$IC$25,J59) -> 0 | ... Y60: =SUMIFS($C$44:$IC$44,$C$25:$IC$25,Y59) -> 0
B61: Repayments | C61: =+SUMIFS($C$48:$IC$48,$C$25:$IC$25,C59) -> 0 | D61: =+SUMIFS($C$48:$IC$48,$C$25:$IC$25,D59) -> 3.6110696 | E61: =+SUMIFS($C$48:$IC$48,$C$25:$IC$25,E59) -> 3.6110696 | F61: =+SUMIFS($C$48:$IC$48,$C$25:$IC$25,F59) -> 3.6110696 | G61: =+SUMIFS($C$48:$IC$48,$C$25:$IC$25,G59) -> 3.6110696 | H61: =+SUMIFS($C$48:$IC$48,$C$25:$IC$25,H59) -> 3.6110696 | I61: =+SUMIFS($C$48:$IC$48,$C$25:$IC$25,I59) -> 3.6110696 | J61: =+SUMIFS($C$48:$IC$48,$C$25:$IC$25,J59) -> 3.6110696 | ... Y61: =+SUMIFS($C$48:$IC$48,$C$25:$IC$25,Y59) -> 0
B62: Interest | C62: =+SUMIFS($C$50:$IC$50,$C$25:$IC$25,C59) -> 1.5331995e-14 | D62: =+SUMIFS($C$50:$IC$50,$C$25:$IC$25,D59) -> 5.1314804 | E62: =+SUMIFS($C$50:$IC$50,$C$25:$IC$25,E59) -> 4.7884288 | F62: =+SUMIFS($C$50:$IC$50,$C$25:$IC$25,F59) -> 4.4453772 | G62: =+SUMIFS($C$50:$IC$50,$C$25:$IC$25,G59) -> 4.1023255 | H62: =+SUMIFS($C$50:$IC$50,$C$25:$IC$25,H59) -> 3.7592739 | I62: =+SUMIFS($C$50:$IC$50,$C$25:$IC$25,I59) -> 3.4162223 | J62: =+SUMIFS($C$50:$IC$50,$C$25:$IC$25,J59) -> 3.0731707 | ... Y62: =+SUMIFS($C$50:$IC$50,$C$25:$IC$25,Y59) -> 0

Sheet Project Expenses
B1: Year count | E1: 0 | F1: =IFERROR(IF(E1+1<=Inputs!$D$4,E1+1,"-"),"-") -> 1 | G1: =IFERROR(IF(F1+1<=Inputs!$D$4,F1+1,"-"),"-") -> 2 | H1: =IFERROR(IF(G1+1<=Inputs!$D$4,G1+1,"-"),"-") -> 3 | I1: =IFERROR(IF(H1+1<=Inputs!$D$4,H1+1,"-"),"-") -> 4 | J1: =IFERROR(IF(I1+1<=Inputs!$D$4,I1+1,"-"),"-") -> 5 | K1: =IFERROR(IF(J1+1<=Inputs!$D$4,J1+1,"-"),"-") -> 6 | L1: =IFERROR(IF(K1+1<=Inputs!$D$4,K1+1,"-"),"-") -> 7 | M1: =IFERROR(IF(L1+1<=Inputs!$D$4,L1+1,"-"),"-") -> 8 | ... AB1: =IFERROR(IF(AA1+1<=Inputs!$D$4,AA1+1,"-"),"-") -> -
B2: Year | E2: =Inputs!G5+1 -> 45992 | F2: =EOMONTH(E2,11)+1 -> 46357 | G2: =EOMONTH(F2,11)+1 -> 46722 | H2: =EOMONTH(G2,11)+1 -> 47088 | I2: =EOMONTH(H2,11)+1 -> 47453 | J2: =EOMONTH(I2,11)+1 -> 47818 | K2: =EOMONTH(J2,11)+1 -> 48183 | L2: =EOMONTH(K2,11)+1 -> 48549 | M2: =EOMONTH(L2,11)+1 -> 48914 | ... AB2: =EOMONTH(AA2,11)+1 -> 54393
F3: =_xlfn.DAYS(F2,E2) -> 365 | G3: =_xlfn.DAYS(G2,F2) -> 365 | H3: =_xlfn.DAYS(H2,G2) -> 366 | I3: =_xlfn.DAYS(I2,H2) -> 365 | J3: =_xlfn.DAYS(J2,I2) -> 365 | K3: =_xlfn.DAYS(K2,J2) -> 365 | L3: =_xlfn.DAYS(L2,K2) -> 366 | M3: =_xlfn.DAYS(M2,L2) -> 365 | ... AB3: =_xlfn.DAYS(AB2,AA2) -> 366
A5: 1 | B5: Operational and maintenance
B6: O&M | C6: 0.05 | F6: =C6*'Project Cost Details'!G3/10^7 -> 1.8054 | G6: =IF(G1="-",0,F6*(1+G7)) -> 1.89567 | H6: =IF(H1="-",0,G6*(1+H7)) -> 1.9904535 | I6: =IF(I1="-",0,H6*(1+I7)) -> 2.0899762 | J6: =IF(J1="-",0,I6*(1+J7)) -> 2.194475 | K6: =IF(K1="-",0,J6*(1+K7)) -> 2.3041987 | L6: =IF(L1="-",0,K6*(1+L7)) -> 2.4194087 | M6: =IF(M1="-",0,L6*(1+M7)) -> 2.5403791 | N6: =IF(N1="-",0,M6*(1+N7)) -> 2.6673981 | ... AB6: =IF(AB1="-",0,AA6*(1+AB7)) -> 0
B7: Escalation | F7: 0 | G7: 0.05 | H7: 0.05 | I7: 0.05 | J7: 0.05 | K7: 0.05 | L7: 0.05 | M7: 0.05 | N7: 0.05 | O7: 0.05 | P7: 0.05 | Q7: 0.05 | R7: 0.05 | S7: 0.05 | T7: 0.05
A9: 2 | B9: Manpower | C9: # of employees | D9: Salary/month
B10: Site Incharge | C10: 1 | D10: 50000
B11: Operators | C11: 4 | D11: 25000
B12: Forklift operators | C12: 8 | D12: 28000
B13: Admin | C13: 2 | D13: 30000
B16: Total | D16: =SUMPRODUCT(C10:C15,D10:D15) -> 434000 | F16: =D16*12/10^7 -> 0.5208 | G16: =IF(G1="-",0,F16*(1+G17)) -> 0.54684 | H16: =IF(H1="-",0,G16*(1+H17)) -> 0.574182 | I16: =IF(I1="-",0,H16*(1+I17)) -> 0.6028911 | J16: =IF(J1="-",0,I16*(1+J17)) -> 0.63303566 | K16: =IF(K1="-",0,J16*(1+K17)) -> 0.66468744 | L16: =IF(L1="-",0,K16*(1+L17)) -> 0.69792181 | M16: =IF(M1="-",0,L16*(1+M17)) -> 0.7328179 | N16: =IF(N1="-",0,M16*(1+N17)) -> 0.7694588 | ... AB16: =IF(AB1="-",0,AA16*(1+AB17)) -> 0
B17: Escalation | G17: 0.05 | H17: =IF(H1="-",0,G17) -> 0.05 | I17: =IF(I1="-",0,H17) -> 0.05 | J17: =IF(J1="-",0,I17) -> 0.05 | K17: =IF(K1="-",0,J17) -> 0.05 | L17: =IF(L1="-",0,K17) -> 0.05 | M17: =IF(M1="-",0,L17) -> 0.05 | N17: =IF(N1="-",0,M17) -> 0.05 | O17: =IF(O1="-",0,N17) -> 0.05 | ... AB17: =IF(AB1="-",0,AA17) -> 0
A19: 3 | B19: Power
B20: Required Power | C20: 350 | D20: kVA | F20: =C20*24*365 -> 3066000 | G20: =F20 -> 3066000 | H20: =G20 -> 3066000 | I20: =H20 -> 3066000 | J20: =I20 -> 3066000 | K20: =J20 -> 3066000 | L20: =K20 -> 3066000 | M20: =L20 -> 3066000 | N20: =M20 -> 3066000 | ... AB20: =AA20 -> 3066000
B21: Demand Charges | C21: 475 | D21: Rs/kVA/month | F21: =C21*C20*12 -> 1995000 | G21: =F21 -> 1995000 | H21: =G21 -> 1995000 | I21: =H21 -> 1995000 | J21: =I21 -> 1995000 | K21: =J21 -> 1995000 | L21: =K21 -> 1995000 | M21: =L21 -> 1995000 | N21: =M21 -> 1995000 | ... AB21: =AA21 -> 1995000
B22: Electricity Tariff | C22: 7.15 | D22: Rs./unit | F22: =F20*$C$22 -> 21921900 | G22: =G20*$C$22 -> 21921900 | H22: =H20*$C$22 -> 21921900 | I22: =I20*$C$22 -> 21921900 | J22: =J20*$C$22 -> 21921900 | K22: =K20*$C$22 -> 21921900 | L22: =L20*$C$22 -> 21921900 | M22: =M20*$C$22 -> 21921900 | ... AB22: =AB20*$C$22 -> 21921900
B23: Electricity Duty | C23: 0.06 | D23: Rs./unit | F23: =$C$23*F20 -> 183960 | G23: =$C$23*G20 -> 183960 | H23: =$C$23*H20 -> 183960 | I23: =$C$23*I20 -> 183960 | J23: =$C$23*J20 -> 183960 | K23: =$C$23*K20 -> 183960 | L23: =$C$23*L20 -> 183960 | M23: =$C$23*M20 -> 183960 | ... AB23: =$C$23*AB20 -> 183960
B24: TOD tariff | C24: 0.3 | D24: Rs./unit | F24: =$C$24*F20 -> 919800 | G24: =$C$24*G20 -> 919800 | H24: =$C$24*H20 -> 919800 | I24: =$C$24*I20 -> 919800 | J24: =$C$24*J20 -> 919800 | K24: =$C$24*K20 -> 919800 | L24: =$C$24*L20 -> 919800 | M24: =$C$24*M20 -> 919800 | ... AB24: =$C$24*AB20 -> 919800
B25: Total | F25: =IF(F1="-",0,SUM(F21:F24)/10^7) -> 2.502066 | G25: =IF(G1="-",0,SUM(G21:G24)/10^7) -> 2.502066 | H25: =IF(H1="-",0,SUM(H21:H24)/10^7) -> 2.502066 | I25: =IF(I1="-",0,SUM(I21:I24)/10^7) -> 2.502066 | J25: =IF(J1="-",0,SUM(J21:J24)/10^7) -> 2.502066 | K25: =IF(K1="-",0,SUM(K21:K24)/10^7) -> 2.502066 | L25: =IF(L1="-",0,SUM(L21:L24)/10^7) -> 2.502066 | M25: =IF(M1="-",0,SUM(M21:M24)/10^7) -> 2.502066 | ... AB25: =IF(AB1="-",0,SUM(AB21:AB24)/10^7) -> 0
A27: 4 | B27: Water
B28: Requirement | C28: 10 | D28: KLD/day | F28: =C28*365 -> 3650 | G28: =F28 -> 3650 | H28: =G28 -> 3650 | I28: =H28 -> 3650 | J28: =I28 -> 3650 | K28: =J28 -> 3650 | L28: =K28 -> 3650 | M28: =L28 -> 3650 | N28: =M28 -> 3650 | ... AB28: =AA28 -> 3650
B29: Total Cost | C29: 180 | D29: Rs/KLD | F29: =IF(F1="-",0,$C$29*F28/10^7) -> 0.0657 | G29: =IF(G1="-",0,$C$29*G28/10^7) -> 0.0657 | H29: =IF(H1="-",0,$C$29*H28/10^7) -> 0.0657 | I29: =IF(I1="-",0,$C$29*I28/10^7) -> 0.0657 | J29: =IF(J1="-",0,$C$29*J28/10^7) -> 0.0657 | K29: =IF(K1="-",0,$C$29*K28/10^7) -> 0.0657 | L29: =IF(L1="-",0,$C$29*L28/10^7) -> 0.0657 | M29: =IF(M1="-",0,$C$29*M28/10^7) -> 0.0657 | ... AB29: =IF(AB1="-",0,$C$29*AB28/10^7) -> 0
A31: 5 | B31: Repayment of Security Deposit
B32: Rent renewal period | C32: =Inputs!D12 -> 7
B33: SD deposit | F33: 0 | G33: {=IFERROR(_xlfn.IFS(MOD(G1-1,$C$32)=0,Computations!D14/12*Inputs!$D$7,G1=Inputs!$D$4,Computations!D14/12*Inputs!$D$7),0)} -> 0 | H33: {=IFERROR(_xlfn.IFS(MOD(H1-1,$C$32)=0,Computations!E14/12*Inputs!$D$7,H1=Inputs!$D$4,Computations!E14/12*Inputs!$D$7),0)} -> 0 | I33: {=IFERROR(_xlfn.IFS(MOD(I1-1,$C$32)=0,Computations!F14/12*Inputs!$D$7,I1=Inputs!$D$4,Computations!F14/12*Inputs!$D$7),0)} -> 0 | J33: {=IFERROR(_xlfn.IFS(MOD(J1-1,$C$32)=0,Computations!G14/12*Inputs!$D$7,J1=Inputs!$D$4,Computations!G14/12*Inputs!$D$7),0)} -> 0 | K33: {=IFERROR(_xlfn.IFS(MOD(K1-1,$C$32)=0,Computations!H14/12*Inputs!$D$7,K1=Inputs!$D$4,Computations!H14/12*Inputs!$D$7),0)} -> 0 | L33: {=IFERROR(_xlfn.IFS(MOD(L1-1,$C$32)=0,Computations!I14/12*Inputs!$D$7,L1=Inputs!$D$4,Computations!I14/12*Inputs!$D$7),0)} -> 0 | M33: {=IFERROR(_xlfn.IFS(MOD(M1-1,$C$32)=0,Computations!J14/12*Inputs!$D$7,M1=Inputs!$D$4,Computations!J14/12*Inputs!$D$7),0)} -> 8.236746 | N33: {=IFERROR(_xlfn.IFS(MOD(N1-1,$C$32)=0,Computations!K14/12*Inputs!$D$7,N1=Inputs!$D$4,Computations!K14/12*Inputs!$D$7),0)} -> 0 | ... T33: {=IFERROR(_xlfn.IFS(MOD(T1-1,$C$32)=0,Computations!Q14/12*Inputs!$D$7,T1=Inputs!$D$4,Computations!Q14/12*Inputs!$D$7),0)} -> 8.4250078 | U33: =IFERROR(IF(MOD(U1-1,$C$32)=0,Computations!R14/12*Inputs!$D$7,0),IF(U1=Inputs!$D$4,Computations!R14/12*Inputs!$D$7,0)) -> 0 | V33: =IFERROR(IF(MOD(V1-1,$C$32)=0,Computations!S14/12*Inputs!$D$7,0),IF(V1=Inputs!$D$4,Computations!S14/12*Inputs!$D$7,0)) -> 0 | W33: =IFERROR(IF(MOD(W1-1,$C$32)=0,Computations!T14/12*Inputs!$D$7,0),IF(W1=Inputs!$D$4,Computations!T14/12*Inputs!$D$7,0)) -> 0 | X33: =IFERROR(IF(MOD(X1-1,$C$32)=0,Computations!U14/12*Inputs!$D$7,0),IF(X1=Inputs!$D$4,Computations!U14/12*Inputs!$D$7,0)) -> 0 | Y33: =IFERROR(IF(MOD(Y1-1,$C$32)=0,Computations!V14/12*Inputs!$D$7,0),IF(Y1=Inputs!$D$4,Computations!V14/12*Inputs!$D$7,0)) -> 0 | Z33: =IFERROR(IF(MOD(Z1-1,$C$32)=0,Computations!W14/12*Inputs!$D$7,0),IF(Z1=Inputs!$D$4,Computations!W14/12*Inputs!$D$7,0)) -> 0 | AA33: =IFERROR(IF(MOD(AA1-1,$C$32)=0,Computations!X14/12*Inputs!$D$7,0),IF(AA1=Inputs!$D$4,Computations!X14/12*Inputs!$D$7,0)) -> 0 | AB33: =IFERROR(IF(MOD(AB1-1,$C$32)=0,Computations!Y14/12*Inputs!$D$7,0),IF(AB1=Inputs!$D$4,Computations!Y14/12*Inputs!$D$7,0)) -> 0
A35: 6 | B35: Land lease rental
B36: Total land area | C36: sq. ft. | F36: =(28474.08-2000-3388.95)*10.76 -> 248396 | G36: =IF(G1="-",0,F36) -> 248396 | H36: =IF(H1="-",0,G36) -> 248396 | I36: =IF(I1="-",0,H36) -> 248396 | J36: =IF(J1="-",0,I36) -> 248396 | K36: =IF(K1="-",0,J36) -> 248396 | L36: =IF(L1="-",0,K36) -> 248396 | M36: =IF(M1="-",0,L36) -> 248396 | N36: =IF(N1="-",0,M36) -> 248396 | ... AB36: =IF(AB1="-",0,AA36) -> 0
B37: Rate per sq. ft. | C37: Rs./sq.ft. /month | F37: 16 | G37: =IFERROR(IF(MOD(G1,Inputs!$N$18)<>0,F37*(1+G38),Inputs!$N$16),0) -> 16 | H37: =IFERROR(IF(MOD(H1,Inputs!$N$18)<>0,G37*(1+H38),Inputs!$N$16),0) -> 16.8 | I37: =IFERROR(IF(MOD(I1,Inputs!$N$18)<>0,H37*(1+I38),Inputs!$N$16),0) -> 17.64 | J37: =IFERROR(IF(MOD(J1,Inputs!$N$18)<>0,I37*(1+J38),Inputs!$N$16),0) -> 18.522 | K37: =IFERROR(IF(MOD(K1,Inputs!$N$18)<>0,J37*(1+K38),Inputs!$N$16),0) -> 19.4481 | L37: =IFERROR(IF(MOD(L1,Inputs!$N$18)<>0,K37*(1+L38),Inputs!$N$16),0) -> 16 | M37: =IFERROR(IF(MOD(M1,Inputs!$N$18)<>0,L37*(1+M38),Inputs!$N$16),0) -> 16 | N37: =IFERROR(IF(MOD(N1,Inputs!$N$18)<>0,M37*(1+N38),Inputs!$N$16),0) -> 16 | ... AB37: =IFERROR(IF(MOD(AB1,Inputs!$N$18)<>0,AA37*(1+AB38),Inputs!$N$16),0) -> 0
B38: Escalation | F38: 0 | G38: 0 | H38: 0.05 | I38: 0.05 | J38: 0.05 | K38: 0.05 | L38: 0.05 | M38: 0 | N38: 0 | O38: 0.05 | P38: 0.05 | Q38: 0.05 | R38: 0.05 | S38: 0.05 | T38: 0.05 | U38: 0.05
B39: Security Deposit | C39: Rs. | F39: =IFERROR((IF(MOD(F1-1,Inputs!$N$18)=0,F36*F37*3,0))-(IF(MOD(F1,Inputs!$N$18)=0,-F36*F37*3,0)),0) -> 11923008 | G39: =IFERROR((IF(MOD(G1-1,Inputs!$N$18)=0,G36*G37*3,0))-(IF(MOD(G1,Inputs!$N$18)=0,G36*G37*3,0)),0) -> 0 | H39: =IFERROR((IF(MOD(H1-1,Inputs!$N$18)=0,H36*H37*3,0))-(IF(MOD(H1,Inputs!$N$18)=0,H36*H37*3,0)),0) -> 0 | I39: =IFERROR((IF(MOD(I1-1,Inputs!$N$18)=0,I36*I37*3,0))-(IF(MOD(I1,Inputs!$N$18)=0,I36*I37*3,0)),0) -> 0 | J39: =IFERROR((IF(MOD(J1-1,Inputs!$N$18)=0,J36*J37*3,0))-(IF(MOD(J1,Inputs!$N$18)=0,J36*J37*3,0)),0) -> 0 | K39: =IFERROR((IF(MOD(K1-1,Inputs!$N$18)=0,K36*K37*3,0))-(IF(MOD(K1,Inputs!$N$18)=0,K36*K37*3,0)),0) -> 0 | L39: =IFERROR((IF(MOD(L1-1,Inputs!$N$18)=0,L36*L37*3,0))-(IF(MOD(L1,Inputs!$N$18)=0,L36*L37*3,0)),0) -> -11923008 | M39: =IFERROR((IF(MOD(M1-1,Inputs!$N$18)=0,M36*M37*3,0))-(IF(MOD(M1,Inputs!$N$18)=0,M36*M37*3,0)),0) -> 11923008 | N39: =IFERROR((IF(MOD(N1-1,Inputs!$N$18)=0,N36*N37*3,0))-(IF(MOD(N1,Inputs!$N$18)=0,N36*N37*3,0)),0) -> 0 | ... S39: =IFERROR((IF(MOD(S1-1,Inputs!$N$18)=0,S36*S37*3,0))-(IF(MOD(S1,Inputs!$N$18)=0,S36*S37*3,0)),0) -> -11923008 | T39: 0 | U39: =IFERROR((IF(MOD(U1-1,Inputs!$N$18)=0,U36*U37*3,0))-(IF(MOD(U1,Inputs!$N$18)=0,U36*U37*3,0)),0) -> 0 | V39: =IFERROR((IF(MOD(V1-1,Inputs!$N$18)=0,V36*V37*3,0))-(IF(MOD(V1,Inputs!$N$18)=0,V36*V37*3,0)),0) -> 0 | W39: =IFERROR((IF(MOD(W1-1,Inputs!$N$18)=0,W36*W37*3,0))-(IF(MOD(W1,Inputs!$N$18)=0,W36*W37*3,0)),0) -> 0 | X39: =IFERROR((IF(MOD(X1-1,Inputs!$N$18)=0,X36*X37*3,0))-(IF(MOD(X1,Inputs!$N$18)=0,X36*X37*3,0)),0) -> 0 | Y39: =IFERROR((IF(MOD(Y1-1,Inputs!$N$18)=0,Y36*Y37*3,0))-(IF(MOD(Y1,Inputs!$N$18)=0,Y36*Y37*3,0)),0) -> 0 | Z39: =IFERROR((IF(MOD(Z1-1,Inputs!$N$18)=0,Z36*Z37*3,0))-(IF(MOD(Z1,Inputs!$N$18)=0,Z36*Z37*3,0)),0) -> 0 | AA39: =IFERROR((IF(MOD(AA1-1,Inputs!$N$18)=0,AA36*AA37*3,0))-(IF(MOD(AA1,Inputs!$N$18)=0,AA36*AA37*3,0)),0) -> 0 | AB39: =IFERROR((IF(MOD(AB1-1,Inputs!$N$18)=0,AB36*AB37*3,0))-(IF(MOD(AB1,Inputs!$N$18)=0,AB36*AB37*3,0)),0) -> 0
B40: Total cost | F40: =F36*F37*12+F39 -> 59615040 | G40: =G36*G37*12+G39 -> 47692032 | H40: =H36*H37*12+H39 -> 50076633 | I40: =I36*I37*12+I39 -> 52580465 | J40: =J36*J37*12+J39 -> 55209488 | K40: =K36*K37*12+K39 -> 57969963 | L40: =L36*L37*12+L39 -> 35769024 | M40: =M36*M37*12+M39 -> 59615040 | ... AB40: =AB36*AB37*12+AB39 -> 0
A42: 7 | B42: Transportation Cost
B43: Monthly contract cost | C43: Rs./month | F43: 0 | G43: =IF(G1="-",0,F43*1.05) -> 0 | H43: =IF(H1="-",0,G43*1.05) -> 0 | I43: =IF(I1="-",0,H43*1.05) -> 0 | J43: =IF(J1="-",0,I43*1.05) -> 0 | K43: =IF(K1="-",0,J43*1.05) -> 0 | L43: =IF(L1="-",0,K43*1.05) -> 0 | M43: =IF(M1="-",0,L43*1.05) -> 0 | N43: =IF(N1="-",0,M43*1.05) -> 0 | ... AB43: =IF(AB1="-",0,AA43*1.05) -> 0
B44: Total annual cost (incl GST) | C44: Rs./year | F44: =F43*12*1.18 -> 0 | G44: =G43*12*1.18 -> 0 | H44: =H43*12*1.18 -> 0 | I44: =I43*12*1.18 -> 0 | J44: =J43*12*1.18 -> 0 | K44: =K43*12*1.18 -> 0 | L44: =L43*12*1.18 -> 0 | M44: =M43*12*1.18 -> 0 | ... AB44: =AB43*12*1.18 -> 0
A47: 8 | B47: Depreciations
B48: Book Deprecaition SLM
B49: Gross Block
A50: 2 | B50: ='Project Cost Details'!B3 -> ASRS | C50: Years | D50: Cost
B51: ='Project Cost Details'!B4 -> Racking system | C51: =Inputs!$D$4/$A$50 -> 7.5 | D51: ='Project Capex'!D40 -> 15.04193 | F51: =D51 -> 15.04193 | G51: =F51 -> 15.04193 | H51: =G51 -> 15.04193 | I51: =H51 -> 15.04193 | J51: =I51 -> 15.04193 | K51: =J51 -> 15.04193 | L51: =K51 -> 15.04193 | M51: =L51 -> 15.04193 | N51: =M51 -> 15.04193 | ... AB51: =AA51 -> 15.04193
B52: ='Project Cost Details'!B5 -> Cladding for high bay | C52: =Inputs!$D$4/$A$50 -> 7.5 | D52: ='Project Capex'!D41 -> 1.416 | F52: =D52 -> 1.416 | G52: =F52 -> 1.416 | H52: =G52 -> 1.416 | I52: =H52 -> 1.416 | J52: =I52 -> 1.416 | K52: =J52 -> 1.416 | L52: =K52 -> 1.416 | M52: =L52 -> 1.416 | N52: =M52 -> 1.416 | ... AB52: =AA52 -> 1.416
B53: ='Project Cost Details'!B6 -> Double deep Stacker crane | C53: =Inputs!$D$4/$A$50 -> 7.5 | D53: ='Project Capex'!D42 -> 6.5254 | F53: =D53 -> 6.5254 | G53: =F53 -> 6.5254 | H53: =G53 -> 6.5254 | I53: =H53 -> 6.5254 | J53: =I53 -> 6.5254 | K53: =J53 -> 6.5254 | L53: =K53 -> 6.5254 | M53: =L53 -> 6.5254 | N53: =M53 -> 6.5254 | ... AB53: =AA53 -> 6.5254
B54: ='Project Cost Details'!B7 -> Bottom Rail with aisle accessories | C54: =Inputs!$D$4/$A$50 -> 7.5 | D54: ='Project Capex'!D43 -> 1.5871925 | F54: =D54 -> 1.5871925 | G54: =F54 -> 1.5871925 | H54: =G54 -> 1.5871925 | I54: =H54 -> 1.5871925 | J54: =I54 -> 1.5871925 | K54: =J54 -> 1.5871925 | L54: =K54 -> 1.5871925 | M54: =L54 -> 1.5871925 | N54: =M54 -> 1.5871925 | ... AB54: =AA54 -> 1.5871925
B55: ='Project Cost Details'!B8 -> Conveyor system | C55: =Inputs!$D$4/$A$50 -> 7.5 | D55: ='Project Capex'!D44 -> 1.7582 | F55: =D55 -> 1.7582 | G55: =F55 -> 1.7582 | H55: =G55 -> 1.7582 | I55: =H55 -> 1.7582 | J55: =I55 -> 1.7582 | K55: =J55 -> 1.7582 | L55: =K55 -> 1.7582 | M55: =L55 -> 1.7582 | N55: =M55 -> 1.7582 | ... AB55: =AA55 -> 1.7582
B56: ='Project Cost Details'!B9 -> Critical spares | C56: =Inputs!$D$4/$A$50 -> 7.5 | D56: ='Project Capex'!D45 -> 0.3304 | F56: =D56 -> 0.3304 | G56: =F56 -> 0.3304 | H56: =G56 -> 0.3304 | I56: =H56 -> 0.3304 | J56: =I56 -> 0.3304 | K56: =J56 -> 0.3304 | L56: =K56 -> 0.3304 | M56: =L56 -> 0.3304 | N56: =M56 -> 0.3304 | ... AB56: =AA56 -> 0.3304
B57: ='Project Cost Details'!B10 -> Metal pallets | C57: =Inputs!$D$4/$A$50 -> 7.5 | D57: ='Project Capex'!D46 -> 9.481536 | F57: =D57 -> 9.481536 | G57: =F57 -> 9.481536 | H57: =G57 -> 9.481536 | I57: =H57 -> 9.481536 | J57: =I57 -> 9.481536 | K57: =J57 -> 9.481536 | L57: =K57 -> 9.481536 | M57: =L57 -> 9.481536 | N57: =M57 -> 9.481536 | ... AB57: =AA57 -> 9.481536
B58: ='Project Cost Details'!B11 -> Discount | C58: =Inputs!$D$4/$A$50 -> 7.5 | D58: ='Project Capex'!D47 -> -0.032658624 | F58: =D58 -> -0.032658624 | G58: =F58 -> -0.032658624 | H58: =G58 -> -0.032658624 | I58: =H58 -> -0.032658624 | J58: =I58 -> -0.032658624 | K58: =J58 -> -0.032658624 | L58: =K58 -> -0.032658624 | M58: =L58 -> -0.032658624 | N58: =M58 -> -0.032658624 | ... AB58: =AA58 -> -0.032658624
B59: ='Project Cost Details'!B12 -> Civil Cost
B60: ='Project Cost Details'!B13 -> Earthworks and soiling | C60: =C58 -> 7.5 | D60: ='Project Capex'!D49 -> 1.593 | F60: =D60 -> 1.593 | G60: =F60 -> 1.593 | H60: =G60 -> 1.593 | I60: =H60 -> 1.593 | J60: =I60 -> 1.593 | K60: =J60 -> 1.593 | L60: =K60 -> 1.593 | M60: =L60 -> 1.593 | N60: =M60 -> 1.593 | ... AB60: =AA60 -> 1.593
B61: ='Project Cost Details'!B14 -> PCC works | C61: =C60 -> 7.5 | D61: ='Project Capex'!D50 -> 0.531 | F61: =D61 -> 0.531 | G61: =F61 -> 0.531 | H61: =G61 -> 0.531 | I61: =H61 -> 0.531 | J61: =I61 -> 0.531 | K61: =J61 -> 0.531 | L61: =K61 -> 0.531 | M61: =L61 -> 0.531 | N61: =M61 -> 0.531 | ... AB61: =AA61 -> 0.531
B62: ='Project Cost Details'!B15 -> RCC works | C62: =C61 -> 7.5 | D62: ='Project Capex'!D51 -> 3.54 | F62: =D62 -> 3.54 | G62: =F62 -> 3.54 | H62: =G62 -> 3.54 | I62: =H62 -> 3.54 | J62: =I62 -> 3.54 | K62: =J62 -> 3.54 | L62: =K62 -> 3.54 | M62: =L62 -> 3.54 | N62: =M62 -> 3.54 | ... AB62: =AA62 -> 3.54
B63: ='Project Cost Details'!B16 -> Shuttering | C63: =C62 -> 7.5 | D63: ='Project Capex'!D52 -> 0.1475 | F63: =D63 -> 0.1475 | G63: =F63 -> 0.1475 | H63: =G63 -> 0.1475 | I63: =H63 -> 0.1475 | J63: =I63 -> 0.1475 | K63: =J63 -> 0.1475 | L63: =K63 -> 0.1475 | M63: =L63 -> 0.1475 | N63: =M63 -> 0.1475 | ... AB63: =AA63 -> 0.1475
B64: ='Project Cost Details'!B17 -> TMT bards Fe 500 | C64: =C63 -> 7.5 | D64: ='Project Capex'!D53 -> 2.478 | F64: =D64 -> 2.478 | G64: =F64 -> 2.478 | H64: =G64 -> 2.478 | I64: =H64 -> 2.478 | J64: =I64 -> 2.478 | K64: =J64 -> 2.478 | L64: =K64 -> 2.478 | M64: =L64 -> 2.478 | N64: =M64 -> 2.478 | ... AB64: =AA64 -> 2.478
B65: ='Project Cost Details'!B18 -> Masonary works | C65: =C64 -> 7.5 | D65: ='Project Capex'!D54 -> 0.0708 | F65: =D65 -> 0.0708 | G65: =F65 -> 0.0708 | H65: =G65 -> 0.0708 | I65: =H65 -> 0.0708 | J65: =I65 -> 0.0708 | K65: =J65 -> 0.0708 | L65: =K65 -> 0.0708 | M65: =L65 -> 0.0708 | N65: =M65 -> 0.0708 | ... AB65: =AA65 -> 0.0708
B66: ='Project Cost Details'!B19 -> Plastering | C66: =C65 -> 7.5 | D66: ='Project Capex'!D55 -> 0.057525 | F66: =D66 -> 0.057525 | G66: =F66 -> 0.057525 | H66: =G66 -> 0.057525 | I66: =H66 -> 0.057525 | J66: =I66 -> 0.057525 | K66: =J66 -> 0.057525 | L66: =K66 -> 0.057525 | M66: =L66 -> 0.057525 | N66: =M66 -> 0.057525 | ... AB66: =AA66 -> 0.057525
B67: ='Project Cost Details'!B20 -> VDF Flooring | C67: =C66 -> 7.5 | D67: ='Project Capex'!D56 -> 0.08496 | F67: =D67 -> 0.08496 | G67: =F67 -> 0.08496 | H67: =G67 -> 0.08496 | I67: =H67 -> 0.08496 | J67: =I67 -> 0.08496 | K67: =J67 -> 0.08496 | L67: =K67 -> 0.08496 | M67: =L67 -> 0.08496 | N67: =M67 -> 0.08496 | ... AB67: =AA67 -> 0.08496
B68: ='Project Cost Details'!B21 -> J BOLTS installation | C68: =C67 -> 7.5 | D68: ='Project Capex'!D57 -> 0.1888 | F68: =D68 -> 0.1888 | G68: =F68 -> 0.1888 | H68: =G68 -> 0.1888 | I68: =H68 -> 0.1888 | J68: =I68 -> 0.1888 | K68: =J68 -> 0.1888 | L68: =K68 -> 0.1888 | M68: =L68 -> 0.1888 | N68: =M68 -> 0.1888 | ... AB68: =AA68 -> 0.1888
B69: ='Project Cost Details'!B22 -> Baseplate Grouting | C69: =C68 -> 7.5 | D69: ='Project Capex'!D58 -> 0.10384 | F69: =D69 -> 0.10384 | G69: =F69 -> 0.10384 | H69: =G69 -> 0.10384 | I69: =H69 -> 0.10384 | J69: =I69 -> 0.10384 | K69: =J69 -> 0.10384 | L69: =K69 -> 0.10384 | M69: =L69 -> 0.10384 | N69: =M69 -> 0.10384 | ... AB69: =AA69 -> 0.10384
B70: ='Project Cost Details'!B23 -> Miscellenous | C70: =C69 -> 7.5 | D70: ='Project Capex'!D59 -> 0.1416 | F70: =D70 -> 0.1416 | G70: =F70 -> 0.1416 | H70: =G70 -> 0.1416 | I70: =H70 -> 0.1416 | J70: =I70 -> 0.1416 | K70: =J70 -> 0.1416 | L70: =K70 -> 0.1416 | M70: =L70 -> 0.1416 | N70: =M70 -> 0.1416 | ... AB70: =AA70 -> 0.1416
B71: ='Project Cost Details'!B24 -> Road | C71: =C70 -> 7.5 | D71: ='Project Capex'!D60 -> 1.6905075 | F71: =D71 -> 1.6905075 | G71: =F71 -> 1.6905075 | H71: =G71 -> 1.6905075 | I71: =H71 -> 1.6905075 | J71: =I71 -> 1.6905075 | K71: =J71 -> 1.6905075 | L71: =K71 -> 1.6905075 | M71: =L71 -> 1.6905075 | N71: =M71 -> 1.6905075 | ... AB71: =AA71 -> 1.6905075
B72: ='Project Cost Details'!B25 -> Electrical | C72: =C71 -> 7.5 | D72: ='Project Capex'!D61 -> 0 | F72: =D72 -> 0 | G72: =F72 -> 0 | H72: =G72 -> 0 | I72: =H72 -> 0 | J72: =I72 -> 0 | K72: =J72 -> 0 | L72: =K72 -> 0 | M72: =L72 -> 0 | N72: =M72 -> 0 | ... AB72: =AA72 -> 0
... B74: ='Project Cost Details'!B27 -> FHS and FAS for the ASRS | C74: =C73 -> 7.5 | D74: ='Project Capex'!D63 -> 0 | F74: =D74 -> 0 | G74: =F74 -> 0 | H74: =G74 -> 0 | I74: =H74 -> 0 | J74: =I74 -> 0 | K74: =J74 -> 0 | L74: =K74 -> 0 | M74: =L74 -> 0 | N74: =M74 -> 0 | ... AB74: =AA74 -> 0
B75: ='Project Cost Details'!B28 -> Dock levellers | C75: =C58 -> 7.5 | D75: ='Project Capex'!D64 -> 0.83846989 | F75: =D75 -> 0.83846989 | G75: =F75 -> 0.83846989 | H75: =G75 -> 0.83846989 | I75: =H75 -> 0.83846989 | J75: =I75 -> 0.83846989 | K75: =J75 -> 0.83846989 | L75: =K75 -> 0.83846989 | M75: =L75 -> 0.83846989 | N75: =M75 -> 0.83846989 | ... AB75: =AA75 -> 0.83846989
B76: ='Project Cost Details'!B29 -> Contingency | C76: =C58 -> 7.5 | D76: ='Project Capex'!D65 -> 2.3787001 | F76: =D76 -> 2.3787001 | G76: =F76 -> 2.3787001 | H76: =G76 -> 2.3787001 | I76: =H76 -> 2.3787001 | J76: =I76 -> 2.3787001 | K76: =J76 -> 2.3787001 | L76: =K76 -> 2.3787001 | M76: =L76 -> 2.3787001 | N76: =M76 -> 2.3787001 | ... AB76: =AA76 -> 2.3787001
B77: ='Project Cost Details'!B30 -> Pre - operating expenses | C77: =C76 -> 7.5 | D77: ='Project Capex'!D66 -> 0.5412517 | F77: =D77 -> 0.5412517 | G77: =F77 -> 0.5412517 | H77: =G77 -> 0.5412517 | I77: =H77 -> 0.5412517 | J77: =I77 -> 0.5412517 | K77: =J77 -> 0.5412517 | L77: =K77 -> 0.5412517 | M77: =L77 -> 0.5412517 | N77: =M77 -> 0.5412517 | ... AB77: =AA77 -> 0.5412517
B78: ='Project Cost Details'!B31 -> IDC | C78: =C77 -> 7.5 | D78: ='Project Capex'!D67 -> 3.4026072 | F78: =D78 -> 3.4026072 | G78: =F78 -> 3.4026072 | H78: =G78 -> 3.4026072 | I78: =H78 -> 3.4026072 | J78: =I78 -> 3.4026072 | K78: =J78 -> 3.4026072 | L78: =K78 -> 3.4026072 | M78: =L78 -> 3.4026072 | N78: =M78 -> 3.4026072 | ... AB78: =AA78 -> 3.4026072
B79: Finance cost | C79: 7.5 | D79: ='Project Capex'!D68 -> 0.26948281 | F79: =D79 -> 0.26948281 | G79: =F79 -> 0.26948281 | H79: =G79 -> 0.26948281 | I79: =H79 -> 0.26948281 | J79: =I79 -> 0.26948281 | K79: =J79 -> 0.26948281 | L79: =K79 -> 0.26948281 | M79: =L79 -> 0.26948281 | N79: =M79 -> 0.26948281 | ... AB79: =AA79 -> 0.26948281
A80: 1 | B80: Total | D80: =SUM(D51:D79)*$A$80 -> 54.166044 | E80: =SUM(E51:E78)*$A$80 -> 0 | F80: =SUM(F51:F79)*$A$80 -> 54.166044 | G80: =SUM(G51:G79)*$A$80 -> 54.166044 | H80: =SUM(H51:H79)*$A$80 -> 54.166044 | I80: =SUM(I51:I79)*$A$80 -> 54.166044 | J80: =SUM(J51:J79)*$A$80 -> 54.166044 | K80: =SUM(K51:K79)*$A$80 -> 54.166044 | L80: =SUM(L51:L79)*$A$80 -> 54.166044 | M80: =SUM(M51:M79)*$A$80 -> 54.166044 | ... T80: =SUM(T51:T79)*$A$80 -> 54.166044
B82: Accumulated Depreciation | C82: 0.05
B83: =B50 -> ASRS
B84: =B51 -> Racking system | F84: =IF(F$1<=$C51,($D51*(1-$C$82)/($C51*12))*12,IF(F$1=ROUNDUP($C51,0),($D51*(1-$C$82)/($C51*12))*((F$1-$C51)*12),0)) -> 1.9053111 | G84: =IF(G$1<=$C51,($D51*(1-$C$82)/($C51*12))*12,IF(G$1=ROUNDUP($C51,0),($D51*(1-$C$82)/($C51*12))*((G$1-$C51)*12),0)) -> 1.9053111 | H84: =IF(H$1<=$C51,($D51*(1-$C$82)/($C51*12))*12,IF(H$1=ROUNDUP($C51,0),($D51*(1-$C$82)/($C51*12))*((H$1-$C51)*12),0)) -> 1.9053111 | I84: =IF(I$1<=$C51,($D51*(1-$C$82)/($C51*12))*12,IF(I$1=ROUNDUP($C51,0),($D51*(1-$C$82)/($C51*12))*((I$1-$C51)*12),0)) -> 1.9053111 | J84: =IF(J$1<=$C51,($D51*(1-$C$82)/($C51*12))*12,IF(J$1=ROUNDUP($C51,0),($D51*(1-$C$82)/($C51*12))*((J$1-$C51)*12),0)) -> 1.9053111 | K84: =IF(K$1<=$C51,($D51*(1-$C$82)/($C51*12))*12,IF(K$1=ROUNDUP($C51,0),($D51*(1-$C$82)/($C51*12))*((K$1-$C51)*12),0)) -> 1.9053111 | L84: =IF(L$1<=$C51,($D51*(1-$C$82)/($C51*12))*12,IF(L$1=ROUNDUP($C51,0),($D51*(1-$C$82)/($C51*12))*((L$1-$C51)*12),0)) -> 1.9053111 | M84: =IF(M$1<=$C51,($D51*(1-$C$82)/($C51*12))*12,IF(M$1=ROUNDUP($C51,0),($D51*(1-$C$82)/($C51*12))*((M$1-$C51)*12),0)) -> 0.95265557 | ... AB84: =IF(AB$1<=$C51,($D51*(1-$C$82)/($C51*12))*12,IF(AB$1=ROUNDUP($C51,0),($D51*(1-$C$82)/($C51*12))*((AB$1-$C51)*12),0)) -> 0
B85: =B52 -> Cladding for high bay | F85: =IF(F$1<=$C52,($D52*(1-$C$82)/($C52*12))*12,IF(F$1=ROUNDUP($C52,0),($D52*(1-$C$82)/($C52*12))*((F$1-$C52)*12),0)) -> 0.17936 | G85: =IF(G$1<=$C52,($D52*(1-$C$82)/($C52*12))*12,IF(G$1=ROUNDUP($C52,0),($D52*(1-$C$82)/($C52*12))*((G$1-$C52)*12),0)) -> 0.17936 | H85: =IF(H$1<=$C52,($D52*(1-$C$82)/($C52*12))*12,IF(H$1=ROUNDUP($C52,0),($D52*(1-$C$82)/($C52*12))*((H$1-$C52)*12),0)) -> 0.17936 | I85: =IF(I$1<=$C52,($D52*(1-$C$82)/($C52*12))*12,IF(I$1=ROUNDUP($C52,0),($D52*(1-$C$82)/($C52*12))*((I$1-$C52)*12),0)) -> 0.17936 | J85: =IF(J$1<=$C52,($D52*(1-$C$82)/($C52*12))*12,IF(J$1=ROUNDUP($C52,0),($D52*(1-$C$82)/($C52*12))*((J$1-$C52)*12),0)) -> 0.17936 | K85: =IF(K$1<=$C52,($D52*(1-$C$82)/($C52*12))*12,IF(K$1=ROUNDUP($C52,0),($D52*(1-$C$82)/($C52*12))*((K$1-$C52)*12),0)) -> 0.17936 | L85: =IF(L$1<=$C52,($D52*(1-$C$82)/($C52*12))*12,IF(L$1=ROUNDUP($C52,0),($D52*(1-$C$82)/($C52*12))*((L$1-$C52)*12),0)) -> 0.17936 | M85: =IF(M$1<=$C52,($D52*(1-$C$82)/($C52*12))*12,IF(M$1=ROUNDUP($C52,0),($D52*(1-$C$82)/($C52*12))*((M$1-$C52)*12),0)) -> 0.08968 | ... AB85: =IF(AB$1<=$C52,($D52*(1-$C$82)/($C52*12))*12,IF(AB$1=ROUNDUP($C52,0),($D52*(1-$C$82)/($C52*12))*((AB$1-$C52)*12),0)) -> 0
B86: =B53 -> Double deep Stacker crane | F86: =IF(F$1<=$C53,($D53*(1-$C$82)/($C53*12))*12,IF(F$1=ROUNDUP($C53,0),($D53*(1-$C$82)/($C53*12))*((F$1-$C53)*12),0)) -> 0.82655067 | G86: =IF(G$1<=$C53,($D53*(1-$C$82)/($C53*12))*12,IF(G$1=ROUNDUP($C53,0),($D53*(1-$C$82)/($C53*12))*((G$1-$C53)*12),0)) -> 0.82655067 | H86: =IF(H$1<=$C53,($D53*(1-$C$82)/($C53*12))*12,IF(H$1=ROUNDUP($C53,0),($D53*(1-$C$82)/($C53*12))*((H$1-$C53)*12),0)) -> 0.82655067 | I86: =IF(I$1<=$C53,($D53*(1-$C$82)/($C53*12))*12,IF(I$1=ROUNDUP($C53,0),($D53*(1-$C$82)/($C53*12))*((I$1-$C53)*12),0)) -> 0.82655067 | J86: =IF(J$1<=$C53,($D53*(1-$C$82)/($C53*12))*12,IF(J$1=ROUNDUP($C53,0),($D53*(1-$C$82)/($C53*12))*((J$1-$C53)*12),0)) -> 0.82655067 | K86: =IF(K$1<=$C53,($D53*(1-$C$82)/($C53*12))*12,IF(K$1=ROUNDUP($C53,0),($D53*(1-$C$82)/($C53*12))*((K$1-$C53)*12),0)) -> 0.82655067 | L86: =IF(L$1<=$C53,($D53*(1-$C$82)/($C53*12))*12,IF(L$1=ROUNDUP($C53,0),($D53*(1-$C$82)/($C53*12))*((L$1-$C53)*12),0)) -> 0.82655067 | M86: =IF(M$1<=$C53,($D53*(1-$C$82)/($C53*12))*12,IF(M$1=ROUNDUP($C53,0),($D53*(1-$C$82)/($C53*12))*((M$1-$C53)*12),0)) -> 0.41327533 | ... AB86: =IF(AB$1<=$C53,($D53*(1-$C$82)/($C53*12))*12,IF(AB$1=ROUNDUP($C53,0),($D53*(1-$C$82)/($C53*12))*((AB$1-$C53)*12),0)) -> 0
B87: =B54 -> Bottom Rail with aisle accessories | F87: =IF(F$1<=$C54,($D54*(1-$C$82)/($C54*12))*12,IF(F$1=ROUNDUP($C54,0),($D54*(1-$C$82)/($C54*12))*((F$1-$C54)*12),0)) -> 0.20104438 | G87: =IF(G$1<=$C54,($D54*(1-$C$82)/($C54*12))*12,IF(G$1=ROUNDUP($C54,0),($D54*(1-$C$82)/($C54*12))*((G$1-$C54)*12),0)) -> 0.20104438 | H87: =IF(H$1<=$C54,($D54*(1-$C$82)/($C54*12))*12,IF(H$1=ROUNDUP($C54,0),($D54*(1-$C$82)/($C54*12))*((H$1-$C54)*12),0)) -> 0.20104438 | I87: =IF(I$1<=$C54,($D54*(1-$C$82)/($C54*12))*12,IF(I$1=ROUNDUP($C54,0),($D54*(1-$C$82)/($C54*12))*((I$1-$C54)*12),0)) -> 0.20104438 | J87: =IF(J$1<=$C54,($D54*(1-$C$82)/($C54*12))*12,IF(J$1=ROUNDUP($C54,0),($D54*(1-$C$82)/($C54*12))*((J$1-$C54)*12),0)) -> 0.20104438 | K87: =IF(K$1<=$C54,($D54*(1-$C$82)/($C54*12))*12,IF(K$1=ROUNDUP($C54,0),($D54*(1-$C$82)/($C54*12))*((K$1-$C54)*12),0)) -> 0.20104438 | L87: =IF(L$1<=$C54,($D54*(1-$C$82)/($C54*12))*12,IF(L$1=ROUNDUP($C54,0),($D54*(1-$C$82)/($C54*12))*((L$1-$C54)*12),0)) -> 0.20104438 | M87: =IF(M$1<=$C54,($D54*(1-$C$82)/($C54*12))*12,IF(M$1=ROUNDUP($C54,0),($D54*(1-$C$82)/($C54*12))*((M$1-$C54)*12),0)) -> 0.10052219 | ... AB87: =IF(AB$1<=$C54,($D54*(1-$C$82)/($C54*12))*12,IF(AB$1=ROUNDUP($C54,0),($D54*(1-$C$82)/($C54*12))*((AB$1-$C54)*12),0)) -> 0
B88: =B55 -> Conveyor system | F88: =IF(F$1<=$C55,($D55*(1-$C$82)/($C55*12))*12,IF(F$1=ROUNDUP($C55,0),($D55*(1-$C$82)/($C55*12))*((F$1-$C55)*12),0)) -> 0.22270533 | G88: =IF(G$1<=$C55,($D55*(1-$C$82)/($C55*12))*12,IF(G$1=ROUNDUP($C55,0),($D55*(1-$C$82)/($C55*12))*((G$1-$C55)*12),0)) -> 0.22270533 | H88: =IF(H$1<=$C55,($D55*(1-$C$82)/($C55*12))*12,IF(H$1=ROUNDUP($C55,0),($D55*(1-$C$82)/($C55*12))*((H$1-$C55)*12),0)) -> 0.22270533 | I88: =IF(I$1<=$C55,($D55*(1-$C$82)/($C55*12))*12,IF(I$1=ROUNDUP($C55,0),($D55*(1-$C$82)/($C55*12))*((I$1-$C55)*12),0)) -> 0.22270533 | J88: =IF(J$1<=$C55,($D55*(1-$C$82)/($C55*12))*12,IF(J$1=ROUNDUP($C55,0),($D55*(1-$C$82)/($C55*12))*((J$1-$C55)*12),0)) -> 0.22270533 | K88: =IF(K$1<=$C55,($D55*(1-$C$82)/($C55*12))*12,IF(K$1=ROUNDUP($C55,0),($D55*(1-$C$82)/($C55*12))*((K$1-$C55)*12),0)) -> 0.22270533 | L88: =IF(L$1<=$C55,($D55*(1-$C$82)/($C55*12))*12,IF(L$1=ROUNDUP($C55,0),($D55*(1-$C$82)/($C55*12))*((L$1-$C55)*12),0)) -> 0.22270533 | M88: =IF(M$1<=$C55,($D55*(1-$C$82)/($C55*12))*12,IF(M$1=ROUNDUP($C55,0),($D55*(1-$C$82)/($C55*12))*((M$1-$C55)*12),0)) -> 0.11135267 | ... AB88: =IF(AB$1<=$C55,($D55*(1-$C$82)/($C55*12))*12,IF(AB$1=ROUNDUP($C55,0),($D55*(1-$C$82)/($C55*12))*((AB$1-$C55)*12),0)) -> 0
B89: =B56 -> Critical spares | F89: =IF(F$1<=$C56,($D56*(1-$C$82)/($C56*12))*12,IF(F$1=ROUNDUP($C56,0),($D56*(1-$C$82)/($C56*12))*((F$1-$C56)*12),0)) -> 0.041850667 | G89: =IF(G$1<=$C56,($D56*(1-$C$82)/($C56*12))*12,IF(G$1=ROUNDUP($C56,0),($D56*(1-$C$82)/($C56*12))*((G$1-$C56)*12),0)) -> 0.041850667 | H89: =IF(H$1<=$C56,($D56*(1-$C$82)/($C56*12))*12,IF(H$1=ROUNDUP($C56,0),($D56*(1-$C$82)/($C56*12))*((H$1-$C56)*12),0)) -> 0.041850667 | I89: =IF(I$1<=$C56,($D56*(1-$C$82)/($C56*12))*12,IF(I$1=ROUNDUP($C56,0),($D56*(1-$C$82)/($C56*12))*((I$1-$C56)*12),0)) -> 0.041850667 | J89: =IF(J$1<=$C56,($D56*(1-$C$82)/($C56*12))*12,IF(J$1=ROUNDUP($C56,0),($D56*(1-$C$82)/($C56*12))*((J$1-$C56)*12),0)) -> 0.041850667 | K89: =IF(K$1<=$C56,($D56*(1-$C$82)/($C56*12))*12,IF(K$1=ROUNDUP($C56,0),($D56*(1-$C$82)/($C56*12))*((K$1-$C56)*12),0)) -> 0.041850667 | L89: =IF(L$1<=$C56,($D56*(1-$C$82)/($C56*12))*12,IF(L$1=ROUNDUP($C56,0),($D56*(1-$C$82)/($C56*12))*((L$1-$C56)*12),0)) -> 0.041850667 | M89: =IF(M$1<=$C56,($D56*(1-$C$82)/($C56*12))*12,IF(M$1=ROUNDUP($C56,0),($D56*(1-$C$82)/($C56*12))*((M$1-$C56)*12),0)) -> 0.020925333 | ... AB89: =IF(AB$1<=$C56,($D56*(1-$C$82)/($C56*12))*12,IF(AB$1=ROUNDUP($C56,0),($D56*(1-$C$82)/($C56*12))*((AB$1-$C56)*12),0)) -> 0
B90: =B57 -> Metal pallets | F90: =IF(F$1<=$C57,($D57*(1-$C$82)/($C57*12))*12,IF(F$1=ROUNDUP($C57,0),($D57*(1-$C$82)/($C57*12))*((F$1-$C57)*12),0)) -> 1.2009946 | G90: =IF(G$1<=$C57,($D57*(1-$C$82)/($C57*12))*12,IF(G$1=ROUNDUP($C57,0),($D57*(1-$C$82)/($C57*12))*((G$1-$C57)*12),0)) -> 1.2009946 | H90: =IF(H$1<=$C57,($D57*(1-$C$82)/($C57*12))*12,IF(H$1=ROUNDUP($C57,0),($D57*(1-$C$82)/($C57*12))*((H$1-$C57)*12),0)) -> 1.2009946 | I90: =IF(I$1<=$C57,($D57*(1-$C$82)/($C57*12))*12,IF(I$1=ROUNDUP($C57,0),($D57*(1-$C$82)/($C57*12))*((I$1-$C57)*12),0)) -> 1.2009946 | J90: =IF(J$1<=$C57,($D57*(1-$C$82)/($C57*12))*12,IF(J$1=ROUNDUP($C57,0),($D57*(1-$C$82)/($C57*12))*((J$1-$C57)*12),0)) -> 1.2009946 | K90: =IF(K$1<=$C57,($D57*(1-$C$82)/($C57*12))*12,IF(K$1=ROUNDUP($C57,0),($D57*(1-$C$82)/($C57*12))*((K$1-$C57)*12),0)) -> 1.2009946 | L90: =IF(L$1<=$C57,($D57*(1-$C$82)/($C57*12))*12,IF(L$1=ROUNDUP($C57,0),($D57*(1-$C$82)/($C57*12))*((L$1-$C57)*12),0)) -> 1.2009946 | M90: =IF(M$1<=$C57,($D57*(1-$C$82)/($C57*12))*12,IF(M$1=ROUNDUP($C57,0),($D57*(1-$C$82)/($C57*12))*((M$1-$C57)*12),0)) -> 0.60049728 | ... AB90: =IF(AB$1<=$C57,($D57*(1-$C$82)/($C57*12))*12,IF(AB$1=ROUNDUP($C57,0),($D57*(1-$C$82)/($C57*12))*((AB$1-$C57)*12),0)) -> 0
B91: =B58 -> Discount | F91: =IF(F$1<=$C58,($D58*(1-$C$82)/($C58*12))*12,IF(F$1=ROUNDUP($C58,0),($D58*(1-$C$82)/($C58*12))*((F$1-$C58)*12),0)) -> -0.004136759 | G91: =IF(G$1<=$C58,($D58*(1-$C$82)/($C58*12))*12,IF(G$1=ROUNDUP($C58,0),($D58*(1-$C$82)/($C58*12))*((G$1-$C58)*12),0)) -> -0.004136759 | H91: =IF(H$1<=$C58,($D58*(1-$C$82)/($C58*12))*12,IF(H$1=ROUNDUP($C58,0),($D58*(1-$C$82)/($C58*12))*((H$1-$C58)*12),0)) -> -0.004136759 | I91: =IF(I$1<=$C58,($D58*(1-$C$82)/($C58*12))*12,IF(I$1=ROUNDUP($C58,0),($D58*(1-$C$82)/($C58*12))*((I$1-$C58)*12),0)) -> -0.004136759 | J91: =IF(J$1<=$C58,($D58*(1-$C$82)/($C58*12))*12,IF(J$1=ROUNDUP($C58,0),($D58*(1-$C$82)/($C58*12))*((J$1-$C58)*12),0)) -> -0.004136759 | K91: =IF(K$1<=$C58,($D58*(1-$C$82)/($C58*12))*12,IF(K$1=ROUNDUP($C58,0),($D58*(1-$C$82)/($C58*12))*((K$1-$C58)*12),0)) -> -0.004136759 | L91: =IF(L$1<=$C58,($D58*(1-$C$82)/($C58*12))*12,IF(L$1=ROUNDUP($C58,0),($D58*(1-$C$82)/($C58*12))*((L$1-$C58)*12),0)) -> -0.004136759 | M91: =IF(M$1<=$C58,($D58*(1-$C$82)/($C58*12))*12,IF(M$1=ROUNDUP($C58,0),($D58*(1-$C$82)/($C58*12))*((M$1-$C58)*12),0)) -> -0.0020683795 | ... AB91: =IF(AB$1<=$C58,($D58*(1-$C$82)/($C58*12))*12,IF(AB$1=ROUNDUP($C58,0),($D58*(1-$C$82)/($C58*12))*((AB$1-$C58)*12),0)) -> 0
B92: =B59 -> Civil Cost
B93: =B60 -> Earthworks and soiling | F93: =IF(F$1<=$C60,($D60*(1-$C$82)/($C60*12))*12,IF(F$1=ROUNDUP($C60,0),($D60*(1-$C$82)/($C60*12))*((F$1-$C60)*12),0)) -> 0.20178 | G93: =IF(G$1<=$C60,($D60*(1-$C$82)/($C60*12))*12,IF(G$1=ROUNDUP($C60,0),($D60*(1-$C$82)/($C60*12))*((G$1-$C60)*12),0)) -> 0.20178 | H93: =IF(H$1<=$C60,($D60*(1-$C$82)/($C60*12))*12,IF(H$1=ROUNDUP($C60,0),($D60*(1-$C$82)/($C60*12))*((H$1-$C60)*12),0)) -> 0.20178 | I93: =IF(I$1<=$C60,($D60*(1-$C$82)/($C60*12))*12,IF(I$1=ROUNDUP($C60,0),($D60*(1-$C$82)/($C60*12))*((I$1-$C60)*12),0)) -> 0.20178 | J93: =IF(J$1<=$C60,($D60*(1-$C$82)/($C60*12))*12,IF(J$1=ROUNDUP($C60,0),($D60*(1-$C$82)/($C60*12))*((J$1-$C60)*12),0)) -> 0.20178 | K93: =IF(K$1<=$C60,($D60*(1-$C$82)/($C60*12))*12,IF(K$1=ROUNDUP($C60,0),($D60*(1-$C$82)/($C60*12))*((K$1-$C60)*12),0)) -> 0.20178 | L93: =IF(L$1<=$C60,($D60*(1-$C$82)/($C60*12))*12,IF(L$1=ROUNDUP($C60,0),($D60*(1-$C$82)/($C60*12))*((L$1-$C60)*12),0)) -> 0.20178 | M93: =IF(M$1<=$C60,($D60*(1-$C$82)/($C60*12))*12,IF(M$1=ROUNDUP($C60,0),($D60*(1-$C$82)/($C60*12))*((M$1-$C60)*12),0)) -> 0.10089 | ... AB93: =IF(AB$1<=$C60,($D60*(1-$C$82)/($C60*12))*12,IF(AB$1=ROUNDUP($C60,0),($D60*(1-$C$82)/($C60*12))*((AB$1-$C60)*12),0)) -> 0
B94: =B61 -> PCC works | F94: =IF(F$1<=$C61,($D61*(1-$C$82)/($C61*12))*12,IF(F$1=ROUNDUP($C61,0),($D61*(1-$C$82)/($C61*12))*((F$1-$C61)*12),0)) -> 0.06726 | G94: =IF(G$1<=$C61,($D61*(1-$C$82)/($C61*12))*12,IF(G$1=ROUNDUP($C61,0),($D61*(1-$C$82)/($C61*12))*((G$1-$C61)*12),0)) -> 0.06726 | H94: =IF(H$1<=$C61,($D61*(1-$C$82)/($C61*12))*12,IF(H$1=ROUNDUP($C61,0),($D61*(1-$C$82)/($C61*12))*((H$1-$C61)*12),0)) -> 0.06726 | I94: =IF(I$1<=$C61,($D61*(1-$C$82)/($C61*12))*12,IF(I$1=ROUNDUP($C61,0),($D61*(1-$C$82)/($C61*12))*((I$1-$C61)*12),0)) -> 0.06726 | J94: =IF(J$1<=$C61,($D61*(1-$C$82)/($C61*12))*12,IF(J$1=ROUNDUP($C61,0),($D61*(1-$C$82)/($C61*12))*((J$1-$C61)*12),0)) -> 0.06726 | K94: =IF(K$1<=$C61,($D61*(1-$C$82)/($C61*12))*12,IF(K$1=ROUNDUP($C61,0),($D61*(1-$C$82)/($C61*12))*((K$1-$C61)*12),0)) -> 0.06726 | L94: =IF(L$1<=$C61,($D61*(1-$C$82)/($C61*12))*12,IF(L$1=ROUNDUP($C61,0),($D61*(1-$C$82)/($C61*12))*((L$1-$C61)*12),0)) -> 0.06726 | M94: =IF(M$1<=$C61,($D61*(1-$C$82)/($C61*12))*12,IF(M$1=ROUNDUP($C61,0),($D61*(1-$C$82)/($C61*12))*((M$1-$C61)*12),0)) -> 0.03363 | ... AB94: =IF(AB$1<=$C61,($D61*(1-$C$82)/($C61*12))*12,IF(AB$1=ROUNDUP($C61,0),($D61*(1-$C$82)/($C61*12))*((AB$1-$C61)*12),0)) -> 0
B95: =B62 -> RCC works | F95: =IF(F$1<=$C62,($D62*(1-$C$82)/($C62*12))*12,IF(F$1=ROUNDUP($C62,0),($D62*(1-$C$82)/($C62*12))*((F$1-$C62)*12),0)) -> 0.4484 | G95: =IF(G$1<=$C62,($D62*(1-$C$82)/($C62*12))*12,IF(G$1=ROUNDUP($C62,0),($D62*(1-$C$82)/($C62*12))*((G$1-$C62)*12),0)) -> 0.4484 | H95: =IF(H$1<=$C62,($D62*(1-$C$82)/($C62*12))*12,IF(H$1=ROUNDUP($C62,0),($D62*(1-$C$82)/($C62*12))*((H$1-$C62)*12),0)) -> 0.4484 | I95: =IF(I$1<=$C62,($D62*(1-$C$82)/($C62*12))*12,IF(I$1=ROUNDUP($C62,0),($D62*(1-$C$82)/($C62*12))*((I$1-$C62)*12),0)) -> 0.4484 | J95: =IF(J$1<=$C62,($D62*(1-$C$82)/($C62*12))*12,IF(J$1=ROUNDUP($C62,0),($D62*(1-$C$82)/($C62*12))*((J$1-$C62)*12),0)) -> 0.4484 | K95: =IF(K$1<=$C62,($D62*(1-$C$82)/($C62*12))*12,IF(K$1=ROUNDUP($C62,0),($D62*(1-$C$82)/($C62*12))*((K$1-$C62)*12),0)) -> 0.4484 | L95: =IF(L$1<=$C62,($D62*(1-$C$82)/($C62*12))*12,IF(L$1=ROUNDUP($C62,0),($D62*(1-$C$82)/($C62*12))*((L$1-$C62)*12),0)) -> 0.4484 | M95: =IF(M$1<=$C62,($D62*(1-$C$82)/($C62*12))*12,IF(M$1=ROUNDUP($C62,0),($D62*(1-$C$82)/($C62*12))*((M$1-$C62)*12),0)) -> 0.2242 | ... AB95: =IF(AB$1<=$C62,($D62*(1-$C$82)/($C62*12))*12,IF(AB$1=ROUNDUP($C62,0),($D62*(1-$C$82)/($C62*12))*((AB$1-$C62)*12),0)) -> 0
B96: =B63 -> Shuttering | F96: =IF(F$1<=$C63,($D63*(1-$C$82)/($C63*12))*12,IF(F$1=ROUNDUP($C63,0),($D63*(1-$C$82)/($C63*12))*((F$1-$C63)*12),0)) -> 0.018683333 | G96: =IF(G$1<=$C63,($D63*(1-$C$82)/($C63*12))*12,IF(G$1=ROUNDUP($C63,0),($D63*(1-$C$82)/($C63*12))*((G$1-$C63)*12),0)) -> 0.018683333 | H96: =IF(H$1<=$C63,($D63*(1-$C$82)/($C63*12))*12,IF(H$1=ROUNDUP($C63,0),($D63*(1-$C$82)/($C63*12))*((H$1-$C63)*12),0)) -> 0.018683333 | I96: =IF(I$1<=$C63,($D63*(1-$C$82)/($C63*12))*12,IF(I$1=ROUNDUP($C63,0),($D63*(1-$C$82)/($C63*12))*((I$1-$C63)*12),0)) -> 0.018683333 | J96: =IF(J$1<=$C63,($D63*(1-$C$82)/($C63*12))*12,IF(J$1=ROUNDUP($C63,0),($D63*(1-$C$82)/($C63*12))*((J$1-$C63)*12),0)) -> 0.018683333 | K96: =IF(K$1<=$C63,($D63*(1-$C$82)/($C63*12))*12,IF(K$1=ROUNDUP($C63,0),($D63*(1-$C$82)/($C63*12))*((K$1-$C63)*12),0)) -> 0.018683333 | L96: =IF(L$1<=$C63,($D63*(1-$C$82)/($C63*12))*12,IF(L$1=ROUNDUP($C63,0),($D63*(1-$C$82)/($C63*12))*((L$1-$C63)*12),0)) -> 0.018683333 | M96: =IF(M$1<=$C63,($D63*(1-$C$82)/($C63*12))*12,IF(M$1=ROUNDUP($C63,0),($D63*(1-$C$82)/($C63*12))*((M$1-$C63)*12),0)) -> 0.0093416667 | ... AB96: =IF(AB$1<=$C63,($D63*(1-$C$82)/($C63*12))*12,IF(AB$1=ROUNDUP($C63,0),($D63*(1-$C$82)/($C63*12))*((AB$1-$C63)*12),0)) -> 0
B97: =B64 -> TMT bards Fe 500 | F97: =IF(F$1<=$C64,($D64*(1-$C$82)/($C64*12))*12,IF(F$1=ROUNDUP($C64,0),($D64*(1-$C$82)/($C64*12))*((F$1-$C64)*12),0)) -> 0.31388 | G97: =IF(G$1<=$C64,($D64*(1-$C$82)/($C64*12))*12,IF(G$1=ROUNDUP($C64,0),($D64*(1-$C$82)/($C64*12))*((G$1-$C64)*12),0)) -> 0.31388 | H97: =IF(H$1<=$C64,($D64*(1-$C$82)/($C64*12))*12,IF(H$1=ROUNDUP($C64,0),($D64*(1-$C$82)/($C64*12))*((H$1-$C64)*12),0)) -> 0.31388 | I97: =IF(I$1<=$C64,($D64*(1-$C$82)/($C64*12))*12,IF(I$1=ROUNDUP($C64,0),($D64*(1-$C$82)/($C64*12))*((I$1-$C64)*12),0)) -> 0.31388 | J97: =IF(J$1<=$C64,($D64*(1-$C$82)/($C64*12))*12,IF(J$1=ROUNDUP($C64,0),($D64*(1-$C$82)/($C64*12))*((J$1-$C64)*12),0)) -> 0.31388 | K97: =IF(K$1<=$C64,($D64*(1-$C$82)/($C64*12))*12,IF(K$1=ROUNDUP($C64,0),($D64*(1-$C$82)/($C64*12))*((K$1-$C64)*12),0)) -> 0.31388 | L97: =IF(L$1<=$C64,($D64*(1-$C$82)/($C64*12))*12,IF(L$1=ROUNDUP($C64,0),($D64*(1-$C$82)/($C64*12))*((L$1-$C64)*12),0)) -> 0.31388 | M97: =IF(M$1<=$C64,($D64*(1-$C$82)/($C64*12))*12,IF(M$1=ROUNDUP($C64,0),($D64*(1-$C$82)/($C64*12))*((M$1-$C64)*12),0)) -> 0.15694 | ... AB97: =IF(AB$1<=$C64,($D64*(1-$C$82)/($C64*12))*12,IF(AB$1=ROUNDUP($C64,0),($D64*(1-$C$82)/($C64*12))*((AB$1-$C64)*12),0)) -> 0
B98: =B65 -> Masonary works | F98: =IF(F$1<=$C65,($D65*(1-$C$82)/($C65*12))*12,IF(F$1=ROUNDUP($C65,0),($D65*(1-$C$82)/($C65*12))*((F$1-$C65)*12),0)) -> 0.008968 | G98: =IF(G$1<=$C65,($D65*(1-$C$82)/($C65*12))*12,IF(G$1=ROUNDUP($C65,0),($D65*(1-$C$82)/($C65*12))*((G$1-$C65)*12),0)) -> 0.008968 | H98: =IF(H$1<=$C65,($D65*(1-$C$82)/($C65*12))*12,IF(H$1=ROUNDUP($C65,0),($D65*(1-$C$82)/($C65*12))*((H$1-$C65)*12),0)) -> 0.008968 | I98: =IF(I$1<=$C65,($D65*(1-$C$82)/($C65*12))*12,IF(I$1=ROUNDUP($C65,0),($D65*(1-$C$82)/($C65*12))*((I$1-$C65)*12),0)) -> 0.008968 | J98: =IF(J$1<=$C65,($D65*(1-$C$82)/($C65*12))*12,IF(J$1=ROUNDUP($C65,0),($D65*(1-$C$82)/($C65*12))*((J$1-$C65)*12),0)) -> 0.008968 | K98: =IF(K$1<=$C65,($D65*(1-$C$82)/($C65*12))*12,IF(K$1=ROUNDUP($C65,0),($D65*(1-$C$82)/($C65*12))*((K$1-$C65)*12),0)) -> 0.008968 | L98: =IF(L$1<=$C65,($D65*(1-$C$82)/($C65*12))*12,IF(L$1=ROUNDUP($C65,0),($D65*(1-$C$82)/($C65*12))*((L$1-$C65)*12),0)) -> 0.008968 | M98: =IF(M$1<=$C65,($D65*(1-$C$82)/($C65*12))*12,IF(M$1=ROUNDUP($C65,0),($D65*(1-$C$82)/($C65*12))*((M$1-$C65)*12),0)) -> 0.004484 | ... AB98: =IF(AB$1<=$C65,($D65*(1-$C$82)/($C65*12))*12,IF(AB$1=ROUNDUP($C65,0),($D65*(1-$C$82)/($C65*12))*((AB$1-$C65)*12),0)) -> 0
B99: =B66 -> Plastering | F99: =IF(F$1<=$C66,($D66*(1-$C$82)/($C66*12))*12,IF(F$1=ROUNDUP($C66,0),($D66*(1-$C$82)/($C66*12))*((F$1-$C66)*12),0)) -> 0.0072865 | G99: =IF(G$1<=$C66,($D66*(1-$C$82)/($C66*12))*12,IF(G$1=ROUNDUP($C66,0),($D66*(1-$C$82)/($C66*12))*((G$1-$C66)*12),0)) -> 0.0072865 | H99: =IF(H$1<=$C66,($D66*(1-$C$82)/($C66*12))*12,IF(H$1=ROUNDUP($C66,0),($D66*(1-$C$82)/($C66*12))*((H$1-$C66)*12),0)) -> 0.0072865 | I99: =IF(I$1<=$C66,($D66*(1-$C$82)/($C66*12))*12,IF(I$1=ROUNDUP($C66,0),($D66*(1-$C$82)/($C66*12))*((I$1-$C66)*12),0)) -> 0.0072865 | J99: =IF(J$1<=$C66,($D66*(1-$C$82)/($C66*12))*12,IF(J$1=ROUNDUP($C66,0),($D66*(1-$C$82)/($C66*12))*((J$1-$C66)*12),0)) -> 0.0072865 | K99: =IF(K$1<=$C66,($D66*(1-$C$82)/($C66*12))*12,IF(K$1=ROUNDUP($C66,0),($D66*(1-$C$82)/($C66*12))*((K$1-$C66)*12),0)) -> 0.0072865 | L99: =IF(L$1<=$C66,($D66*(1-$C$82)/($C66*12))*12,IF(L$1=ROUNDUP($C66,0),($D66*(1-$C$82)/($C66*12))*((L$1-$C66)*12),0)) -> 0.0072865 | M99: =IF(M$1<=$C66,($D66*(1-$C$82)/($C66*12))*12,IF(M$1=ROUNDUP($C66,0),($D66*(1-$C$82)/($C66*12))*((M$1-$C66)*12),0)) -> 0.00364325 | ... AB99: =IF(AB$1<=$C66,($D66*(1-$C$82)/($C66*12))*12,IF(AB$1=ROUNDUP($C66,0),($D66*(1-$C$82)/($C66*12))*((AB$1-$C66)*12),0)) -> 0
B100: =B67 -> VDF Flooring | F100: =IF(F$1<=$C67,($D67*(1-$C$82)/($C67*12))*12,IF(F$1=ROUNDUP($C67,0),($D67*(1-$C$82)/($C67*12))*((F$1-$C67)*12),0)) -> 0.0107616 | G100: =IF(G$1<=$C67,($D67*(1-$C$82)/($C67*12))*12,IF(G$1=ROUNDUP($C67,0),($D67*(1-$C$82)/($C67*12))*((G$1-$C67)*12),0)) -> 0.0107616 | H100: =IF(H$1<=$C67,($D67*(1-$C$82)/($C67*12))*12,IF(H$1=ROUNDUP($C67,0),($D67*(1-$C$82)/($C67*12))*((H$1-$C67)*12),0)) -> 0.0107616 | I100: =IF(I$1<=$C67,($D67*(1-$C$82)/($C67*12))*12,IF(I$1=ROUNDUP($C67,0),($D67*(1-$C$82)/($C67*12))*((I$1-$C67)*12),0)) -> 0.0107616 | J100: =IF(J$1<=$C67,($D67*(1-$C$82)/($C67*12))*12,IF(J$1=ROUNDUP($C67,0),($D67*(1-$C$82)/($C67*12))*((J$1-$C67)*12),0)) -> 0.0107616 | K100: =IF(K$1<=$C67,($D67*(1-$C$82)/($C67*12))*12,IF(K$1=ROUNDUP($C67,0),($D67*(1-$C$82)/($C67*12))*((K$1-$C67)*12),0)) -> 0.0107616 | L100: =IF(L$1<=$C67,($D67*(1-$C$82)/($C67*12))*12,IF(L$1=ROUNDUP($C67,0),($D67*(1-$C$82)/($C67*12))*((L$1-$C67)*12),0)) -> 0.0107616 | M100: =IF(M$1<=$C67,($D67*(1-$C$82)/($C67*12))*12,IF(M$1=ROUNDUP($C67,0),($D67*(1-$C$82)/($C67*12))*((M$1-$C67)*12),0)) -> 0.0053808 | ... AB100: =IF(AB$1<=$C67,($D67*(1-$C$82)/($C67*12))*12,IF(AB$1=ROUNDUP($C67,0),($D67*(1-$C$82)/($C67*12))*((AB$1-$C67)*12),0)) -> 0
B101: =B68 -> J BOLTS installation | F101: =IF(F$1<=$C68,($D68*(1-$C$82)/($C68*12))*12,IF(F$1=ROUNDUP($C68,0),($D68*(1-$C$82)/($C68*12))*((F$1-$C68)*12),0)) -> 0.023914667 | G101: =IF(G$1<=$C68,($D68*(1-$C$82)/($C68*12))*12,IF(G$1=ROUNDUP($C68,0),($D68*(1-$C$82)/($C68*12))*((G$1-$C68)*12),0)) -> 0.023914667 | H101: =IF(H$1<=$C68,($D68*(1-$C$82)/($C68*12))*12,IF(H$1=ROUNDUP($C68,0),($D68*(1-$C$82)/($C68*12))*((H$1-$C68)*12),0)) -> 0.023914667 | I101: =IF(I$1<=$C68,($D68*(1-$C$82)/($C68*12))*12,IF(I$1=ROUNDUP($C68,0),($D68*(1-$C$82)/($C68*12))*((I$1-$C68)*12),0)) -> 0.023914667 | J101: =IF(J$1<=$C68,($D68*(1-$C$82)/($C68*12))*12,IF(J$1=ROUNDUP($C68,0),($D68*(1-$C$82)/($C68*12))*((J$1-$C68)*12),0)) -> 0.023914667 | K101: =IF(K$1<=$C68,($D68*(1-$C$82)/($C68*12))*12,IF(K$1=ROUNDUP($C68,0),($D68*(1-$C$82)/($C68*12))*((K$1-$C68)*12),0)) -> 0.023914667 | L101: =IF(L$1<=$C68,($D68*(1-$C$82)/($C68*12))*12,IF(L$1=ROUNDUP($C68,0),($D68*(1-$C$82)/($C68*12))*((L$1-$C68)*12),0)) -> 0.023914667 | M101: =IF(M$1<=$C68,($D68*(1-$C$82)/($C68*12))*12,IF(M$1=ROUNDUP($C68,0),($D68*(1-$C$82)/($C68*12))*((M$1-$C68)*12),0)) -> 0.011957333 | ... AB101: =IF(AB$1<=$C68,($D68*(1-$C$82)/($C68*12))*12,IF(AB$1=ROUNDUP($C68,0),($D68*(1-$C$82)/($C68*12))*((AB$1-$C68)*12),0)) -> 0
B102: =B69 -> Baseplate Grouting | F102: =IF(F$1<=$C69,($D69*(1-$C$82)/($C69*12))*12,IF(F$1=ROUNDUP($C69,0),($D69*(1-$C$82)/($C69*12))*((F$1-$C69)*12),0)) -> 0.013153067 | G102: =IF(G$1<=$C69,($D69*(1-$C$82)/($C69*12))*12,IF(G$1=ROUNDUP($C69,0),($D69*(1-$C$82)/($C69*12))*((G$1-$C69)*12),0)) -> 0.013153067 | H102: =IF(H$1<=$C69,($D69*(1-$C$82)/($C69*12))*12,IF(H$1=ROUNDUP($C69,0),($D69*(1-$C$82)/($C69*12))*((H$1-$C69)*12),0)) -> 0.013153067 | I102: =IF(I$1<=$C69,($D69*(1-$C$82)/($C69*12))*12,IF(I$1=ROUNDUP($C69,0),($D69*(1-$C$82)/($C69*12))*((I$1-$C69)*12),0)) -> 0.013153067 | J102: =IF(J$1<=$C69,($D69*(1-$C$82)/($C69*12))*12,IF(J$1=ROUNDUP($C69,0),($D69*(1-$C$82)/($C69*12))*((J$1-$C69)*12),0)) -> 0.013153067 | K102: =IF(K$1<=$C69,($D69*(1-$C$82)/($C69*12))*12,IF(K$1=ROUNDUP($C69,0),($D69*(1-$C$82)/($C69*12))*((K$1-$C69)*12),0)) -> 0.013153067 | L102: =IF(L$1<=$C69,($D69*(1-$C$82)/($C69*12))*12,IF(L$1=ROUNDUP($C69,0),($D69*(1-$C$82)/($C69*12))*((L$1-$C69)*12),0)) -> 0.013153067 | M102: =IF(M$1<=$C69,($D69*(1-$C$82)/($C69*12))*12,IF(M$1=ROUNDUP($C69,0),($D69*(1-$C$82)/($C69*12))*((M$1-$C69)*12),0)) -> 0.0065765333 | ... AB102: =IF(AB$1<=$C69,($D69*(1-$C$82)/($C69*12))*12,IF(AB$1=ROUNDUP($C69,0),($D69*(1-$C$82)/($C69*12))*((AB$1-$C69)*12),0)) -> 0
B103: =B70 -> Miscellenous | F103: =IF(F$1<=$C70,($D70*(1-$C$82)/($C70*12))*12,IF(F$1=ROUNDUP($C70,0),($D70*(1-$C$82)/($C70*12))*((F$1-$C70)*12),0)) -> 0.017936 | G103: =IF(G$1<=$C70,($D70*(1-$C$82)/($C70*12))*12,IF(G$1=ROUNDUP($C70,0),($D70*(1-$C$82)/($C70*12))*((G$1-$C70)*12),0)) -> 0.017936 | H103: =IF(H$1<=$C70,($D70*(1-$C$82)/($C70*12))*12,IF(H$1=ROUNDUP($C70,0),($D70*(1-$C$82)/($C70*12))*((H$1-$C70)*12),0)) -> 0.017936 | I103: =IF(I$1<=$C70,($D70*(1-$C$82)/($C70*12))*12,IF(I$1=ROUNDUP($C70,0),($D70*(1-$C$82)/($C70*12))*((I$1-$C70)*12),0)) -> 0.017936 | J103: =IF(J$1<=$C70,($D70*(1-$C$82)/($C70*12))*12,IF(J$1=ROUNDUP($C70,0),($D70*(1-$C$82)/($C70*12))*((J$1-$C70)*12),0)) -> 0.017936 | K103: =IF(K$1<=$C70,($D70*(1-$C$82)/($C70*12))*12,IF(K$1=ROUNDUP($C70,0),($D70*(1-$C$82)/($C70*12))*((K$1-$C70)*12),0)) -> 0.017936 | L103: =IF(L$1<=$C70,($D70*(1-$C$82)/($C70*12))*12,IF(L$1=ROUNDUP($C70,0),($D70*(1-$C$82)/($C70*12))*((L$1-$C70)*12),0)) -> 0.017936 | M103: =IF(M$1<=$C70,($D70*(1-$C$82)/($C70*12))*12,IF(M$1=ROUNDUP($C70,0),($D70*(1-$C$82)/($C70*12))*((M$1-$C70)*12),0)) -> 0.008968 | ... AB103: =IF(AB$1<=$C70,($D70*(1-$C$82)/($C70*12))*12,IF(AB$1=ROUNDUP($C70,0),($D70*(1-$C$82)/($C70*12))*((AB$1-$C70)*12),0)) -> 0
B104: =B71 -> Road | F104: =IF(F$1<=$C71,($D71*(1-$C$82)/($C71*12))*12,IF(F$1=ROUNDUP($C71,0),($D71*(1-$C$82)/($C71*12))*((F$1-$C71)*12),0)) -> 0.21413095 | G104: =IF(G$1<=$C71,($D71*(1-$C$82)/($C71*12))*12,IF(G$1=ROUNDUP($C71,0),($D71*(1-$C$82)/($C71*12))*((G$1-$C71)*12),0)) -> 0.21413095 | H104: =IF(H$1<=$C71,($D71*(1-$C$82)/($C71*12))*12,IF(H$1=ROUNDUP($C71,0),($D71*(1-$C$82)/($C71*12))*((H$1-$C71)*12),0)) -> 0.21413095 | I104: =IF(I$1<=$C71,($D71*(1-$C$82)/($C71*12))*12,IF(I$1=ROUNDUP($C71,0),($D71*(1-$C$82)/($C71*12))*((I$1-$C71)*12),0)) -> 0.21413095 | J104: =IF(J$1<=$C71,($D71*(1-$C$82)/($C71*12))*12,IF(J$1=ROUNDUP($C71,0),($D71*(1-$C$82)/($C71*12))*((J$1-$C71)*12),0)) -> 0.21413095 | K104: =IF(K$1<=$C71,($D71*(1-$C$82)/($C71*12))*12,IF(K$1=ROUNDUP($C71,0),($D71*(1-$C$82)/($C71*12))*((K$1-$C71)*12),0)) -> 0.21413095 | L104: =IF(L$1<=$C71,($D71*(1-$C$82)/($C71*12))*12,IF(L$1=ROUNDUP($C71,0),($D71*(1-$C$82)/($C71*12))*((L$1-$C71)*12),0)) -> 0.21413095 | M104: =IF(M$1<=$C71,($D71*(1-$C$82)/($C71*12))*12,IF(M$1=ROUNDUP($C71,0),($D71*(1-$C$82)/($C71*12))*((M$1-$C71)*12),0)) -> 0.10706548 | ... AB104: =IF(AB$1<=$C71,($D71*(1-$C$82)/($C71*12))*12,IF(AB$1=ROUNDUP($C71,0),($D71*(1-$C$82)/($C71*12))*((AB$1-$C71)*12),0)) -> 0
... B111: =B78 -> IDC | F111: =IF(F$1<=$C78,($D78*(1-$C$82)/($C78*12))*12,IF(F$1=ROUNDUP($C78,0),($D78*(1-$C$82)/($C78*12))*((F$1-$C78)*12),0)) -> 0.43099691 | G111: =IF(G$1<=$C78,($D78*(1-$C$82)/($C78*12))*12,IF(G$1=ROUNDUP($C78,0),($D78*(1-$C$82)/($C78*12))*((G$1-$C78)*12),0)) -> 0.43099691 | H111: =IF(H$1<=$C78,($D78*(1-$C$82)/($C78*12))*12,IF(H$1=ROUNDUP($C78,0),($D78*(1-$C$82)/($C78*12))*((H$1-$C78)*12),0)) -> 0.43099691 | I111: =IF(I$1<=$C78,($D78*(1-$C$82)/($C78*12))*12,IF(I$1=ROUNDUP($C78,0),($D78*(1-$C$82)/($C78*12))*((I$1-$C78)*12),0)) -> 0.43099691 | J111: =IF(J$1<=$C78,($D78*(1-$C$82)/($C78*12))*12,IF(J$1=ROUNDUP($C78,0),($D78*(1-$C$82)/($C78*12))*((J$1-$C78)*12),0)) -> 0.43099691 | K111: =IF(K$1<=$C78,($D78*(1-$C$82)/($C78*12))*12,IF(K$1=ROUNDUP($C78,0),($D78*(1-$C$82)/($C78*12))*((K$1-$C78)*12),0)) -> 0.43099691 | L111: =IF(L$1<=$C78,($D78*(1-$C$82)/($C78*12))*12,IF(L$1=ROUNDUP($C78,0),($D78*(1-$C$82)/($C78*12))*((L$1-$C78)*12),0)) -> 0.43099691 | M111: =IF(M$1<=$C78,($D78*(1-$C$82)/($C78*12))*12,IF(M$1=ROUNDUP($C78,0),($D78*(1-$C$82)/($C78*12))*((M$1-$C78)*12),0)) -> 0.21549845 | ... AB111: =IF(AB$1<=$C78,($D78*(1-$C$82)/($C78*12))*12,IF(AB$1=ROUNDUP($C78,0),($D78*(1-$C$82)/($C78*12))*((AB$1-$C78)*12),0)) -> 0
B112: Finance cost | F112: =IF(F$1<=$C79,($D79*(1-$C$82)/($C79*12))*12,IF(F$1=ROUNDUP($C79,0),($D79*(1-$C$82)/($C79*12))*((F$1-$C79)*12),0)) -> 0.034134489 | G112: =IF(G$1<=$C79,($D79*(1-$C$82)/($C79*12))*12,IF(G$1=ROUNDUP($C79,0),($D79*(1-$C$82)/($C79*12))*((G$1-$C79)*12),0)) -> 0.034134489 | H112: =IF(H$1<=$C79,($D79*(1-$C$82)/($C79*12))*12,IF(H$1=ROUNDUP($C79,0),($D79*(1-$C$82)/($C79*12))*((H$1-$C79)*12),0)) -> 0.034134489 | I112: =IF(I$1<=$C79,($D79*(1-$C$82)/($C79*12))*12,IF(I$1=ROUNDUP($C79,0),($D79*(1-$C$82)/($C79*12))*((I$1-$C79)*12),0)) -> 0.034134489 | J112: =IF(J$1<=$C79,($D79*(1-$C$82)/($C79*12))*12,IF(J$1=ROUNDUP($C79,0),($D79*(1-$C$82)/($C79*12))*((J$1-$C79)*12),0)) -> 0.034134489 | K112: =IF(K$1<=$C79,($D79*(1-$C$82)/($C79*12))*12,IF(K$1=ROUNDUP($C79,0),($D79*(1-$C$82)/($C79*12))*((K$1-$C79)*12),0)) -> 0.034134489 | L112: =IF(L$1<=$C79,($D79*(1-$C$82)/($C79*12))*12,IF(L$1=ROUNDUP($C79,0),($D79*(1-$C$82)/($C79*12))*((L$1-$C79)*12),0)) -> 0.034134489 | M112: =IF(M$1<=$C79,($D79*(1-$C$82)/($C79*12))*12,IF(M$1=ROUNDUP($C79,0),($D79*(1-$C$82)/($C79*12))*((M$1-$C79)*12),0)) -> 0.017067244 | ... AB112: =IF(AB$1<=$C79,($D79*(1-$C$82)/($C79*12))*12,IF(AB$1=ROUNDUP($C79,0),($D79*(1-$C$82)/($C79*12))*((AB$1-$C79)*12),0)) -> 0
A113: 2 | B113: =B80 -> Total | F113: =SUM(F84:F112) -> 6.8610323 | G113: =SUM(G84:G112) -> 6.8610323 | H113: =SUM(H84:H112) -> 6.8610323 | I113: =SUM(I84:I112) -> 6.8610323 | J113: =SUM(J84:J112) -> 6.8610323 | K113: =SUM(K84:K112) -> 6.8610323 | L113: =SUM(L84:L112) -> 6.8610323 | M113: =SUM(M84:M112) -> 3.4305161 | ... T113: =SUM(T84:T112) -> 0
B114: Cummulative Depreciation | F114: =F113 -> 6.8610323 | G114: =G113+F114 -> 13.722065 | H114: =H113+G114 -> 20.583097 | I114: =I113+H114 -> 27.444129 | J114: =J113+I114 -> 34.305161 | K114: =K113+J114 -> 41.166194 | L114: =L113+K114 -> 48.027226 | M114: =M113+L114 -> 51.457742 | N114: =N113+M114 -> 51.457742 | ... AB114: =AB113+AA114 -> 51.457742
B116: Closing Balance
B117: =B83 -> ASRS
B118: =B84 -> Racking system | F118: =IF(AND(F$1="-",F$1>ROUNDUP($C51,0)),0,F51-F84) -> 13.136619 | G118: =IF(OR(G$1="-",G$1>ROUNDUP($C51,0)),0,F118-G84) -> 11.231308 | H118: =IF(OR(H$1="-",H$1>ROUNDUP($C51,0)),0,G118-H84) -> 9.3259967 | I118: =IF(OR(I$1="-",I$1>ROUNDUP($C51,0)),0,H118-I84) -> 7.4206855 | J118: =IF(OR(J$1="-",J$1>ROUNDUP($C51,0)),0,I118-J84) -> 5.5153744 | K118: =IF(OR(K$1="-",K$1>ROUNDUP($C51,0)),0,J118-K84) -> 3.6100632 | L118: =IF(OR(L$1="-",L$1>ROUNDUP($C51,0)),0,K118-L84) -> 1.7047521 | M118: =IF(OR(M$1="-",M$1>ROUNDUP($C51,0)),0,L118-M84) -> 0.75209651 | N118: =IF(OR(N$1="-",N$1>ROUNDUP($C51,0)),0,M118-N84) -> 0 | ... AB118: =IF(OR(AB$1="-",AB$1>ROUNDUP($C51,0)),0,AA118-AB84) -> 0
B119: =B85 -> Cladding for high bay | F119: =IF(AND(F$1="-",F$1>ROUNDUP($C52,0)),0,F52-F85) -> 1.23664 | G119: =IF(OR(G$1="-",G$1>ROUNDUP($C52,0)),0,F119-G85) -> 1.05728 | H119: =IF(OR(H$1="-",H$1>ROUNDUP($C52,0)),0,G119-H85) -> 0.87792 | I119: =IF(OR(I$1="-",I$1>ROUNDUP($C52,0)),0,H119-I85) -> 0.69856 | J119: =IF(OR(J$1="-",J$1>ROUNDUP($C52,0)),0,I119-J85) -> 0.5192 | K119: =IF(OR(K$1="-",K$1>ROUNDUP($C52,0)),0,J119-K85) -> 0.33984 | L119: =IF(OR(L$1="-",L$1>ROUNDUP($C52,0)),0,K119-L85) -> 0.16048 | M119: =IF(OR(M$1="-",M$1>ROUNDUP($C52,0)),0,L119-M85) -> 0.0708 | N119: =IF(OR(N$1="-",N$1>ROUNDUP($C52,0)),0,M119-N85) -> 0 | ... AB119: =IF(OR(AB$1="-",AB$1>ROUNDUP($C52,0)),0,AA119-AB85) -> 0
B120: =B86 -> Double deep Stacker crane | F120: =IF(AND(F$1="-",F$1>ROUNDUP($C53,0)),0,F53-F86) -> 5.6988493 | G120: =IF(OR(G$1="-",G$1>ROUNDUP($C53,0)),0,F120-G86) -> 4.8722987 | H120: =IF(OR(H$1="-",H$1>ROUNDUP($C53,0)),0,G120-H86) -> 4.045748 | I120: =IF(OR(I$1="-",I$1>ROUNDUP($C53,0)),0,H120-I86) -> 3.2191973 | J120: =IF(OR(J$1="-",J$1>ROUNDUP($C53,0)),0,I120-J86) -> 2.3926467 | K120: =IF(OR(K$1="-",K$1>ROUNDUP($C53,0)),0,J120-K86) -> 1.566096 | L120: =IF(OR(L$1="-",L$1>ROUNDUP($C53,0)),0,K120-L86) -> 0.73954533 | M120: =IF(OR(M$1="-",M$1>ROUNDUP($C53,0)),0,L120-M86) -> 0.32627 | N120: =IF(OR(N$1="-",N$1>ROUNDUP($C53,0)),0,M120-N86) -> 0 | ... AB120: =IF(OR(AB$1="-",AB$1>ROUNDUP($C53,0)),0,AA120-AB86) -> 0
...

Sheet Project Cost Details
B2: Parameters | C2: Quantity | D2: Rate | E2: Sub Total | F2: GST | G2: Total
B3: ASRS | E3: =SUM(E4:E11) -> 306000000 | F3: =SUM(F4:F11) -> 55080000 | G3: =E3+F3 -> 361080000
B4: Racking system | C4: 8928 | D4: 14278 | E4: =D4*C4 -> 127473984 | F4: =E4*0.18 -> 22945317 | G4: =E4+F4 -> 1.504193e+08
B5: Cladding for high bay | C5: 50 | D5: 240000 | E5: =D5*C5 -> 12000000 | F5: =E5*0.18 -> 2160000 | G5: =E5+F5 -> 14160000
B6: Double deep Stacker crane | C6: 20 | D6: 2765000 | E6: =D6*C6 -> 55300000 | F6: =E6*0.18 -> 9954000 | G6: =E6+F6 -> 65254000
B7: Bottom Rail with aisle accessories | C7: 4 | D7: 3362696 | E7: =D7*C7 -> 13450784 | F7: =E7*0.18 -> 2421141.1 | G7: =E7+F7 -> 15871925
B8: Conveyor system | C8: 50 | D8: 298000 | E8: =D8*C8 -> 14900000 | F8: =E8*0.18 -> 2682000 | G8: =E8+F8 -> 17582000
B9: Critical spares | C9: 2 | D9: 1400000 | E9: =D9*C9 -> 2800000 | F9: =E9*0.18 -> 504000 | G9: =E9+F9 -> 3304000
B10: Metal pallets | C10: =C4 -> 8928 | D10: 9000 | E10: =D10*C10 -> 80352000 | F10: =E10*0.18 -> 14463360 | G10: =E10+F10 -> 94815360
B11: Discount | E11: -276768 | F11: =E11*0.18 -> -49818.24 | G11: =E11+F11 -> -326586.24
B12: Civil Cost | E12: =SUM(E13:E23) -> 75737500 | F12: =SUM(F13:F23) -> 13632750 | G12: =E12+F12 -> 89370250
B13: Earthworks and soiling | E13: 13500000 | F13: =E13*0.18 -> 2430000 | G13: =F13+E13 -> 15930000
B14: PCC works | E14: 4500000 | F14: =E14*0.18 -> 810000 | G14: =F14+E14 -> 5310000
B15: RCC works | E15: 30000000 | F15: =E15*0.18 -> 5400000 | G15: =F15+E15 -> 35400000
B16: Shuttering | E16: 1250000 | F16: =E16*0.18 -> 225000 | G16: =F16+E16 -> 1475000
B17: TMT bards Fe 500 | E17: 21000000 | F17: =E17*0.18 -> 3780000 | G17: =F17+E17 -> 24780000
B18: Masonary works | E18: 600000 | F18: =E18*0.18 -> 108000 | G18: =F18+E18 -> 708000
B19: Plastering | E19: 487500 | F19: =E19*0.18 -> 87750 | G19: =F19+E19 -> 575250
B20: VDF Flooring | E20: 720000 | F20: =E20*0.18 -> 129600 | G20: =F20+E20 -> 849600
B21: J BOLTS installation | E21: 1600000 | F21: =E21*0.18 -> 288000 | G21: =F21+E21 -> 1888000
B22: Baseplate Grouting | E22: 880000 | F22: =E22*0.18 -> 158400 | G22: =F22+E22 -> 1038400
B23: Miscellenous | E23: 1200000 | F23: =E23*0.18 -> 216000 | G23: =F23+E23 -> 1416000
B24: Road | E24: 14326335 | F24: =E24*0.18 -> 2578740.3 | G24: =F24+E24 -> 16905075
B25: Electrical
B26: CDA
B27: FHS and FAS for the ASRS
B28: Dock levellers | C28: 8 | D28: 429544 | E28: =C28*D28 -> 3436352 | F28: =E28*0.18 -> 618543.36 | G28: =(D28+F28)*C28 -> 8384698.9
B29: Contingency | C29: 0.05 | G29: =C29*SUM(G12,G3,G24,G28) -> 23787001
B30: Pre - operating expenses | G30: ='Pre - operating expense'!H11 -> 5412517
B31: IDC | G31: ='Term Loan'!A44*10^7 -> 34026072 | H31: =G31/G35 -> 0.062818085
B32: Finance cost | G32: =0.5%*SUM(G24:G31,G12,G3) -> 2694828.1
B33: Working Capital Margin
B35: Total | G35: =G3+G28+G30+G31+G32+G33+G29+G12+G24+G25+G27+G26 -> 5.4166044e+08
B37: Project Financing
B38: Debt | D38: =Inputs!J6 -> 1 | G38: =D38*G35 -> 5.4166044e+08
B39: Equity | D39: =Inputs!J7 -> 1e-12 | G39: =D39*G35 -> 0.00054166044
B40: Total | D40: =SUM(D38:D39) -> 1 | G40: =SUM(G38:G39) -> 5.4166044e+08

Sheet Pre - operating expense
B2: Sr. No. | C2: Position | D2: Number | E2: Monthly cost | F2: Monthly total | G2: No. of months | H2: Total cost
B3: 1 | C3: Site Engineer | D3: 1 | E3: 40000 | F3: =D3*E3 -> 40000 | G3: =Inputs!$G$4 -> 14 | H3: =F3*G3 -> 560000
B4: 2 | C4: Travelling expense | D4: 1 | E4: 10000 | F4: =D4*E4 -> 10000 | G4: =Inputs!$G$4 -> 14 | H4: =F4*G4 -> 140000
B5: 3 | C5: Admin expenses during implementation | D5: 1 | E5: 10000 | F5: =D5*E5 -> 10000 | G5: =Inputs!$G$4 -> 14 | H5: =F5*G5 -> 140000
B6: 4 | C6: Consultant charges | D6: 1 | E6: 0 | F6: 500000 | G6: 1 | H6: =F6*G6 -> 500000
B7: 5 | C7: Project insurance | D7: 0.01 | F7: =D7*SUM('Project Cost Details'!G3,'Project Cost Details'!G28,'Project Cost Details'!G29) -> 3932517 | H7: =F7 -> 3932517
B8: 6 | C8: Miscellaneous Expenses | D8: 1 | E8: 10000 | F8: =D8*E8 -> 10000 | G8: =Inputs!$G$4 -> 14 | H8: =F8*G8 -> 140000
F9: =D9*E9 -> 0 | G9: =Inputs!$G$4 -> 14 | H9: =F9*G9 -> 0
F10: =D10*E10 -> 0 | G10: =Inputs!$G$4 -> 14 | H10: =F10*G10 -> 0
C11: Total | F11: =SUM(F3:F10) -> 4502517 | H11: =SUM(H3:H10) -> 5412517

Sheet HSTL 
B2: Year | C2: 0 | D2: 1 | E2: =D2+1 -> 2 | F2: =E2+1 -> 3 | G2: =F2+1 -> 4 | H2: =G2+1 -> 5 | I2: =H2+1 -> 6 | J2: =I2+1 -> 7 | K2: =J2+1 -> 8 | L2: =K2+1 -> 9 | ... AG2: =AF2+1 -> 30
B3: Cost | C3: =3.85*1.18 -> 4.543
B4: Contingency | C4: =C3*2% -> 0.09086
B5: Insurance | C5: =C3*0.5% -> 0.022715
B6: Total cost | C6: =SUM(C2:C5) -> 4.656575
B8: Lease area | C8: sq. ft. | D8: =Inputs!$N$15 -> 248396 | E8: =Inputs!$N$15 -> 248396 | F8: =Inputs!$N$15 -> 248396 | G8: =Inputs!$N$15 -> 248396 | H8: =Inputs!$N$15 -> 248396 | I8: =Inputs!$N$15 -> 248396 | J8: =Inputs!$N$15 -> 248396 | K8: =Inputs!$N$15 -> 248396 | ... AG8: =Inputs!$N$15 -> 248396
B9: Per sq. ft. cost | C9: 45 | D9: =D8*$C$9 -> 11177820 | E9: =E8*$C$9 -> 11177820 | F9: =F8*$C$9 -> 11177820 | G9: =G8*$C$9 -> 11177820 | H9: =H8*$C$9 -> 11177820 | I9: =I8*$C$9 -> 11177820 | J9: =J8*$C$9 -> 11177820 | K9: =K8*$C$9 -> 11177820 | ... AG9: =AG8*$C$9 -> 11177820
B10: Total | D10: =D9/10^7 -> 1.117782 | E10: =E9/10^7 -> 1.117782 | F10: =F9/10^7 -> 1.117782 | G10: =G9/10^7 -> 1.117782 | H10: =H9/10^7 -> 1.117782 | I10: =I9/10^7 -> 1.117782 | J10: =J9/10^7 -> 1.117782 | K10: =K9/10^7 -> 1.117782 | ... AG10: =AG9/10^7 -> 1.117782
B11: Escalation | E11: 0.05 | F11: 0.05 | G11: 0.05 | H11: 0.05 | I11: 0.05 | J11: 0.05 | K11: 0.05 | L11: 0.05 | M11: 0.05 | N11: 0.05 | O11: 0.05 | P11: 0.05 | Q11: 0.05 | R11: 0.05 | S11: 0.05 | T11: 0.05 | U11: 0.05 | V11: 0.05 | W11: 0.05 | X11: 0.05 | Y11: 0.05 | Z11: 0.05 | AA11: 0.05 | AB11: 0.05 | AC11: 0.05 | AD11: 0.05 | AE11: 0.05 | AF11: 0.05 | AG11: 0.05
B12: Total | D12: =D10 -> 1.117782 | E12: =D12*(1+$E$11) -> 1.1736711 | F12: =E12*(1+$E$11) -> 1.2323546 | G12: =F12*(1+$E$11) -> 1.2939724 | H12: =G12*(1+$E$11) -> 1.358671 | I12: =H12*(1+$E$11) -> 1.4266046 | J12: =I12*(1+$E$11) -> 1.4979348 | K12: =J12*(1+$E$11) -> 1.5728315 | L12: =K12*(1+$E$11) -> 1.6514731 | ... AG12: =AF12*(1+$E$11) -> 4.6009423
B14: Expense
B15: Depreciaton | D15: =$C$6*95%/30 -> 0.14745821 | E15: =$C$6*95%/30 -> 0.14745821 | F15: =$C$6*95%/30 -> 0.14745821 | G15: =$C$6*95%/30 -> 0.14745821 | H15: =$C$6*95%/30 -> 0.14745821 | I15: =$C$6*95%/30 -> 0.14745821 | J15: =$C$6*95%/30 -> 0.14745821 | K15: =$C$6*95%/30 -> 0.14745821 | ... AG15: =$C$6*95%/30 -> 0.14745821
B17: EBIT | D17: =D10-D15 -> 0.97032379 | E17: =E10-E15 -> 0.97032379 | F17: =F10-F15 -> 0.97032379 | G17: =G10-G15 -> 0.97032379 | H17: =H10-H15 -> 0.97032379 | I17: =I10-I15 -> 0.97032379 | J17: =J10-J15 -> 0.97032379 | K17: =K10-K15 -> 0.97032379 | ... AG17: =AG10-AG15 -> 0.97032379
B19: Tax | D19: =D17*25.18% -> 0.24432753 | E19: =E17*25.18% -> 0.24432753 | F19: =F17*25.18% -> 0.24432753 | G19: =G17*25.18% -> 0.24432753 | H19: =H17*25.18% -> 0.24432753 | I19: =I17*25.18% -> 0.24432753 | J19: =J17*25.18% -> 0.24432753 | K19: =K17*25.18% -> 0.24432753 | ... AG19: =AG17*25.18% -> 0.24432753
B21: PAT | D21: =D17-D19 -> 0.72599626 | E21: =E17-E19 -> 0.72599626 | F21: =F17-F19 -> 0.72599626 | G21: =G17-G19 -> 0.72599626 | H21: =H17-H19 -> 0.72599626 | I21: =I17-I19 -> 0.72599626 | J21: =J17-J19 -> 0.72599626 | K21: =K17-K19 -> 0.72599626 | ... AG21: =AG17-AG19 -> 0.72599626
B24: IRR | C24: =-C6 -> -4.656575 | D24: =D21+D15 -> 0.87345447 | E24: =E21+E15 -> 0.87345447 | F24: =F21+F15 -> 0.87345447 | G24: =G21+G15 -> 0.87345447 | H24: =H21+H15 -> 0.87345447 | I24: =I21+I15 -> 0.87345447 | J24: =J21+J15 -> 0.87345447 | K24: =K21+K15 -> 0.87345447 | ... AG24: =AG21+AG15 -> 0.87345447
A25: 0.2 | B25: DCF @ 20% | C25: =C24*(1/(1+$A$25)^C2) -> -4.656575 | D25: =D24*(1/(1+$A$25)^D2) -> 0.72787872 | E25: =E24*(1/(1+$A$25)^E2) -> 0.6065656 | F25: =F24*(1/(1+$A$25)^F2) -> 0.50547133 | G25: =G24*(1/(1+$A$25)^G2) -> 0.42122611 | H25: =H24*(1/(1+$A$25)^H2) -> 0.35102176 | I25: =I24*(1/(1+$A$25)^I2) -> 0.29251813 | J25: =J24*(1/(1+$A$25)^J2) -> 0.24376511 | ... AG25: =AG24*(1/(1+$A$25)^AG2) -> 0.0036796193
B27: NPV | C27: =SUM(C25:AG25) -> -0.30770077
B28: IRR | C28: =IRR(C25:AG25) -> -0.011280088
D30: =D15/D8*10^7 -> 5.9364164

Sheet Warehouse Inventory 
B2: Month | C2: Sept | D2: Oct | E2: Nov | F2: Dec | G2: Jan | H2: Feb | I2: Average
B3: Radiant
B4: Opening | F4: =E6 -> 48307 | G4: =F6 -> 39341 | I4: =AVERAGE(F4:G4) -> 43824
B5: Change in inventory | F5: =F6-F4 -> -8966 | G5: =G6-G4 -> 60444 | I5: =AVERAGE(F5:G5) -> 25739
B6: Closing | E6: =22877+9094+16181+155 -> 48307 | F6: =19708+8990+10488+155 -> 39341 | G6: =31790+27044+40951+0 -> 99785 | I6: =AVERAGE(E6:G6) -> 62477.667
B7: Utilisation
B10: Kothur
B11: Opening | C11: 7440 | D11: =C13 -> 252571 | E11: =D13 -> 277176 | F11: =E13 -> 218079 | G11: =F13 -> 263702 | I11: =AVERAGE(F11:G11) -> 240890.5
B12: Change in inventory | C12: =C13-C11 -> 245131 | D12: =D13-D11 -> 24605 | E12: =E13-E11 -> -59097 | F12: =F13-F11 -> 45623 | G12: =G13-G11 -> 8167 | I12: =AVERAGE(C12:G12) -> 52885.8
B13: Closing | C13: 252571 | D13: 277176 | E13: 218079 | F13: 263702 | G13: 271869 | I13: =AVERAGE(C13:G13) -> 256679.4
B15: Total Storage potential
B16: Radiant + Kothur | I16: =('Radiant Reference'!C3+'Kothur Reference'!C3)*31 -> 379990
B17: Total average closing | I17: =I6+I13 -> 319157.07
B18: Utilisation | I18: =I17/I16 -> 0.83990912

Sheet Radiant Reference
B1: Warehouse cost to company | G1: Pallets availabity
B2: Total space available | C2: 71858 | D2: sq. ft. | G2: Storage duration of each pallet | H2: 1 | I2: days
B3: Maximum storage capacity | C3: =89990/31 -> 2902.9032 | D3: pallets | E3: =89990/31 -> 2902.9032 | G3: Annual inventory turnover | H3: =365/H2 -> 365 | I3: times per year
A5: 1 | B5: Rentals
B6: Rent/month | C6: 22 | D6: Rs./sq.ft/month | I6: Sqft | J6: Pallots | M6: Cost per pallet
B7: Total rent /month | C7: =C6*C2*1.18 -> 1865433.7 | D7: Rs./month | F7: Kottur | G7: ='Kothur Reference'!C7 -> 7099747.5 | I7: ='Kothur Reference'!C2 -> 261597.18 | J7: ='Kothur Reference'!C3 -> 9354.8387 | K7: =G7/I7 -> 27.14 | M7: =G7/J7 -> 758.93852
B8: Security Deposit (SD) | C8: =C7*3 -> 5596301 | D8: 3 months | F8: Rediant | G8: =C7 -> 1865433.7 | I8: =C2 -> 71858 | J8: =C3 -> 2902.9032 | K8: =G8/I8 -> 25.96 | M8: =G8/J8 -> 642.60967 | P8: 0.8
B9: Total annual cost excl. SD | C9: =C7*12 -> 22385204 | D9: Rs./year | G9: =SUM(G7:G8) -> 8965181.1 | I9: =SUM(I7:I8) -> 333455.18 | J9: =SUM(J7:J8) -> 12257.742 | K9: =G9/I9 -> 26.885716 | M9: =G9/J9 -> 731.38929 | N9: =M9/30 -> 24.379643 | O9: =8928 -> 8928 | P9: =O9*P8*N9*365 -> 63557144
B10: y.o.y. escalation | C10: 0.01 | M10: =Computations!C9 -> 8928 | P10: =P9/10^7 -> 6.3557144
B11: Rent period | C11: 1 | D11: year | M11: =M9*M10 -> 6529843.6
M12: =M11*12 -> 78358123
A13: 2 | B13: Manpower Requirement | G13: =G7*12 -> 85196970 | M13: =M12/10^7 -> 7.8358123
B14: Total number of employees | D14: Monthly salary | E14: Total annual cost | G14: =10000*365*10 -> 36500000
B15: Security | C15: 2 | D15: 15000 | E15: =D15*C15*12 -> 360000 | G15: =G13+G14 -> 1.2169697e+08
B16: Site incharge | C16: 1 | D16: 50000 | E16: =D16*C16*12 -> 600000
B17: Managers | C17: 3 | D17: ='Kothur Reference'!D17 -> 15000 | E17: =D17*C17*12 -> 540000
B18: Operators | C18: 8 | D18: ='Kothur Reference'!D18 -> 12000 | E18: =D18*C18*12 -> 1152000
B19: Total | E19: =SUM(E15:E18) -> 2652000
B20: Escalation | E20: 0.05
A22: 3 | B22: IT assets | D22: Cost per month | E22: Total annual cost
B23: Printer | C23: 1 | D23: 5000 | E23: =D23*C23*12 -> 60000
B24: Laptops | D24: =100000/12 -> 8333.3333 | E24: =D24*12 -> 100000
B25: Wifi | C25: 1 | D25: 1500 | E25: =D25*C25*12 -> 18000
B26: Total | E26: =SUM(E23:E25) -> 178000
A28: 4 | B28: Machineries
B29: Rentals
B30: Rental Electrical Forklifts charges | C30: 2 | D30: 138702.5 | E30: =C30*D30*12 -> 3328860
B31: BOPT | C31: 2 | D31: 50000 | E31: =C31*D31*12 -> 1200000
B32: Total | E32: =SUM(E30:E31) -> 4528860
B33: One time payment
B34: Dock Levellers | C34: 2 | D34: =392044*1.18 -> 462611.92 | E34: =C34*D34 -> 925223.84
B35: Installation | C35: 2 | D35: =16500*1.18 -> 19470 | E35: =C35*D35 -> 38940
B36: Total | E36: =E34+E35 -> 964163.84
A38: 5 | B38: Transportation cost
B39: Monthly contract rate | C39: =1.45*10^5 -> 145000 | D39: Rs./month
B40: GST | C40: =C39*0.18 -> 26100 | D40: Rs./month
B41: Total | C41: =SUM(C39:C40) -> 171100 | D41: Rs./month
B42: Annual cost | C42: =C41*12 -> 2053200 | D42: Rs./year
B43: Escalation | C43: 0.03
B45: Year (in Rs. Cr.) | C45: 1 | D45: =IFERROR(IF(C45+1<=$C$11,C45+1,"-"),"-") -> - | E45: =IFERROR(IF(D45+1<=$C$11,D45+1,"-"),"-") -> - | F45: =IFERROR(IF(E45+1<=$C$11,E45+1,"-"),"-") -> - | G45: =IFERROR(IF(F45+1<=$C$11,F45+1,"-"),"-") -> - | H45: =IFERROR(IF(G45+1<=$C$11,G45+1,"-"),"-") -> - | I45: =IFERROR(IF(H45+1<=$C$11,H45+1,"-"),"-") -> - | J45: =IFERROR(IF(I45+1<=$C$11,I45+1,"-"),"-") -> - | K45: =IFERROR(IF(J45+1<=$C$11,J45+1,"-"),"-") -> - | ... Q45: =IFERROR(IF(P45+1<=$C$11,P45+1,"-"),"-") -> -
B46: Annual rent | C46: =C9/10^7 -> 2.2385204 | D46: =IF(D45="-",0,C46*(1+$C$10)) -> 0 | E46: =IF(E45="-",0,D46*(1+$C$10)) -> 0 | F46: =IF(F45="-",0,E46*(1+$C$10)) -> 0 | G46: =IF(G45="-",0,F46*(1+$C$10)) -> 0 | H46: =IF(H45="-",0,G46*(1+$C$10)) -> 0 | I46: =IF(I45="-",0,H46*(1+$C$10)) -> 0 | J46: =IF(J45="-",0,I46*(1+$C$10)) -> 0 | K46: =IF(K45="-",0,J46*(1+$C$10)) -> 0 | ... Q46: =IF(Q45="-",0,P46*(1+$C$10)) -> 0
B47: SD | C47: =C8/10^7+IF(AND(C45=$C$11,D45="-"),-$C$8/10^7,0) -> 0 | D47: =IF(AND(D45=$C$11,E45="-"),-$C$47,0) -> 0 | E47: =IF(AND(E45=$C$11,F45="-"),-$C$47,0) -> 0 | F47: =IF(AND(F45=$C$11,G45="-"),-$C$47,0) -> 0 | G47: =IF(AND(G45=$C$11,H45="-"),-$C$47,0) -> 0 | H47: =IF(AND(H45=$C$11,I45="-"),-$C$47,0) -> 0 | I47: =IF(AND(I45=$C$11,J45="-"),-$C$47,0) -> 0 | J47: =IF(AND(J45=$C$11,K45="-"),-$C$47,0) -> 0 | K47: =IF(AND(K45=$C$11,L45="-"),-$C$47,0) -> 0 | ... Q47: =IF(AND(Q45=$C$11,R45="-"),-$C$47,0) -> 0
B48: Total | C48: =C46+C47 -> 2.2385204 | D48: =D46+D47 -> 0 | E48: =E46+E47 -> 0 | F48: =F46+F47 -> 0 | G48: =G46+G47 -> 0 | H48: =H46+H47 -> 0 | I48: =I46+I47 -> 0 | J48: =J46+J47 -> 0 | ... M48: =M46+M47 -> 0 | N48: =N46+Q47 -> 0 | O48: =O46+O47 -> 0 | P48: =P46+P47 -> 0 | Q48: =Q46+Q47 -> 0
B49: Electricity | C49: =28660*12/10^7 -> 0.034392 | D49: =IF(D45="-",0,C49*(1+1%)) -> 0 | E49: =IF(E45="-",0,D49*(1+1%)) -> 0 | F49: =IF(F45="-",0,E49*(1+1%)) -> 0 | G49: =IF(G45="-",0,F49*(1+1%)) -> 0 | H49: =IF(H45="-",0,G49*(1+1%)) -> 0 | I49: =IF(I45="-",0,H49*(1+1%)) -> 0 | J49: =IF(J45="-",0,I49*(1+1%)) -> 0 | K49: =IF(K45="-",0,J49*(1+1%)) -> 0 | ... Q49: =IF(Q45="-",0,P49*(1+1%)) -> 0
B50: Manpower | C50: =E19/10^7 -> 0.2652 | D50: =IF(D45="-",0,C50*(1+$E$20)) -> 0 | E50: =IF(E45="-",0,D50*(1+$E$20)) -> 0 | F50: =IF(F45="-",0,E50*(1+$E$20)) -> 0 | G50: =IF(G45="-",0,F50*(1+$E$20)) -> 0 | H50: =IF(H45="-",0,G50*(1+$E$20)) -> 0 | I50: =IF(I45="-",0,H50*(1+$E$20)) -> 0 | J50: =IF(J45="-",0,I50*(1+$E$20)) -> 0 | K50: =IF(K45="-",0,J50*(1+$E$20)) -> 0 | ... Q50: =IF(Q45="-",0,P50*(1+$E$20)) -> 0
B51: IT Cost | C51: =(E23+E24+E25)/10^7 -> 0.0178 | D51: =IF(D45="-",0,$E$25*1.02/10^7) -> 0 | E51: =IF(E45="-",0,D51*1.02) -> 0 | F51: =IF(F45="-",0,E51*1.02) -> 0 | G51: =IF(G45="-",0,F51*1.02) -> 0 | H51: =IF(H45="-",0,G51*1.02) -> 0 | I51: =IF(I45="-",0,H51*1.02) -> 0 | J51: =IF(J45="-",0,I51*1.02) -> 0 | K51: =IF(K45="-",0,J51*1.02) -> 0 | L51: =IF(L45="-",0,K51*1.02) -> 0 | ... Q51: =IF(Q45="-",0,P51*1.02) -> 0
B52: =B28 -> Machineries | C52: =(E36+E31)/10^7+E30/10^7 -> 0.54930238 | D52: =IF(D45="-",0,(E30+E31)/10^7*1.01) -> 0 | E52: =IF(E45="-",0,D52*1.01) -> 0 | F52: =IF(F45="-",0,E52*1.01) -> 0 | G52: =IF(G45="-",0,F52*1.01) -> 0 | H52: =IF(H45="-",0,G52*1.01) -> 0 | I52: =IF(I45="-",0,H52*1.01) -> 0 | J52: =IF(J45="-",0,I52*1.01) -> 0 | K52: =IF(K45="-",0,J52*1.01) -> 0 | L52: =IF(L45="-",0,K52*1.01) -> 0 | ... Q52: =IF(Q45="-",0,P52*1.01) -> 0
B53: Transporatation | C53: =C42/10^7 -> 0.20532 | D53: =IF(D45="-",0,C53*(1+$C$43)) -> 0 | E53: =IF(E45="-",0,D53*(1+$C$43)) -> 0 | F53: =IF(F45="-",0,E53*(1+$C$43)) -> 0 | G53: =IF(G45="-",0,F53*(1+$C$43)) -> 0 | H53: =IF(H45="-",0,G53*(1+$C$43)) -> 0 | I53: =IF(I45="-",0,H53*(1+$C$43)) -> 0 | J53: =IF(J45="-",0,I53*(1+$C$43)) -> 0 | K53: =IF(K45="-",0,J53*(1+$C$43)) -> 0 | ... Q53: =IF(Q45="-",0,P53*(1+$C$43)) -> 0
B54: Total cost | C54: =C48+C49+C50+C51+C52+C53 -> 3.3105348 | D54: =D48+D49+D50+D51+D52+D53 -> 0 | E54: =E48+E49+E50+E51+E52+E53 -> 0 | F54: =F48+F49+F50+F51+F52+F53 -> 0 | G54: =G48+G49+G50+G51+G52+G53 -> 0 | H54: =H48+H49+H50+H51+H52+H53 -> 0 | I54: =I48+I49+I50+I51+I52+I53 -> 0 | J54: =J48+J49+J50+J51+J52+J53 -> 0 | ... Q54: =Q48+Q49+Q50+Q51+Q52+Q53 -> 0
A55: 0.2 | B55: Present Value | C55: =IFERROR(C54*(1/((1+A55)^(C45))),0) -> 2.758779 | D55: =IFERROR(D54*(1/((1+B55)^(D45))),0) -> 0 | E55: =IFERROR(E54*(1/((1+C55)^(E45))),0) -> 0 | F55: =IFERROR(F54*(1/((1+D55)^(F45))),0) -> 0 | G55: =IFERROR(G54*(1/((1+E55)^(G45))),0) -> 0 | H55: =IFERROR(H54*(1/((1+F55)^(H45))),0) -> 0 | I55: =IFERROR(I54*(1/((1+G55)^(I45))),0) -> 0 | J55: =IFERROR(J54*(1/((1+H55)^(J45))),0) -> 0 | ... Q55: =IFERROR(Q54*(1/((1+O55)^(Q45))),0) -> 0
B56: Cost per pallet per year (Rs.) | C56: =(C54/($C$3*$H$3))*10^7 -> 31.244439 | D56: =(D54/($C$3*$H$3))*10^7 -> 0 | E56: =(E54/($C$3*$H$3))*10^7 -> 0 | F56: =(F54/($C$3*$H$3))*10^7 -> 0 | G56: =(G54/($C$3*$H$3))*10^7 -> 0 | H56: =(H54/($C$3*$H$3))*10^7 -> 0 | I56: =(I54/($C$3*$H$3))*10^7 -> 0 | J56: =(J54/($C$3*$H$3))*10^7 -> 0 | ... Q56: =(Q54/($C$3*$H$3))*10^7 -> 0
B57: Average (Rs.) | C57: =AVERAGE(C56) -> 31.244439 | D57: Cost per pallet per day
G62: =MAX(G153:G214) -> 131449 | Y62: =AVERAGE(Y67:Y68) -> 31.816157
B63: DATE | C63: Month | D63: O/P stock | E63: Receipt | F63: Dispatches | G63: Closing stock | H63: Change | I63: Average Inventory Level | N63: Start | O63: End | P63: Days | Q63: Opening | R63: Change average | S63: Closing | T63: AIL | U63: Pallets | V63: Rental Cost + CAPEX | W63: Operational Cost | X63: Total | Y63: Rs./pallet/day | Z63: Utilisation
B64: =B65-1 -> 45569 | C64: =MONTH(B64) -> 10 | H64: =G64-D64 -> 0 | I64: =(D64+G64)/2 -> 0 | M64: =MONTH(N64) -> 10 | N64: 45566 | O64: 45596 | P64: =_xlfn.DAYS(O64,N64)+1 -> 31 | Q64: =AVERAGEIF($C$64:$C$214,M64,$D$64:$D$214) -> #DIV/0! | R64: =AVERAGEIF($C$64:$C$214,M64,$H$64:$H$214) -> 0 | S64: =AVERAGEIF($C$64:$C$214,M64,$G$64:$G$214) -> #DIV/0! | T64: =AVERAGEIF($C$64:$C$214,M64,$I$64:$I$214) -> 0 | U64: =T64/31 -> 0 | V64: =C7+(E36+C8)/12 -> 2412139.1 | W64: =(E19+E26+E32+C42)/12 -> 784338.33 | X64: =V64+W64 -> 3196477.4 | Y64: =X64/(T64/31)/P64 -> #DIV/0! | Z64: =S64/$G$62 -> #DIV/0!
B65: =B66-1 -> 45570 | C65: =MONTH(B65) -> 10 | H65: =G65-D65 -> 0 | I65: =(D65+G65)/2 -> 0 | M65: =MONTH(N65) -> 11 | N65: =O64+1 -> 45597 | O65: =EOMONTH(N65,0.5) -> 45626 | P65: =_xlfn.DAYS(O65,N65)+1 -> 30 | Q65: =AVERAGEIF($C$64:$C$214,M65,$D$64:$D$214) -> #DIV/0! | R65: =AVERAGEIF($C$64:$C$214,M65,$H$64:$H$214) -> 0 | S65: =AVERAGEIF($C$64:$C$214,M65,$G$64:$G$214) -> #DIV/0! | T65: =AVERAGEIF($C$64:$C$214,M65,$I$64:$I$214) -> 0 | U65: =T65/31 -> 0 | V65: =V64 -> 2412139.1 | W65: =W64 -> 784338.33 | X65: =V65+W65 -> 3196477.4 | Y65: =X65/(T65/31)/P65 -> #DIV/0! | Z65: =S65/$G$62 -> #DIV/0!
B66: =B67-1 -> 45571 | C66: =MONTH(B66) -> 10 | H66: =G66-D66 -> 0 | I66: =(D66+G66)/2 -> 0 | M66: =MONTH(N66) -> 12 | N66: =O65+1 -> 45627 | O66: =EOMONTH(N66,0.5) -> 45657 | P66: =_xlfn.DAYS(O66,N66)+1 -> 31 | Q66: =AVERAGEIF($C$64:$C$214,M66,$D$64:$D$214) -> #DIV/0! | R66: =AVERAGEIF($C$64:$C$214,M66,$H$64:$H$214) -> 0 | S66: =AVERAGEIF($C$64:$C$214,M66,$G$64:$G$214) -> 0 | T66: =AVERAGEIF($C$64:$C$211,M66,$I$64:$I$211) -> 0 | U66: =T66/31 -> 0 | V66: =V65 -> 2412139.1 | W66: =W65 -> 784338.33 | X66: =V66+W66 -> 3196477.4 | Y66: =X66/(T66/31)/P66 -> #DIV/0! | Z66: =S66/$G$62 -> 0
B67: =B68-1 -> 45572 | C67: =MONTH(B67) -> 10 | H67: =G67-D67 -> 0 | I67: =(D67+G67)/2 -> 0 | M67: =MONTH(N67) -> 1 | N67: =O66+1 -> 45658 | O67: =EOMONTH(N67,0.5) -> 45688 | P67: =_xlfn.DAYS(O67,N67)+1 -> 31 | Q67: =AVERAGEIF($C$64:$C$214,M67,$D$64:$D$214) -> 118499.26 | R67: =AVERAGEIF($C$64:$C$214,M67,$H$64:$H$214) -> -268.03226 | S67: =AVERAGEIF($C$64:$C$214,M67,$G$64:$G$214) -> 118231.23 | T67: =AVERAGEIF($C$64:$C$211,M67,$I$64:$I$211) -> 118365.24 | U67: =T67/31 -> 3818.2336 | V67: =V66 -> 2412139.1 | W67: =W66 -> 784338.33 | X67: =V67+W67 -> 3196477.4 | Y67: =X67/(T67/31)/P67 -> 27.005203 | Z67: =S67/$G$62 -> 0.89944561
B68: =B69-1 -> 45573 | C68: =MONTH(B68) -> 10 | H68: =G68-D68 -> 0 | I68: =(D68+G68)/2 -> 0 | M68: =MONTH(N68) -> 2 | N68: =O67+1 -> 45689 | O68: =EOMONTH(N68,0.5) -> 45716 | P68: =_xlfn.DAYS(O68,N68)+1 -> 28 | Q68: =AVERAGEIF($C$64:$C$214,M68,$D$64:$D$214) -> 97527.214 | R68: =AVERAGEIF($C$64:$C$214,M68,$H$64:$H$214) -> -1811.9286 | S68: =AVERAGEIF($C$64:$C$214,M68,$G$64:$G$214) -> 95715.286 | T68: =AVERAGEIF($C$64:$C$211,M68,$I$64:$I$211) -> 96621.25 | U68: =T68/31 -> 3116.8145 | V68: =V67 -> 2412139.1 | W68: =W67 -> 784338.33 | X68: =V68+W68 -> 3196477.4 | Y68: =X68/(T68/31)/P68 -> 36.62711 | Z68: =S68/$G$62 -> 0.7281553
B69: =B70-1 -> 45574 | C69: =MONTH(B69) -> 10 | H69: =G69-D69 -> 0 | I69: =(D69+G69)/2 -> 0
B70: =B71-1 -> 45575 | C70: =MONTH(B70) -> 10 | H70: =G70-D70 -> 0 | I70: =(D70+G70)/2 -> 0
B71: =B72-1 -> 45576 | C71: =MONTH(B71) -> 10 | H71: =G71-D71 -> 0 | I71: =(D71+G71)/2 -> 0
B72: =B73-1 -> 45577 | C72: =MONTH(B72) -> 10 | H72: =G72-D72 -> 0 | I72: =(D72+G72)/2 -> 0
B73: =B74-1 -> 45578 | C73: =MONTH(B73) -> 10 | H73: =G73-D73 -> 0 | I73: =(D73+G73)/2 -> 0
B74: =B75-1 -> 45579 | C74: =MONTH(B74) -> 10 | H74: =G74-D74 -> 0 | I74: =(D74+G74)/2 -> 0
B75: =B76-1 -> 45580 | C75: =MONTH(B75) -> 10 | H75: =G75-D75 -> 0 | I75: =(D75+G75)/2 -> 0
B76: =B77-1 -> 45581 | C76: =MONTH(B76) -> 10 | H76: =G76-D76 -> 0 | I76: =(D76+G76)/2 -> 0
B77: =B78-1 -> 45582 | C77: =MONTH(B77) -> 10 | H77: =G77-D77 -> 0 | I77: =(D77+G77)/2 -> 0
B78: =B79-1 -> 45583 | C78: =MONTH(B78) -> 10 | H78: =G78-D78 -> 0 | I78: =(D78+G78)/2 -> 0
B79: =B80-1 -> 45584 | C79: =MONTH(B79) -> 10 | H79: =G79-D79 -> 0 | I79: =(D79+G79)/2 -> 0
B80: =B81-1 -> 45585 | C80: =MONTH(B80) -> 10 | H80: =G80-D80 -> 0 | I80: =(D80+G80)/2 -> 0
... B151: =B152-1 -> 45656 | C151: =MONTH(B151) -> 12 | H151: =G151-D151 -> 0 | I151: =(D151+G151)/2 -> 0
B152: =B153-1 -> 45657 | C152: =MONTH(B152) -> 12 | G152: 0 | H152: =G152-D152 -> 0 | I152: =(D152+G152)/2 -> 0
B153: =B154-1 -> 45658 | C153: =MONTH(B153) -> 1 | D153: =G153+F153-E153 -> 131874 | E153: 11436 | F153: 23786 | G153: =D154 -> 119524 | H153: =G153-D153 -> -12350 | I153: =(D153+G153)/2 -> 125699
B154: =B155-1 -> 45659 | C154: =MONTH(B154) -> 1 | D154: =G154+F154-E154 -> 119524 | E154: 12019 | F154: 10141 | G154: =D155 -> 121402 | H154: =G154-D154 -> 1878 | I154: =(D154+G154)/2 -> 120463
B155: =B156-1 -> 45660 | C155: =MONTH(B155) -> 1 | D155: =G155+F155-E155 -> 121402 | E155: 13981 | F155: 13019 | G155: =D156 -> 122364 | H155: =G155-D155 -> 962 | I155: =(D155+G155)/2 -> 121883
B156: =B157-1 -> 45661 | C156: =MONTH(B156) -> 1 | D156: =G156+F156-E156 -> 122364 | E156: 14067 | F156: 14063 | G156: =D157 -> 122368 | H156: =G156-D156 -> 4 | I156: =(D156+G156)/2 -> 122366
B157: =B158-1 -> 45662 | C157: =MONTH(B157) -> 1 | D157: =G157+F157-E157 -> 122368 | E157: 14237 | F157: 11089 | G157: =D158 -> 125516 | H157: =G157-D157 -> 3148 | I157: =(D157+G157)/2 -> 123942
B158: =B159-1 -> 45663 | C158: =MONTH(B158) -> 1 | D158: =G158+F158-E158 -> 125516 | E158: 1583 | F158: 6970 | G158: =D159 -> 120129 | H158: =G158-D158 -> -5387 | I158: =(D158+G158)/2 -> 122822.5
B159: =B160-1 -> 45664 | C159: =MONTH(B159) -> 1 | D159: =G159+F159-E159 -> 120129 | E159: 14679 | F159: 10950 | G159: =D160 -> 123858 | H159: =G159-D159 -> 3729 | I159: =(D159+G159)/2 -> 121993.5
B160: =B161-1 -> 45665 | C160: =MONTH(B160) -> 1 | D160: =G160+F160-E160 -> 123858 | E160: 14260 | F160: 19132 | G160: =D161 -> 118986 | H160: =G160-D160 -> -4872 | I160: =(D160+G160)/2 -> 121422
B161: =B162-1 -> 45666 | C161: =MONTH(B161) -> 1 | D161: =G161+F161-E161 -> 118986 | E161: 14231 | F161: 18418 | G161: =D162 -> 114799 | H161: =G161-D161 -> -4187 | I161: =(D161+G161)/2 -> 116892.5
B162: =B163-1 -> 45667 | C162: =MONTH(B162) -> 1 | D162: =G162+F162-E162 -> 114799 | E162: 14231 | F162: 13514 | G162: =D163 -> 115516 | H162: =G162-D162 -> 717 | I162: =(D162+G162)/2 -> 115157.5
B163: =B164-1 -> 45668 | C163: =MONTH(B163) -> 1 | D163: =G163+F163-E163 -> 115516 | E163: 13506 | F163: 18346 | G163: =D164 -> 110676 | H163: =G163-D163 -> -4840 | I163: =(D163+G163)/2 -> 113096
B164: =B165-1 -> 45669 | C164: =MONTH(B164) -> 1 | D164: =G164+F164-E164 -> 110676 | E164: 13829 | F164: 13144 | G164: =D165 -> 111361 | H164: =G164-D164 -> 685 | I164: =(D164+G164)/2 -> 111018.5
... B182: =B183-1 -> 45687 | C182: =MONTH(B182) -> 1 | D182: =G182+F182-E182 -> 124702 | E182: 14215 | F182: 15352 | G182: =D183 -> 123565 | H182: =G182-D182 -> -1137 | I182: =(D182+G182)/2 -> 124133.5
B183: 45688 | C183: =MONTH(B183) -> 1 | D183: =G183+F183-E183 -> 123565 | E183: 0 | F183: 0 | G183: =D184 -> 123565 | H183: =G183-D183 -> 0 | I183: =(D183+G183)/2 -> 123565
B184: 45689 | C184: =MONTH(B184) -> 2 | D184: 123565 | E184: 9021 | F184: 8385 | G184: =D184+E184-F184 -> 124201 | H184: =G184-D184 -> 636 | I184: =(D184+G184)/2 -> 123883
B185: 45690 | C185: =MONTH(B185) -> 2 | D185: =G184 -> 124201 | E185: 9641 | F185: 5828 | G185: =D185+E185-F185 -> 128014 | H185: =G185-D185 -> 3813 | I185: =(D185+G185)/2 -> 126107.5
B186: 45691 | C186: =MONTH(B186) -> 2 | D186: =G185 -> 128014 | E186: 9573 | F186: 6138 | G186: =D186+E186-F186 -> 131449 | H186: =G186-D186 -> 3435 | I186: =(D186+G186)/2 -> 129731.5
B187: 45692 | C187: =MONTH(B187) -> 2 | D187: =G186 -> 131449 | E187: 9804 | F187: 10269 | G187: =D187+E187-F187 -> 130984 | H187: =G187-D187 -> -465 | I187: =(D187+G187)/2 -> 131216.5
B188: 45693 | C188: =MONTH(B188) -> 2 | D188: =G187 -> 130984 | E188: 9041 | F188: 14224 | G188: =D188+E188-F188 -> 125801 | H188: =G188-D188 -> -5183 | I188: =(D188+G188)/2 -> 128392.5
B189: 45694 | C189: =MONTH(B189) -> 2 | D189: =G188 -> 125801 | E189: 8837 | F189: 6090 | G189: =D189+E189-F189 -> 128548 | H189: =G189-D189 -> 2747 | I189: =(D189+G189)/2 -> 127174.5
B190: 45695 | C190: =MONTH(B190) -> 2 | D190: =G189 -> 128548 | E190: 9052 | F190: 16961 | G190: =D190+E190-F190 -> 120639 | H190: =G190-D190 -> -7909 | I190: =(D190+G190)/2 -> 124593.5
B191: 45696 | C191: =MONTH(B191) -> 2 | D191: =G190 -> 120639 | E191: 9805 | F191: 17765 | G191: =D191+E191-F191 -> 112679 | H191: =G191-D191 -> -7960 | I191: =(D191+G191)/2 -> 116659
B192: 45697 | C192: =MONTH(B192) -> 2 | D192: =G191 -> 112679 | E192: 8618 | F192: 11968 | G192: =D192+E192-F192 -> 109329 | H192: =G192-D192 -> -3350 | I192: =(D192+G192)/2 -> 111004
B193: 45698 | C193: =MONTH(B193) -> 2 | D193: =G192 -> 109329 | E193: 9234 | F193: 13647 | G193: =D193+E193-F193 -> 104916 | H193: =G193-D193 -> -4413 | I193: =(D193+G193)/2 -> 107122.5
B194: 45699 | C194: =MONTH(B194) -> 2 | D194: =G193 -> 104916 | E194: 8896 | F194: 10172 | G194: =D194+E194-F194 -> 103640 | H194: =G194-D194 -> -1276 | I194: =(D194+G194)/2 -> 104278
B195: 45700 | C195: =MONTH(B195) -> 2 | D195: =G194 -> 103640 | E195: 9889 | F195: 11215 | G195: =D195+E195-F195 -> 102314 | H195: =G195-D195 -> -1326 | I195: =(D195+G195)/2 -> 102977
B196: 45701 | C196: =MONTH(B196) -> 2 | D196: =G195 -> 102314 | E196: 9172 | F196: 11734 | G196: =D196+E196-F196 -> 99752 | H196: =G196-D196 -> -2562 | I196: =(D196+G196)/2 -> 101033
...

Sheet Kothur Reference
B1: Warehouse cost to company | G1: Pallets availabity
B2: Total space available | C2: 261597.18 | D2: sq. ft. | G2: Storage duration of each pallet | H2: 1 | I2: days
B3: Maximum storage capacity | C3: =2.9*10^5/31 -> 9354.8387 | D3: pallets | G3: Annual inventory turnover | H3: =365/H2 -> 365 | I3: times per year
A5: 1 | B5: Rentals
B6: Rent/month | C6: 23 | D6: Rs./sq.ft/month
B7: Total rent /month | C7: =C6*C2*1.18 -> 7099747.5 | D7: Rs./month
B8: Security Deposit (SD) | C8: =C7*3 -> 21299242 | D8: 3 months
B9: Total annual cost excl. SD | C9: =C7*12 -> 85196970 | D9: Rs./year
B10: y.o.y. escalation | C10: 0.05
B11: Rental period | C11: 3 | D11: years
A13: 2 | B13: Manpower Requirement
B14: Total number of employees | D14: Monthly salary | E14: Total annual cost
B15: Security | C15: 2 | D15: 15000 | E15: =D15*C15*12 -> 360000
B16: Site incharge | C16: 3 | D16: 50000 | E16: =D16*C16*12 -> 1800000
B17: Managers | C17: 4 | D17: 15000 | E17: =D17*C17*12 -> 720000
B18: Operators | C18: 23 | D18: 12000 | E18: =D18*C18*12 -> 3312000
B19: Total | E19: =SUM(E15:E18) -> 6192000
B20: Escalation | E20: 0.05
A22: 3 | B22: IT assets | D22: Cost per month | E22: Total annual cost
B23: Printer | C23: 1 | D23: 5000 | E23: =D23*C23*12 -> 60000
B24: Laptops | D24: =100000/12 -> 8333.3333 | E24: =D24*12 -> 100000
B25: Wifi | C25: 1 | D25: 1500 | E25: =D25*C25*12 -> 18000
B26: Total | E26: =SUM(E23:E25) -> 178000
A28: 4 | B28: Machineries
B29: Rentals
B30: Rental Electrical Forklifts charges | C30: 7 | D30: 138702.5 | E30: =C30*D30*12 -> 11651010
B31: BOPT | C31: 2 | D31: 50000 | E31: =C31*D31*12 -> 1200000
B32: Total | E32: =SUM(E30:E31) -> 12851010
B33: One time payment
B34: Dock Levellers | C34: 7 | D34: =392044*1.18 -> 462611.92 | E34: =C34*D34 -> 3238283.4
B35: Installation | C35: 7 | D35: =16500*1.18 -> 19470 | E35: =C35*D35 -> 136290
B36: Total | E36: =E34+E35 -> 3374573.4
A38: 5 | B38: Transport Cost
B39: Total number of daily trips | C39: 15 | D39: # of trips per day
B40: Cost per trip (incl. GST) | C40: =10000*1.18 -> 11800 | D40: Rs./trip
B41: Total annual days | C41: 350 | D41: days
B42: Total cost | C42: =C39*C40*C41 -> 61950000 | D42: Rs./year
B43: escalation | C43: 0.03
B45: Year (in Rs. Cr.) | C45: 1 | D45: =IFERROR(IF(C45+1<=$C$11,C45+1,"-"),"-") -> 2 | E45: =IFERROR(IF(D45+1<=$C$11,D45+1,"-"),"-") -> 3 | F45: =IFERROR(IF(E45+1<=$C$11,E45+1,"-"),"-") -> - | G45: =IFERROR(IF(F45+1<=$C$11,F45+1,"-"),"-") -> - | H45: =IFERROR(IF(G45+1<=$C$11,G45+1,"-"),"-") -> - | I45: =IFERROR(IF(H45+1<=$C$11,H45+1,"-"),"-") -> - | J45: =IFERROR(IF(I45+1<=$C$11,I45+1,"-"),"-") -> - | K45: =IFERROR(IF(J45+1<=$C$11,J45+1,"-"),"-") -> - | ... Q45: =IFERROR(IF(P45+1<=$C$11,P45+1,"-"),"-") -> -
B46: Annual rent | C46: =C9/10^7 -> 8.519697 | D46: =IF(D45="-",0,C46*(1+$C$10)) -> 8.9456818 | E46: =IF(E45="-",0,D46*(1+$C$10)) -> 9.3929659 | F46: =IF(F45="-",0,E46*(1+$C$10)) -> 0 | G46: =IF(G45="-",0,F46*(1+$C$10)) -> 0 | H46: =IF(H45="-",0,G46*(1+$C$10)) -> 0 | I46: =IF(I45="-",0,H46*(1+$C$10)) -> 0 | J46: =IF(J45="-",0,I46*(1+$C$10)) -> 0 | K46: =IF(K45="-",0,J46*(1+$C$10)) -> 0 | ... Q46: =IF(Q45="-",0,P46*(1+$C$10)) -> 0
B47: SD | C47: =C8/10^7 -> 2.1299242 | D47: =IF(AND(D45=$C$11,E45="-"),-$C$47,0) -> 0 | E47: =IF(AND(E45=$C$11,F45="-"),-$C$47,0) -> -2.1299242 | F47: =IF(AND(F45=$C$11,G45="-"),-$C$47,0) -> 0 | G47: =IF(AND(G45=$C$11,H45="-"),-$C$47,0) -> 0 | H47: =IF(AND(H45=$C$11,I45="-"),-$C$47,0) -> 0 | I47: =IF(AND(I45=$C$11,J45="-"),-$C$47,0) -> 0 | J47: =IF(AND(J45=$C$11,K45="-"),-$C$47,0) -> 0 | K47: =IF(AND(K45=$C$11,L45="-"),-$C$47,0) -> 0 | ... Q47: =IF(AND(Q45=$C$11,R45="-"),-$C$47,0) -> 0
B48: Total | C48: =C46+C47 -> 10.649621 | D48: =D46+D47 -> 8.9456818 | E48: =E46+E47 -> 7.2630417 | F48: =F46+F47 -> 0 | G48: =G46+G47 -> 0 | H48: =H46+H47 -> 0 | I48: =I46+I47 -> 0 | J48: =J46+J47 -> 0 | ... M48: =M46+M47 -> 0 | N48: =N46+Q47 -> 0 | O48: =O46+O47 -> 0 | P48: =P46+P47 -> 0 | Q48: =Q46+Q47 -> 0
B49: Electricity | C49: =28660*12/10^7 -> 0.034392 | D49: =IF(D45="-",0,C49*(1+1%)) -> 0.03473592 | E49: =IF(E45="-",0,D49*(1+1%)) -> 0.035083279 | F49: =IF(F45="-",0,E49*(1+1%)) -> 0 | G49: =IF(G45="-",0,F49*(1+1%)) -> 0 | H49: =IF(H45="-",0,G49*(1+1%)) -> 0 | I49: =IF(I45="-",0,H49*(1+1%)) -> 0 | J49: =IF(J45="-",0,I49*(1+1%)) -> 0 | K49: =IF(K45="-",0,J49*(1+1%)) -> 0 | ... Q49: =IF(Q45="-",0,P49*(1+1%)) -> 0
B50: Manpower | C50: =E19/10^7 -> 0.6192 | D50: =IF(D45="-",0,C50*(1+$E$20)) -> 0.65016 | E50: =IF(E45="-",0,D50*(1+$E$20)) -> 0.682668 | F50: =IF(F45="-",0,E50*(1+$E$20)) -> 0 | G50: =IF(G45="-",0,F50*(1+$E$20)) -> 0 | H50: =IF(H45="-",0,G50*(1+$E$20)) -> 0 | I50: =IF(I45="-",0,H50*(1+$E$20)) -> 0 | J50: =IF(J45="-",0,I50*(1+$E$20)) -> 0 | K50: =IF(K45="-",0,J50*(1+$E$20)) -> 0 | ... Q50: =IF(Q45="-",0,P50*(1+$E$20)) -> 0
B51: IT Cost | C51: =(E23+E24+E25)/10^7 -> 0.0178 | D51: =IF(D45="-",0,$E$25*1.02/10^7) -> 0.001836 | E51: =IF(E45="-",0,$E$25*1.02/10^7) -> 0.001836 | F51: =IF(F45="-",0,$E$25*1.02/10^7) -> 0 | G51: =IF(G45="-",0,$E$25*1.02/10^7) -> 0 | H51: =IF(H45="-",0,$E$25*1.02/10^7) -> 0 | I51: =IF(I45="-",0,$E$25*1.02/10^7) -> 0 | J51: =IF(J45="-",0,$E$25*1.02/10^7) -> 0 | K51: =IF(K45="-",0,$E$25*1.02/10^7) -> 0 | ... Q51: =IF(Q45="-",0,$E$25*1.02/10^7) -> 0
B52: =B28 -> Machineries | C52: =(E36+E31)/10^7+E30/10^7 -> 1.6225583 | D52: =IF(D45="-",0,(E30+E31)/10^7*1.01) -> 1.297952 | E52: =IF(E45="-",0,D52*1.01) -> 1.3109315 | F52: =IF(F45="-",0,(G30+G31)/10^7*1.01) -> 0 | G52: =IF(G45="-",0,(H30+H31)/10^7*1.01) -> 0 | H52: =IF(H45="-",0,(I30+I31)/10^7*1.01) -> 0 | I52: =IF(I45="-",0,(J30+J31)/10^7*1.01) -> 0 | J52: =IF(J45="-",0,(K30+K31)/10^7*1.01) -> 0 | K52: =IF(K45="-",0,(L30+L31)/10^7*1.01) -> 0 | L52: =IF(L45="-",0,(M30+M31)/10^7*1.01) -> 0 | M52: =IF(M45="-",0,(N30+N31)/10^7*1.01) -> 0 | ... Q52: =IF(Q45="-",0,(R30+R31)/10^7*1.01) -> 0
B53: Transporatation | C53: =C42/10^7 -> 6.195 | D53: =IF(D45="-",0,C53*(1+$C$43)) -> 6.38085 | E53: =IF(E45="-",0,D53*(1+$C$43)) -> 6.5722755 | F53: =IF(F45="-",0,E53*(1+$C$43)) -> 0 | G53: =IF(G45="-",0,F53*(1+$C$43)) -> 0 | H53: =IF(H45="-",0,G53*(1+$C$43)) -> 0 | I53: =IF(I45="-",0,H53*(1+$C$43)) -> 0 | J53: =IF(J45="-",0,I53*(1+$C$43)) -> 0 | K53: =IF(K45="-",0,J53*(1+$C$43)) -> 0 | ... Q53: =IF(Q45="-",0,P53*(1+$C$43)) -> 0
B54: Total cost | C54: =C48+C49+C50+C51+C52+C53 -> 19.138572 | D54: =D48+D49+D50+D51+D52+D53 -> 17.311216 | E54: =E48+E49+E50+E51+E52+E53 -> 15.865836 | F54: =F48+F49+F50+F51+F52+F53 -> 0 | G54: =G48+G49+G50+G51+G52+G53 -> 0 | H54: =H48+H49+H50+H51+H52+H53 -> 0 | I54: =I48+I49+I50+I51+I52+I53 -> 0 | J54: =J48+J49+J50+J51+J52+J53 -> 0 | ... Q54: =Q48+Q49+Q50+Q51+Q52+Q53 -> 0
B56: Cost per pallet per year (Rs.) | C56: =(C54/($C$3*$H$3))*10^7 -> 56.050611 | D56: =(D54/($C$3*$H$3))*10^7 -> 50.698884 | E56: =(E54/($C$3*$H$3))*10^7 -> 46.46584 | F56: =(F54/($C$3*$H$3))*10^7 -> 0 | G56: =(G54/($C$3*$H$3))*10^7 -> 0 | H56: =(H54/($C$3*$H$3))*10^7 -> 0 | I56: =(I54/($C$3*$H$3))*10^7 -> 0 | J56: =(J54/($C$3*$H$3))*10^7 -> 0 | ... Q56: =(Q54/($C$3*$H$3))*10^7 -> 0
B58: Average (Rs.) | C58: =AVERAGE(C56:E56) -> 51.071778 | D58: Cost per pallet per day
B62: Kothur
G63: =MAX(G65:G215) -> 286681 | R63: =SUM(R65:R69) -> 1245453.5 | W63: =SUM(W65:W69) -> 79600748 | X63: =AVERAGE(X65:X70) -> 67.409817
B64: Date | C64: Month | D64: Opening | E64: Inward | F64: Outward | G64: Closing | H64: Change | I64: Average Inventory Level (AIL) | M64: Start | N64: End | O64: Days | P64: Opening | Q64: Change average | R64: Closing | S64: AIL | T64: Pallets | U64: Rental Cost+ CAPEX | V64: Operational Cost | W64: Total | X64: Rs./pallet/day | Y64: Utilisation
B65: 45566 | C65: =MONTH(B65) -> 10 | D65: 252271 | E65: 3224 | F65: 5859 | G65: =D65+E65-F65 -> 249636 | H65: =G65-D65 -> -2635 | I65: =(D65+G65)/2 -> 250953.5 | L65: =MONTH(M65) -> 10 | M65: 45566 | N65: 45596 | O65: =_xlfn.DAYS(N65,M65)+1 -> 31 | P65: =AVERAGEIF($C$65:$C$215,L65,$D$65:$D$215) -> 244840.58 | Q65: =AVERAGEIF($C$65:$C$215,L65,$H$65:$H$215) -> 764.70968 | R65: =AVERAGEIF($C$65:$C$215,$L65,$G$65:$G$215) -> 245605.29 | S65: =AVERAGEIF($C$65:$C$215,$L65,$I$65:$I$215) -> 245222.94 | T65: =S65/31 -> 7910.4173 | U65: =C7+(C8+E36)/12 -> 9155898.8 | V65: =(E19+E26+E32+C42)/12 -> 6764250.8 | W65: =U65+V65 -> 15920150 | X65: =W65/(S65/31)/O65 -> 64.921128 | Y65: =R65/$G$63 -> 0.8567198
B66: 45567 | C66: =MONTH(B66) -> 10 | D66: =G65 -> 249636 | E66: 11284 | F66: 9083 | G66: =D66+E66-F66 -> 251837 | H66: =G66-D66 -> 2201 | I66: =(D66+G66)/2 -> 250736.5 | L66: =MONTH(M66) -> 11 | M66: =N65+1 -> 45597 | N66: =EOMONTH(M66,0.5) -> 45626 | O66: =_xlfn.DAYS(N66,M66)+1 -> 30 | P66: =AVERAGEIF($C$65:$C$215,L66,$D$65:$D$215) -> 265209.53 | Q66: =AVERAGEIF($C$65:$C$215,L66,$H$65:$H$215) -> -2426.6667 | R66: =AVERAGEIF($C$65:$C$215,L66,$G$65:$G$215) -> 262782.87 | S66: =AVERAGEIF($C$65:$C$215,$L66,$I$65:$I$215) -> 263996.2 | T66: =S66/31 -> 8516.0065 | U66: =U65 -> 9155898.8 | V66: =V65 -> 6764250.8 | W66: =U66+V66 -> 15920150 | X66: =W66/(S66/31)/O66 -> 62.314614 | Y66: =R66/$G$63 -> 0.91663859
B67: 45568 | C67: =MONTH(B67) -> 10 | D67: =G66 -> 251837 | E67: 13454 | F67: 7223 | G67: =D67+E67-F67 -> 258068 | H67: =G67-D67 -> 6231 | I67: =(D67+G67)/2 -> 254952.5 | L67: =MONTH(M67) -> 12 | M67: =N66+1 -> 45627 | N67: =EOMONTH(M67,0.5) -> 45657 | O67: =_xlfn.DAYS(N67,M67)+1 -> 31 | P67: =AVERAGEIF($C$65:$C$215,L67,$D$65:$D$215) -> 236016.74 | Q67: =AVERAGEIF($C$65:$C$215,L67,$H$65:$H$215) -> 1390.9032 | R67: =AVERAGEIF($C$65:$C$215,L67,$G$65:$G$215) -> 237407.65 | S67: =AVERAGEIF($C$65:$C$215,$L67,$I$65:$I$215) -> 236712.19 | T67: =S67/31 -> 7635.8772 | U67: =U66 -> 9155898.8 | V67: =V66 -> 6764250.8 | W67: =U67+V67 -> 15920150 | X67: =W67/(S67/31)/O67 -> 67.2553 | Y67: =R67/$G$63 -> 0.8281248
B68: 45569 | C68: =MONTH(B68) -> 10 | D68: =G67 -> 258068 | E68: 13609 | F68: 4464 | G68: =D68+E68-F68 -> 267213 | H68: =G68-D68 -> 9145 | I68: =(D68+G68)/2 -> 262640.5 | L68: =MONTH(M68) -> 1 | M68: =N67+1 -> 45658 | N68: =EOMONTH(M68,0.5) -> 45688 | O68: =_xlfn.DAYS(N68,M68)+1 -> 31 | P68: =AVERAGEIF($C$65:$C$215,L68,$D$65:$D$215) -> 250909.55 | Q68: =AVERAGEIF($C$65:$C$215,L68,$H$65:$H$215) -> 310.70968 | R68: =AVERAGEIF($C$65:$C$215,L68,$G$65:$G$215) -> 251220.26 | S68: =AVERAGEIF($C$65:$C$215,$L68,$I$65:$I$215) -> 251064.9 | T68: =S68/31 -> 8098.8678 | U68: =U67 -> 9155898.8 | V68: =V67 -> 6764250.8 | W68: =U68+V68 -> 15920150 | X68: =W68/(S68/31)/O68 -> 63.410494 | Y68: =R68/$G$63 -> 0.87630592
B69: 45570 | C69: =MONTH(B69) -> 10 | D69: =G68 -> 267213 | E69: 8804 | F69: 8463 | G69: =D69+E69-F69 -> 267554 | H69: =G69-D69 -> 341 | I69: =(D69+G69)/2 -> 267383.5 | L69: =MONTH(M69) -> 2 | M69: =N68+1 -> 45689 | N69: =EOMONTH(M69,0.5) -> 45716 | O69: =_xlfn.DAYS(N69,M69)+1 -> 28 | P69: =AVERAGEIF($C$65:$C$215,L69,$D$65:$D$215) -> 249451.14 | Q69: =AVERAGEIF($C$65:$C$215,L69,$H$65:$H$215) -> -1013.6786 | R69: =AVERAGEIF($C$65:$C$215,L69,$G$65:$G$215) -> 248437.46 | S69: =AVERAGEIF($C$65:$C$215,$L69,$I$65:$I$215) -> 248944.3 | T69: =S69/31 -> 8030.4614 | U69: =U68 -> 9155898.8 | V69: =V68 -> 6764250.8 | W69: =U69+V69 -> 15920150 | X69: =W69/(S69/31)/O69 -> 70.802504 | Y69: =R69/$G$63 -> 0.86659899
B70: 45571 | C70: =MONTH(B70) -> 10 | D70: =G69 -> 267554 | E70: 961 | F70: 7440 | G70: =D70+E70-F70 -> 261075 | H70: =G70-D70 -> -6479 | I70: =(D70+G70)/2 -> 264314.5 | L70: 3 | M70: 45717 | N70: 45747 | O70: =_xlfn.DAYS(N70,M70)+1 -> 31 | P70: 227544 | Q70: =R70-P70 -> -34781 | R70: =190624+2139 -> 192763 | S70: =AVERAGE(R70,P70) -> 210153.5 | T70: =S70/31 -> 6779.1452 | U70: =U69 -> 9155898.8 | V70: =V69 -> 6764250.8 | W70: =U70+V70 -> 15920150 | X70: =W70/(S70/31)/O70 -> 75.754863 | Y70: =R70/$G$63 -> 0.67239545
B71: 45572 | C71: =MONTH(B71) -> 10 | D71: =G70 -> 261075 | E71: 3596 | F71: 9672 | G71: =D71+E71-F71 -> 254999 | H71: =G71-D71 -> -6076 | I71: =(D71+G71)/2 -> 258037 | Y71: =R71/$G$63 -> 0
B72: 45573 | C72: =MONTH(B72) -> 10 | D72: =G71 -> 254999 | E72: 5627 | F72: 10540 | G72: =D72+E72-F72 -> 250086 | H72: =G72-D72 -> -4913 | I72: =(D72+G72)/2 -> 252542.5
B73: 45574 | C73: =MONTH(B73) -> 10 | D73: =G72 -> 250086 | E73: 10258 | F73: 15020 | G73: =D73+E73-F73 -> 245324 | H73: =G73-D73 -> -4762 | I73: =(D73+G73)/2 -> 247705
B74: 45575 | C74: =MONTH(B74) -> 10 | D74: =G73 -> 245324 | E74: 8804 | F74: 10168 | G74: =D74+E74-F74 -> 243960 | H74: =G74-D74 -> -1364 | I74: =(D74+G74)/2 -> 244642
B75: 45576 | C75: =MONTH(B75) -> 10 | D75: =G74 -> 243960 | E75: 4309 | F75: 8060 | G75: =D75+E75-F75 -> 240209 | H75: =G75-D75 -> -3751 | I75: =(D75+G75)/2 -> 242084.5
B76: 45577 | C76: =MONTH(B76) -> 10 | D76: =G75 -> 240209 | E76: 2604 | F76: 13361 | G76: =D76+E76-F76 -> 229452 | H76: =G76-D76 -> -10757 | I76: =(D76+G76)/2 -> 234830.5
B77: 45578 | C77: =MONTH(B77) -> 10 | D77: =G76 -> 229452 | E77: 6386 | F77: 10385 | G77: =D77+E77-F77 -> 225453 | H77: =G77-D77 -> -3999 | I77: =(D77+G77)/2 -> 227452.5
B78: 45579 | C78: =MONTH(B78) -> 10 | D78: =G77 -> 225453 | E78: 5053 | F78: 12462 | G78: =D78+E78-F78 -> 218044 | H78: =G78-D78 -> -7409 | I78: =(D78+G78)/2 -> 221748.5
B79: 45580 | C79: =MONTH(B79) -> 10 | D79: =G78 -> 218044 | E79: 4092 | F79: 11346 | G79: =D79+E79-F79 -> 210790 | H79: =G79-D79 -> -7254 | I79: =(D79+G79)/2 -> 214417
B80: 45581 | C80: =MONTH(B80) -> 10 | D80: =G79 -> 210790 | E80: 16113 | F80: 7626 | G80: =D80+E80-F80 -> 219277 | H80: =G80-D80 -> 8487 | I80: =(D80+G80)/2 -> 215033.5
B81: 45582 | C81: =MONTH(B81) -> 10 | D81: =G80 -> 219277 | E81: 12245 | F81: 10974 | G81: =D81+E81-F81 -> 220548 | H81: =G81-D81 -> 1271 | I81: =(D81+G81)/2 -> 219912.5
B82: 45583 | C82: =MONTH(B82) -> 10 | D82: =G81 -> 220548 | E82: 14446 | F82: 11966 | G82: =D82+E82-F82 -> 223028 | H82: =G82-D82 -> 2480 | I82: =(D82+G82)/2 -> 221788
B83: 45584 | C83: =MONTH(B83) -> 10 | D83: =G82 -> 223028 | E83: 12769 | F83: 9337 | G83: =D83+E83-F83 -> 226460 | H83: =G83-D83 -> 3432 | I83: =(D83+G83)/2 -> 224744
... B214: 45715 | C214: =MONTH(B214) -> 2 | D214: =G213 -> 221749 | E214: 8432 | F214: 2637 | G214: =D214+E214-F214 -> 227544 | H214: =G214-D214 -> 5795 | I214: =(D214+G214)/2 -> 224646.5
B215: 45716 | C215: =MONTH(B215) -> 2 | D215: =G214 -> 227544 | G215: =D215+E215-F215 -> 227544 | H215: =G215-D215 -> 0 | I215: =(D215+G215)/2 -> 227544

Sheet Sheet5

Sheet Day wise Churning
B1: Kothur
G2: =MAX(G4:G154) -> 286681 | R2: =SUM(R4:R8) -> 1245453.5 | V2: =SUM(V4:V8) -> 69319991 | W2: =AVERAGE(W4:W8) -> 57.250118
B3: Date | C3: Month | D3: Opening | E3: Inward | F3: Outward | G3: Closing | H3: Change | I3: Average Inventory | M3: Start | N3: End | O3: Days | P3: Opening | Q3: Change average | R3: Closing | S3: Average Inventory Level | T3: Rental Cost | U3: Operational Cost | V3: Total | W3: Rs./pallet/day
B4: 45566 | C4: =MONTH(B4) -> 10 | D4: 252271 | E4: 3224 | F4: 5859 | G4: =D4+E4-F4 -> 249636 | H4: =G4-D4 -> -2635 | I4: =(D4+G4)/2 -> 250953.5 | L4: =MONTH(M4) -> 10 | M4: 45566 | N4: 45596 | O4: =_xlfn.DAYS(N4,M4)+1 -> 31 | P4: =AVERAGEIF($C$4:$C$154,L4,$D$4:$D$154) -> 244840.58 | Q4: =AVERAGEIF($C$4:$C$154,L4,$H$4:$H$154) -> 764.70968 | R4: =AVERAGEIF($C$4:$C$154,L4,$G$4:$G$154) -> 245605.29 | S4: =AVERAGEIF($C$4:$C$154,L4,$I$4:$I$154) -> 245222.94 | T4: =Inputs!F26 -> 7099747.5 | U4: =('Kothur Reference'!E19+'Kothur Reference'!E26+'Kothur Reference'!E32+'Kothur Reference'!C42)/12 -> 6764250.8 | V4: =T4+U4 -> 13863998 | W4: =V4/(S4/31)/O4 -> 56.536303
B5: 45567 | C5: =MONTH(B5) -> 10 | D5: =G4 -> 249636 | E5: 11284 | F5: 9083 | G5: =D5+E5-F5 -> 251837 | H5: =G5-D5 -> 2201 | I5: =(D5+G5)/2 -> 250736.5 | L5: =MONTH(M5) -> 11 | M5: =N4+1 -> 45597 | N5: =EOMONTH(M5,0.5) -> 45626 | O5: =_xlfn.DAYS(N5,M5)+1 -> 30 | P5: =AVERAGEIF($C$4:$C$154,L5,$D$4:$D$154) -> 265209.53 | Q5: =AVERAGEIF($C$4:$C$154,L5,$H$4:$H$154) -> -2426.6667 | R5: =AVERAGEIF($C$4:$C$154,L5,$G$4:$G$154) -> 262782.87 | S5: =AVERAGEIF($C$4:$C$154,L5,$I$4:$I$154) -> 263996.2 | T5: =T4 -> 7099747.5 | U5: =U4 -> 6764250.8 | V5: =T5+U5 -> 13863998 | W5: =V5/(S5/31)/O5 -> 54.266431
B6: 45568 | C6: =MONTH(B6) -> 10 | D6: =G5 -> 251837 | E6: 13454 | F6: 7223 | G6: =D6+E6-F6 -> 258068 | H6: =G6-D6 -> 6231 | I6: =(D6+G6)/2 -> 254952.5 | L6: =MONTH(M6) -> 12 | M6: =N5+1 -> 45627 | N6: =EOMONTH(M6,0.5) -> 45657 | O6: =_xlfn.DAYS(N6,M6)+1 -> 31 | P6: =AVERAGEIF($C$4:$C$154,L6,$D$4:$D$154) -> 236016.74 | Q6: =AVERAGEIF($C$4:$C$154,L6,$H$4:$H$154) -> 1390.9032 | R6: =AVERAGEIF($C$4:$C$154,L6,$G$4:$G$154) -> 237407.65 | S6: =AVERAGEIF($C$4:$C$154,L6,$I$4:$I$154) -> 236712.19 | T6: =T5 -> 7099747.5 | U6: =U5 -> 6764250.8 | V6: =T6+U6 -> 13863998 | W6: =V6/(S6/31)/O6 -> 58.569008
B7: 45569 | C7: =MONTH(B7) -> 10 | D7: =G6 -> 258068 | E7: 13609 | F7: 4464 | G7: =D7+E7-F7 -> 267213 | H7: =G7-D7 -> 9145 | I7: =(D7+G7)/2 -> 262640.5 | L7: =MONTH(M7) -> 1 | M7: =N6+1 -> 45658 | N7: =EOMONTH(M7,0.5) -> 45688 | O7: =_xlfn.DAYS(N7,M7)+1 -> 31 | P7: =AVERAGEIF($C$4:$C$154,L7,$D$4:$D$154) -> 250909.55 | Q7: =AVERAGEIF($C$4:$C$154,L7,$H$4:$H$154) -> 310.70968 | R7: =AVERAGEIF($C$4:$C$154,L7,$G$4:$G$154) -> 251220.26 | S7: =AVERAGEIF($C$4:$C$154,L7,$I$4:$I$154) -> 251064.9 | T7: =T6 -> 7099747.5 | U7: =U6 -> 6764250.8 | V7: =T7+U7 -> 13863998 | W7: =V7/(S7/31)/O7 -> 55.220774
B8: 45570 | C8: =MONTH(B8) -> 10 | D8: =G7 -> 267213 | E8: 8804 | F8: 8463 | G8: =D8+E8-F8 -> 267554 | H8: =G8-D8 -> 341 | I8: =(D8+G8)/2 -> 267383.5 | L8: =MONTH(M8) -> 2 | M8: =N7+1 -> 45689 | N8: =EOMONTH(M8,0.5) -> 45716 | O8: =_xlfn.DAYS(N8,M8)+1 -> 28 | P8: =AVERAGEIF($C$4:$C$154,L8,$D$4:$D$154) -> 249451.14 | Q8: =AVERAGEIF($C$4:$C$154,L8,$H$4:$H$154) -> -1013.6786 | R8: =AVERAGEIF($C$4:$C$154,L8,$G$4:$G$154) -> 248437.46 | S8: =AVERAGEIF($C$4:$C$154,L8,$I$4:$I$154) -> 248944.3 | T8: =T7 -> 7099747.5 | U8: =U7 -> 6764250.8 | V8: =T8+U8 -> 13863998 | W8: =V8/(S8/31)/O8 -> 61.658076
B9: 45571 | C9: =MONTH(B9) -> 10 | D9: =G8 -> 267554 | E9: 961 | F9: 7440 | G9: =D9+E9-F9 -> 261075 | H9: =G9-D9 -> -6479 | I9: =(D9+G9)/2 -> 264314.5 | L9: =MONTH(M9) -> 3 | M9: =N8+1 -> 45717 | N9: =EOMONTH(M9,0.5) -> 45747 | O9: =_xlfn.DAYS(N9,M9)+1 -> 31 | P9: =AVERAGEIF($C$4:$C$154,L9,$D$4:$D$154) -> #DIV/0! | Q9: =AVERAGEIF($C$4:$C$154,L9,$H$4:$H$154) -> #DIV/0! | R9: =AVERAGEIF($C$4:$C$154,L9,$G$4:$G$154) -> #DIV/0!
B10: 45572 | C10: =MONTH(B10) -> 10 | D10: =G9 -> 261075 | E10: 3596 | F10: 9672 | G10: =D10+E10-F10 -> 254999 | H10: =G10-D10 -> -6076 | I10: =(D10+G10)/2 -> 258037
B11: 45573 | C11: =MONTH(B11) -> 10 | D11: =G10 -> 254999 | E11: 5627 | F11: 10540 | G11: =D11+E11-F11 -> 250086 | H11: =G11-D11 -> -4913 | I11: =(D11+G11)/2 -> 252542.5
B12: 45574 | C12: =MONTH(B12) -> 10 | D12: =G11 -> 250086 | E12: 10258 | F12: 15020 | G12: =D12+E12-F12 -> 245324 | H12: =G12-D12 -> -4762 | I12: =(D12+G12)/2 -> 247705
B13: 45575 | C13: =MONTH(B13) -> 10 | D13: =G12 -> 245324 | E13: 8804 | F13: 10168 | G13: =D13+E13-F13 -> 243960 | H13: =G13-D13 -> -1364 | I13: =(D13+G13)/2 -> 244642
B14: 45576 | C14: =MONTH(B14) -> 10 | D14: =G13 -> 243960 | E14: 4309 | F14: 8060 | G14: =D14+E14-F14 -> 240209 | H14: =G14-D14 -> -3751 | I14: =(D14+G14)/2 -> 242084.5
B15: 45577 | C15: =MONTH(B15) -> 10 | D15: =G14 -> 240209 | E15: 2604 | F15: 13361 | G15: =D15+E15-F15 -> 229452 | H15: =G15-D15 -> -10757 | I15: =(D15+G15)/2 -> 234830.5
B16: 45578 | C16: =MONTH(B16) -> 10 | D16: =G15 -> 229452 | E16: 6386 | F16: 10385 | G16: =D16+E16-F16 -> 225453 | H16: =G16-D16 -> -3999 | I16: =(D16+G16)/2 -> 227452.5
B17: 45579 | C17: =MONTH(B17) -> 10 | D17: =G16 -> 225453 | E17: 5053 | F17: 12462 | G17: =D17+E17-F17 -> 218044 | H17: =G17-D17 -> -7409 | I17: =(D17+G17)/2 -> 221748.5
B18: 45580 | C18: =MONTH(B18) -> 10 | D18: =G17 -> 218044 | E18: 4092 | F18: 11346 | G18: =D18+E18-F18 -> 210790 | H18: =G18-D18 -> -7254 | I18: =(D18+G18)/2 -> 214417
B19: 45581 | C19: =MONTH(B19) -> 10 | D19: =G18 -> 210790 | E19: 16113 | F19: 7626 | G19: =D19+E19-F19 -> 219277 | H19: =G19-D19 -> 8487 | I19: =(D19+G19)/2 -> 215033.5
B20: 45582 | C20: =MONTH(B20) -> 10 | D20: =G19 -> 219277 | E20: 12245 | F20: 10974 | G20: =D20+E20-F20 -> 220548 | H20: =G20-D20 -> 1271 | I20: =(D20+G20)/2 -> 219912.5
B21: 45583 | C21: =MONTH(B21) -> 10 | D21: =G20 -> 220548 | E21: 14446 | F21: 11966 | G21: =D21+E21-F21 -> 223028 | H21: =G21-D21 -> 2480 | I21: =(D21+G21)/2 -> 221788
... B153: 45715 | C153: =MONTH(B153) -> 2 | D153: =G152 -> 221749 | E153: 8432 | F153: 2637 | G153: =D153+E153-F153 -> 227544 | H153: =G153-D153 -> 5795 | I153: =(D153+G153)/2 -> 224646.5
B154: 45716 | C154: =MONTH(B154) -> 2 | D154: =G153 -> 227544 | G154: =D154+E154-F154 -> 227544 | H154: =G154-D154 -> 0 | I154: =(D154+G154)/2 -> 227544

Sheet Tax and WACC
A3: Company | B3: Tax Rate | C3: WACC
A4: PEL | B4: 0.2517 | C4: =[1]Group!$E$6 -> 0.2
A5: PEPPL | B5: 0.2912 | C5: =[1]Group!$F$6 -> 0.13314816
A6: PSPTL | B6: 0.2517 | C6: =[1]Group!$G$6 -> 0.2
A7: PEGEPL | B7: 0.1718 | C7: =[1]Group!$H$6 -> 0.13103113
A8: PEIPL | B8: 0.1718 | C8: =[1]Group!$I$6 -> 0.090338275
A9: PPGPL | B9: 0.2517 | C9: =[1]Group!$J$6 -> 0.2
A10: PPZPL | B10: 0.2517 | C10: =[1]Group!$K$6 -> 0.2
